Workbook

Sheet Overview & Methodology
A1: Financial audit - final 27 measures, FY2021-FY2025
A3: Course: Introduction to Business Finance, IBA Karachi. Instructor: Dr. Noureen Ayaz. Group members / IDs: to be completed by students.
A4: Five companies: KOHC, LUCK, DGKC, MLCF and FCCL. Official audited standalone / unconsolidated accounts. Financial amounts are PKR million unless stated.
A6: CURRENT: 27 Scope, 27 Calculations, 27 Industry, 27 Published, Balance Practices, EV Inputs and Reconciliation Guide. These define and verify the final submission.
A7: PRESERVED EVIDENCE: PSX Prices, Share Basis, Corporate Actions, Price Evidence, source register, Input Review, Opening Balances and the complete forensic investigation.
A8: ARCHIVED: company ratio tables and Industry Comparison use the prior 33-measure model. Published Ratio Reconciliation, Ratio Verification, Full Audit Summary and Archived Methodology retain historical results. Do not use them as current headline calculations.
A10: Current controls: 675 company-year results, 135 sample means, 422 balance tests and 455 published observations. 437 published values are numerically reconstructed; 18 remain unreproduced. A fit does not establish an expressly disclosed issuer formula.
A11: Sample means give equal weight to available numeric observations, exclude n/m and show valid counts in 27 Industry. Signed negative source amounts remain preserved. Genuine zeros remain numeric.
A13: Common formula and balance decisions
A14: Average opening/closing total inventory and net trade receivables. Closing PPE including CWIP, total assets, common equity and invested capital. FY2020 audited openings retained.
A15: EBIT = pre-levy/pre-tax profit + expensed interest. Non-interest finance charges stay expenses. ROIC uses actual uncapped audited ETR. Cash equivalents follow audited component notes before borrowing netting and after restricted-cash exclusions.
A16: Debt ratio uses all liabilities. D/E and debt-to-capital use interest-bearing principal and leases. EV adds identified other financial claims and uses book debt as an explicit market-value approximation.
... A19: Final 27-measure definitions
A21: ID | B21: Category | C21: Measure | D21: Requirement | E21: Origin | F21: Formula | G21: Short method note | H21: Basis detail
A22: 1 | B22: Liquidity | C22: Current Ratio | D22: Mandatory | E22: Table 4.2 | F22: Current assets / Current liabilities | G22: Closing current assets and liabilities. | H22: Period/share basis
A23: 2 | B23: Liquidity | C23: Quick Ratio | D23: Mandatory | E23: Table 4.2 | F23: (Current assets - Inventory) / Current liabilities | G23: Stores and stock excluded from current assets. | H23: Period/share basis
A24: 3 | B24: Liquidity | C24: Cash Ratio | D24: Mandatory | E24: University guideline | F24: Cash and equivalents / Current liabilities | G24: Available cash equivalents; borrowings remain in liabilities. | H24: Period/share basis
A25: 4 | B25: Liquidity | C25: Net Working Capital | D25: Additional | E25: Class PPT | F25: Current assets - Current liabilities | G25: Closing balances; signed working capital retained. | H25: Period/share basis
A26: 5 | B26: Asset Management | C26: Inventory Turnover | D26: Mandatory | E26: Table 4.2 | F26: COGS / Average inventory | G26: Average opening and closing stores and stock. | H26: Average
A27: 6 | B27: Asset Management | C27: Receivables Turnover | D27: Additional | E27: Class PPT | F27: Sales / Average trade receivables | G27: Average opening and closing net trade receivables. | H27: Average
A28: 7 | B28: Asset Management | C28: Days Inventory Outstanding | D28: Additional | E28: Class PPT | F28: 365 / Inventory turnover | G28: Average inventory; 365 days used. | H28: Average
A29: 8 | B29: Asset Management | C29: Days Sales Outstanding | D29: Mandatory | E29: Table 4.2 | F29: Receivables / (Annual sales / 365) | G29: Average receivables; sales proxy; 365 days. | H29: Average
A30: 9 | B30: Asset Management | C30: Fixed Asset Turnover | D30: Mandatory | E30: Table 4.2 | F30: Sales / Net fixed assets | G30: Closing net PPE, including CWIP. | H30: Closing
A31: 10 | B31: Asset Management | C31: Total Asset Turnover | D31: Mandatory | E31: Table 4.2 | F31: Sales / Total assets | G31: Closing total assets used consistently. | H31: Closing
A32: 11 | B32: Debt Management | C32: Debt Ratio | D32: Mandatory | E32: University guideline | F32: Total liabilities / Total assets | G32: All liabilities, including operating payables. | H32: Closing
A33: 12 | B33: Debt Management | C33: Debt-to-Equity Ratio | D33: Mandatory | E33: University guideline | F33: Interest-bearing debt / Common equity | G33: Interest-bearing principal and leases only. | H33: Closing
... A48: 27 | B48: Market Value | C48: Enterprise Value/EBITDA | D48: Additional | E48: Table 4.2 | F48: Enterprise value / (EBIT + D&A) | G48: Book debt approximates market financing value. | H48: Period/share basis
A52: Grouped reconciliation explanations
A53: Inventory and receivables use opening/closing averages, including audited FY2020 openings for FY2021. Assets, net PPE, equity and invested capital use closing balances for every company. Company-published closing or average variants are reconstructed separately. An isolated numerical fit does not confirm an issuer policy.
A54: Inventory includes stores, spares and stock-in-trade. PPE includes CWIP. Cash includes only audited qualifying equivalents, excludes pledged balances, and is gross of borrowing netting. Debt ratio includes all liabilities; D/E and debt-to-capital use interest-bearing principal and leases. MLCF freight reclassification changes COGS and gross margin without changing operating profit.
A55: EBIT = profit before levy/tax + expensed interest. Other recognized income stays included. Non-interest finance charges stay expenses. TIE uses expensed interest, not cash paid. ROIC uses this EBIT, actual uncapped audited ETR and closing IBD + equity. LUCK published ROE is numerically reproduced using comprehensive income; this project consistently uses net income.
A56: Market ratios use official PSX closes at year-end or the last preceding trading day. KOHC split trading began 25-Aug-2025, after FY2025; its FY2025 price is not divided by five. LUCK split trading began 28-Apr-2025. EPS, DPS and share counts retain compatible bases. Some published ratios use different or unconfirmed prices, share denominators or tangible-asset definitions.
A57: 437 of 455 current published observations are numerically reconstructed; this does not prove expressly disclosed issuer formulas. Eight FCCL asset-turnover observations conflict with annual sales/assets and the same report DuPont table. Five FCCL P/E, three FCCL DSO, one FCCL FY2025 TIE and one DGKC FY2021 cash ratio have unconfirmed exact published bases. All 18 remain disclosed below.
A60: Reconciliation Guide lists the exact numerator, denominator, project result and published value for each remaining case, with source references and confirmation status. Forensic 63 and Forensic Tests preserve every previous investigation.
A62: Prior confirmed input corrections are retained: LUCK FY2020 deferred tax 5,167.561m (note24.2), and FY2021 D&A 4,309.413m including amortization10.653m. Historical source values remain in the archived input model.
A64: References: supplied Project Guidelines pp5-6; Brigham & Houston Chapter4 Table4.2; class Chapter04 slides2-8; original audited annual reports and PSX disclosures. Secondary investigative material remains internal and supplies no authoritative financial input.

Sheet Published Ratio Reconciliation
A1: ARCHIVED - original published-ratio reconstruction record
A2: 544 official-source observations; baseline 44 financial failures and 10 market failures retained in column K. Numeric reproduction and officially disclosed formulas remain distinct.
A4: Company | B4: Published measure | C4: FY | D4: Published | E4: Standardized | F4: Reconstruction | G4: Convention tested | H4: Numeric comparison | I4: Investigation finding | J4: Official report / page | K4: Prior status | L4: Finding category | M4: Std minus published | N4: Reconstruction minus published | O4: Precision | P4: Official-glossary diagnostic | Q4: Diagnostic finding (not a standardized formula)
A5: KOHC | B5: Current ratio | C5: FY2021 | D5: 1.3 | E5: =KOHC!D138 -> 1.3006447 | F5: =KOHC!D36/KOHC!D61 -> 1.3006447 | G5: Standard definition | H5: =IF(AND(ISNUMBER(D5),ISNUMBER(F5)),IF(ROUND(D5,O5)=ROUND(F5,O5),"Reproduced to precision","Unresolved published value"),"Not comparable") -> Reproduced to precision | I5: Tested the source-based convention shown in G against official published precision. Unmatched values remain unresolved; neither the standardized method nor the financial inputs were altered to force agreement. | J5: FY2025 AR p53 "Key financial data for the last six years" (per-share items split-adjusted 5:1) | K5: Agrees (same convention) | L5: Source comparison | M5: =IF(ISNUMBER(E5),E5-D5,"n/m") -> 0.00064466914 | N5: =IF(ISNUMBER(F5),F5-D5,"n/m") -> 0.00064466914 | O5: 2
A6: KOHC | B6: Current ratio | C6: FY2022 | D6: 1.87 | E6: =KOHC!E138 -> 1.8735085 | F6: =KOHC!E36/KOHC!E61 -> 1.8735085 | G6: Standard definition | H6: =IF(AND(ISNUMBER(D6),ISNUMBER(F6)),IF(ROUND(D6,O6)=ROUND(F6,O6),"Reproduced to precision","Unresolved published value"),"Not comparable") -> Reproduced to precision | I6: Tested the source-based convention shown in G against official published precision. Unmatched values remain unresolved; neither the standardized method nor the financial inputs were altered to force agreement. | J6: FY2025 AR p53 "Key financial data for the last six years" (per-share items split-adjusted 5:1) | K6: Agrees (same convention) | L6: Source comparison | M6: =IF(ISNUMBER(E6),E6-D6,"n/m") -> 0.0035085276 | N6: =IF(ISNUMBER(F6),F6-D6,"n/m") -> 0.0035085276 | O6: 2
A7: KOHC | B7: Current ratio | C7: FY2023 | D7: 2.31 | E7: =KOHC!F138 -> 2.3115705 | F7: =KOHC!F36/KOHC!F61 -> 2.3115705 | G7: Standard definition | H7: =IF(AND(ISNUMBER(D7),ISNUMBER(F7)),IF(ROUND(D7,O7)=ROUND(F7,O7),"Reproduced to precision","Unresolved published value"),"Not comparable") -> Reproduced to precision | I7: Tested the source-based convention shown in G against official published precision. Unmatched values remain unresolved; neither the standardized method nor the financial inputs were altered to force agreement. | J7: FY2025 AR p53 "Key financial data for the last six years" (per-share items split-adjusted 5:1) | K7: Agrees (same convention) | L7: Source comparison | M7: =IF(ISNUMBER(E7),E7-D7,"n/m") -> 0.0015705155 | N7: =IF(ISNUMBER(F7),F7-D7,"n/m") -> 0.0015705155 | O7: 2
A8: KOHC | B8: Current ratio | C8: FY2024 | D8: 2.9 | E8: =KOHC!G138 -> 2.9031591 | F8: =KOHC!G36/KOHC!G61 -> 2.9031591 | G8: Standard definition | H8: =IF(AND(ISNUMBER(D8),ISNUMBER(F8)),IF(ROUND(D8,O8)=ROUND(F8,O8),"Reproduced to precision","Unresolved published value"),"Not comparable") -> Reproduced to precision | I8: Tested the source-based convention shown in G against official published precision. Unmatched values remain unresolved; neither the standardized method nor the financial inputs were altered to force agreement. | J8: FY2025 AR p53 "Key financial data for the last six years" (per-share items split-adjusted 5:1) | K8: Agrees (same convention) | L8: Source comparison | M8: =IF(ISNUMBER(E8),E8-D8,"n/m") -> 0.003159053 | N8: =IF(ISNUMBER(F8),F8-D8,"n/m") -> 0.003159053 | O8: 2
A9: KOHC | B9: Current ratio | C9: FY2025 | D9: 3.31 | E9: =KOHC!H138 -> 3.3112487 | F9: =KOHC!H36/KOHC!H61 -> 3.3112487 | G9: Standard definition | H9: =IF(AND(ISNUMBER(D9),ISNUMBER(F9)),IF(ROUND(D9,O9)=ROUND(F9,O9),"Reproduced to precision","Unresolved published value"),"Not comparable") -> Reproduced to precision | I9: Tested the source-based convention shown in G against official published precision. Unmatched values remain unresolved; neither the standardized method nor the financial inputs were altered to force agreement. | J9: FY2025 AR p53 "Key financial data for the last six years" (per-share items split-adjusted 5:1) | K9: Agrees (same convention) | L9: Source comparison | M9: =IF(ISNUMBER(E9),E9-D9,"n/m") -> 0.0012486872 | N9: =IF(ISNUMBER(F9),F9-D9,"n/m") -> 0.0012486872 | O9: 2
A10: KOHC | B10: Quick ratio | C10: FY2021 | D10: 0.75 | E10: =KOHC!D139 -> 0.74816044 | F10: =(KOHC!D36-KOHC!D65)/KOHC!D61 -> 0.74816044 | G10: Standard definition | H10: =IF(AND(ISNUMBER(D10),ISNUMBER(F10)),IF(ROUND(D10,O10)=ROUND(F10,O10),"Reproduced to precision","Unresolved published value"),"Not comparable") -> Reproduced to precision | I10: Tested the source-based convention shown in G against official published precision. Unmatched values remain unresolved; neither the standardized method nor the financial inputs were altered to force agreement. | J10: FY2025 AR p53 "Key financial data for the last six years" (per-share items split-adjusted 5:1) | K10: Agrees (same convention) | L10: Source comparison | M10: =IF(ISNUMBER(E10),E10-D10,"n/m") -> -0.0018395614 | N10: =IF(ISNUMBER(F10),F10-D10,"n/m") -> -0.0018395614 | O10: 2
A11: KOHC | B11: Quick ratio | C11: FY2022 | D11: 1.28 | E11: =KOHC!E139 -> 1.275807 | F11: =(KOHC!E36-KOHC!E65)/KOHC!E61 -> 1.275807 | G11: Standard definition | H11: =IF(AND(ISNUMBER(D11),ISNUMBER(F11)),IF(ROUND(D11,O11)=ROUND(F11,O11),"Reproduced to precision","Unresolved published value"),"Not comparable") -> Reproduced to precision | I11: Tested the source-based convention shown in G against official published precision. Unmatched values remain unresolved; neither the standardized method nor the financial inputs were altered to force agreement. | J11: FY2025 AR p53 "Key financial data for the last six years" (per-share items split-adjusted 5:1) | K11: Agrees (same convention) | L11: Source comparison | M11: =IF(ISNUMBER(E11),E11-D11,"n/m") -> -0.004192989 | N11: =IF(ISNUMBER(F11),F11-D11,"n/m") -> -0.004192989 | O11: 2
A12: KOHC | B12: Quick ratio | C12: FY2023 | D12: 1.54 | E12: =KOHC!F139 -> 1.539211 | F12: =(KOHC!F36-KOHC!F65)/KOHC!F61 -> 1.539211 | G12: Standard definition | H12: =IF(AND(ISNUMBER(D12),ISNUMBER(F12)),IF(ROUND(D12,O12)=ROUND(F12,O12),"Reproduced to precision","Unresolved published value"),"Not comparable") -> Reproduced to precision | I12: Tested the source-based convention shown in G against official published precision. Unmatched values remain unresolved; neither the standardized method nor the financial inputs were altered to force agreement. | J12: FY2025 AR p53 "Key financial data for the last six years" (per-share items split-adjusted 5:1) | K12: Agrees (same convention) | L12: Source comparison | M12: =IF(ISNUMBER(E12),E12-D12,"n/m") -> -0.00078896994 | N12: =IF(ISNUMBER(F12),F12-D12,"n/m") -> -0.00078896994 | O12: 2
A13: KOHC | B13: Quick ratio | C13: FY2024 | D13: 2.22 | E13: =KOHC!G139 -> 2.2200593 | F13: =(KOHC!G36-KOHC!G65)/KOHC!G61 -> 2.2200593 | G13: Standard definition | H13: =IF(AND(ISNUMBER(D13),ISNUMBER(F13)),IF(ROUND(D13,O13)=ROUND(F13,O13),"Reproduced to precision","Unresolved published value"),"Not comparable") -> Reproduced to precision | I13: Tested the source-based convention shown in G against official published precision. Unmatched values remain unresolved; neither the standardized method nor the financial inputs were altered to force agreement. | J13: FY2025 AR p53 "Key financial data for the last six years" (per-share items split-adjusted 5:1) | K13: Agrees (same convention) | L13: Source comparison | M13: =IF(ISNUMBER(E13),E13-D13,"n/m") -> 5.9339921e-05 | N13: =IF(ISNUMBER(F13),F13-D13,"n/m") -> 5.9339921e-05 | O13: 2
A14: KOHC | B14: Quick ratio | C14: FY2025 | D14: 2.67 | E14: =KOHC!H139 -> 2.6677004 | F14: =(KOHC!H36-KOHC!H65)/KOHC!H61 -> 2.6677004 | G14: Standard definition | H14: =IF(AND(ISNUMBER(D14),ISNUMBER(F14)),IF(ROUND(D14,O14)=ROUND(F14,O14),"Reproduced to precision","Unresolved published value"),"Not comparable") -> Reproduced to precision | I14: Tested the source-based convention shown in G against official published precision. Unmatched values remain unresolved; neither the standardized method nor the financial inputs were altered to force agreement. | J14: FY2025 AR p53 "Key financial data for the last six years" (per-share items split-adjusted 5:1) | K14: Agrees (same convention) | L14: Source comparison | M14: =IF(ISNUMBER(E14),E14-D14,"n/m") -> -0.0022996216 | N14: =IF(ISNUMBER(F14),F14-D14,"n/m") -> -0.0022996216 | O14: 2
A15: KOHC | B15: Inventory turnover | C15: FY2021 | D15: 5.75 | E15: =KOHC!D144 -> 4.8570986 | F15: =KOHC!D84/KOHC!D65 -> 5.7504757 | G15: Sales / closing stores + stock | H15: =IF(AND(ISNUMBER(D15),ISNUMBER(F15)),IF(ROUND(D15,O15)=ROUND(F15,O15),"Reproduced to precision","Unresolved published value"),"Not comparable") -> Reproduced to precision | I15: All five values reproduce using sales / closing total inventory. The class formula remains COGS / average total inventory. This is a mathematical reconstruction using audited inputs; the report does not explicitly state the inventory-turnover formula. | J15: FY2025 AR p53 "Key financial data for the last six years" (per-share items split-adjusted 5:1) | K15: Not reproduced | L15: Published methodology difference (reconstructed) | M15: =IF(ISNUMBER(E15),E15-D15,"n/m") -> -0.8929014 | N15: =IF(ISNUMBER(F15),F15-D15,"n/m") -> 0.00047570459 | O15: 2
A16: KOHC | B16: Inventory turnover | C16: FY2022 | D16: 5.8 | E16: =KOHC!E144 -> 4.6811317 | F16: =KOHC!E84/KOHC!E65 -> 5.7973952 | G16: Sales / closing stores + stock | H16: =IF(AND(ISNUMBER(D16),ISNUMBER(F16)),IF(ROUND(D16,O16)=ROUND(F16,O16),"Reproduced to precision","Unresolved published value"),"Not comparable") -> Reproduced to precision | I16: All five values reproduce using sales / closing total inventory. The class formula remains COGS / average total inventory. This is a mathematical reconstruction using audited inputs; the report does not explicitly state the inventory-turnover formula. | J16: FY2025 AR p53 "Key financial data for the last six years" (per-share items split-adjusted 5:1) | K16: Not reproduced | L16: Published methodology difference (reconstructed) | M16: =IF(ISNUMBER(E16),E16-D16,"n/m") -> -1.1188683 | N16: =IF(ISNUMBER(F16),F16-D16,"n/m") -> -0.0026048458 | O16: 2
A17: KOHC | B17: Inventory turnover | C17: FY2023 | D17: 5.08 | E17: =KOHC!F144 -> 4.2753791 | F17: =KOHC!F84/KOHC!F65 -> 5.0838139 | G17: Sales / closing stores + stock | H17: =IF(AND(ISNUMBER(D17),ISNUMBER(F17)),IF(ROUND(D17,O17)=ROUND(F17,O17),"Reproduced to precision","Unresolved published value"),"Not comparable") -> Reproduced to precision | I17: All five values reproduce using sales / closing total inventory. The class formula remains COGS / average total inventory. This is a mathematical reconstruction using audited inputs; the report does not explicitly state the inventory-turnover formula. | J17: FY2025 AR p53 "Key financial data for the last six years" (per-share items split-adjusted 5:1) | K17: Not reproduced | L17: Published methodology difference (reconstructed) | M17: =IF(ISNUMBER(E17),E17-D17,"n/m") -> -0.80462086 | N17: =IF(ISNUMBER(F17),F17-D17,"n/m") -> 0.0038139352 | O17: 2
A18: KOHC | B18: Inventory turnover | C18: FY2024 | D18: 5.1 | E18: =KOHC!G144 -> 3.595737 | F18: =KOHC!G84/KOHC!G65 -> 5.0990363 | G18: Sales / closing stores + stock | H18: =IF(AND(ISNUMBER(D18),ISNUMBER(F18)),IF(ROUND(D18,O18)=ROUND(F18,O18),"Reproduced to precision","Unresolved published value"),"Not comparable") -> Reproduced to precision | I18: All five values reproduce using sales / closing total inventory. The class formula remains COGS / average total inventory. This is a mathematical reconstruction using audited inputs; the report does not explicitly state the inventory-turnover formula. | J18: FY2025 AR p53 "Key financial data for the last six years" (per-share items split-adjusted 5:1) | K18: Not reproduced | L18: Published methodology difference (reconstructed) | M18: =IF(ISNUMBER(E18),E18-D18,"n/m") -> -1.504263 | N18: =IF(ISNUMBER(F18),F18-D18,"n/m") -> -0.00096369444 | O18: 2
A19: KOHC | B19: Inventory turnover | C19: FY2025 | D19: 5 | E19: =KOHC!H144 -> 3.0248806 | F19: =KOHC!H84/KOHC!H65 -> 5.0015137 | G19: Sales / closing stores + stock | H19: =IF(AND(ISNUMBER(D19),ISNUMBER(F19)),IF(ROUND(D19,O19)=ROUND(F19,O19),"Reproduced to precision","Unresolved published value"),"Not comparable") -> Reproduced to precision | I19: All five values reproduce using sales / closing total inventory. The class formula remains COGS / average total inventory. This is a mathematical reconstruction using audited inputs; the report does not explicitly state the inventory-turnover formula. | J19: FY2025 AR p53 "Key financial data for the last six years" (per-share items split-adjusted 5:1) | K19: Not reproduced | L19: Published methodology difference (reconstructed) | M19: =IF(ISNUMBER(E19),E19-D19,"n/m") -> -1.9751194 | N19: =IF(ISNUMBER(F19),F19-D19,"n/m") -> 0.0015137158 | O19: 2
A20: KOHC | B20: Days in receivables | C20: FY2021 | D20: 14.92 | E20: =KOHC!D148 -> 11.21127 | F20: =365*KOHC!D32/KOHC!D84 -> 14.922758 | G20: 365 x closing trade debts / sales | H20: =IF(AND(ISNUMBER(D20),ISNUMBER(F20)),IF(ROUND(D20,O20)=ROUND(F20,O20),"Reproduced to precision","Unresolved published value"),"Not comparable") -> Reproduced to precision | I20: Tested the source-based convention shown in G against official published precision. Unmatched values remain unresolved; neither the standardized method nor the financial inputs were altered to force agreement. | J20: FY2025 AR p53 "Key financial data for the last six years" (per-share items split-adjusted 5:1) | K20: Reconciled (company convention) | L20: Source comparison | M20: =IF(ISNUMBER(E20),E20-D20,"n/m") -> -3.7087305 | N20: =IF(ISNUMBER(F20),F20-D20,"n/m") -> 0.0027580562 | O20: 2
A21: KOHC | B21: Days in receivables | C21: FY2022 | D21: 10.17 | E21: =KOHC!E148 -> 10.544725 | F21: =365*KOHC!E32/KOHC!E84 -> 10.169873 | G21: 365 x closing trade debts / sales | H21: =IF(AND(ISNUMBER(D21),ISNUMBER(F21)),IF(ROUND(D21,O21)=ROUND(F21,O21),"Reproduced to precision","Unresolved published value"),"Not comparable") -> Reproduced to precision | I21: Tested the source-based convention shown in G against official published precision. Unmatched values remain unresolved; neither the standardized method nor the financial inputs were altered to force agreement. | J21: FY2025 AR p53 "Key financial data for the last six years" (per-share items split-adjusted 5:1) | K21: Reconciled (company convention) | L21: Source comparison | M21: =IF(ISNUMBER(E21),E21-D21,"n/m") -> 0.37472548 | N21: =IF(ISNUMBER(F21),F21-D21,"n/m") -> -0.00012674429 | O21: 2
A22: KOHC | B22: Days in receivables | C22: FY2023 | D22: 11.31 | E22: =KOHC!F148 -> 9.9479554 | F22: =365*KOHC!F32/KOHC!F84 -> 11.30546 | G22: 365 x closing trade debts / sales | H22: =IF(AND(ISNUMBER(D22),ISNUMBER(F22)),IF(ROUND(D22,O22)=ROUND(F22,O22),"Reproduced to precision","Unresolved published value"),"Not comparable") -> Reproduced to precision | I22: Tested the source-based convention shown in G against official published precision. Unmatched values remain unresolved; neither the standardized method nor the financial inputs were altered to force agreement. | J22: FY2025 AR p53 "Key financial data for the last six years" (per-share items split-adjusted 5:1) | K22: Reconciled (company convention) | L22: Source comparison | M22: =IF(ISNUMBER(E22),E22-D22,"n/m") -> -1.3620446 | N22: =IF(ISNUMBER(F22),F22-D22,"n/m") -> -0.0045402495 | O22: 2
A23: KOHC | B23: Days in receivables | C23: FY2024 | D23: 19.93 | E23: =KOHC!G148 -> 15.657663 | F23: =365*KOHC!G32/KOHC!G84 -> 19.929753 | G23: 365 x closing trade debts / sales | H23: =IF(AND(ISNUMBER(D23),ISNUMBER(F23)),IF(ROUND(D23,O23)=ROUND(F23,O23),"Reproduced to precision","Unresolved published value"),"Not comparable") -> Reproduced to precision | I23: Tested the source-based convention shown in G against official published precision. Unmatched values remain unresolved; neither the standardized method nor the financial inputs were altered to force agreement. | J23: FY2025 AR p53 "Key financial data for the last six years" (per-share items split-adjusted 5:1) | K23: Reconciled (company convention) | L23: Source comparison | M23: =IF(ISNUMBER(E23),E23-D23,"n/m") -> -4.2723368 | N23: =IF(ISNUMBER(F23),F23-D23,"n/m") -> -0.00024662361 | O23: 2
A24: KOHC | B24: Days in receivables | C24: FY2025 | D24: 16.46 | E24: =KOHC!H148 -> 18.487733 | F24: =365*KOHC!H32/KOHC!H84 -> 16.455255 | G24: 365 x closing trade debts / sales | H24: =IF(AND(ISNUMBER(D24),ISNUMBER(F24)),IF(ROUND(D24,O24)=ROUND(F24,O24),"Reproduced to precision","Unresolved published value"),"Not comparable") -> Reproduced to precision | I24: Tested the source-based convention shown in G against official published precision. Unmatched values remain unresolved; neither the standardized method nor the financial inputs were altered to force agreement. | J24: FY2025 AR p53 "Key financial data for the last six years" (per-share items split-adjusted 5:1) | K24: Reconciled (company convention) | L24: Source comparison | M24: =IF(ISNUMBER(E24),E24-D24,"n/m") -> 2.0277327 | N24: =IF(ISNUMBER(F24),F24-D24,"n/m") -> -0.0047453342 | O24: 2
A25: KOHC | B25: Days in payables | C25: FY2021 | D25: 33.74 | E25: =KOHC!D149 -> 26.695664 | F25: =365/((-KOHC!D85)/(KOHC!D51+KOHC!D254)) -> 33.736941 | G25: COGS / closing (trade creditors + contractors bills) | H25: =IF(AND(ISNUMBER(D25),ISNUMBER(F25)),IF(ROUND(D25,O25)=ROUND(F25,O25),"Reproduced to precision","Unresolved published value"),"Not comparable") -> Reproduced to precision | I25: Official note 9 lists local creditors, import bills and contractors bills separately. Published series reproduces by including contractors bills and using the closing balance. Standardized supplier-payable measure excludes unallocated contractor/capital balances and uses average opening/closing balances. | J25: FY2025 AR p53 "Key financial data for the last six years" (per-share items split-adjusted 5:1) | K25: Not reproduced | L25: Published methodology difference (reconstructed) | M25: =IF(ISNUMBER(E25),E25-D25,"n/m") -> -7.0443356 | N25: =IF(ISNUMBER(F25),F25-D25,"n/m") -> -0.0030591072 | O25: 2
A26: KOHC | B26: Days in payables | C26: FY2022 | D26: 20.97 | E26: =KOHC!E149 -> 22.445127 | F26: =365/((-KOHC!E85)/(KOHC!E51+KOHC!E254)) -> 20.968252 | G26: COGS / closing (trade creditors + contractors bills) | H26: =IF(AND(ISNUMBER(D26),ISNUMBER(F26)),IF(ROUND(D26,O26)=ROUND(F26,O26),"Reproduced to precision","Unresolved published value"),"Not comparable") -> Reproduced to precision | I26: Official note 9 lists local creditors, import bills and contractors bills separately. Published series reproduces by including contractors bills and using the closing balance. Standardized supplier-payable measure excludes unallocated contractor/capital balances and uses average opening/closing balances. | J26: FY2025 AR p53 "Key financial data for the last six years" (per-share items split-adjusted 5:1) | K26: Not reproduced | L26: Published methodology difference (reconstructed) | M26: =IF(ISNUMBER(E26),E26-D26,"n/m") -> 1.4751272 | N26: =IF(ISNUMBER(F26),F26-D26,"n/m") -> -0.0017484526 | O26: 2
A27: KOHC | B27: Days in payables | C27: FY2023 | D27: 9.14 | E27: =KOHC!F149 -> 12.531625 | F27: =365/((-KOHC!F85)/(KOHC!F51+KOHC!F254)) -> 9.1383817 | G27: COGS / closing (trade creditors + contractors bills) | H27: =IF(AND(ISNUMBER(D27),ISNUMBER(F27)),IF(ROUND(D27,O27)=ROUND(F27,O27),"Reproduced to precision","Unresolved published value"),"Not comparable") -> Reproduced to precision | I27: Official note 9 lists local creditors, import bills and contractors bills separately. Published series reproduces by including contractors bills and using the closing balance. Standardized supplier-payable measure excludes unallocated contractor/capital balances and uses average opening/closing balances. | J27: FY2025 AR p53 "Key financial data for the last six years" (per-share items split-adjusted 5:1) | K27: Not reproduced | L27: Published methodology difference (reconstructed) | M27: =IF(ISNUMBER(E27),E27-D27,"n/m") -> 3.3916247 | N27: =IF(ISNUMBER(F27),F27-D27,"n/m") -> -0.0016183424 | O27: 2
A28: KOHC | B28: Days in payables | C28: FY2024 | D28: 24.36 | E28: =KOHC!G149 -> 16.364411 | F28: =365/((-KOHC!G85)/(KOHC!G51+KOHC!G254)) -> 24.357241 | G28: COGS / closing (trade creditors + contractors bills) | H28: =IF(AND(ISNUMBER(D28),ISNUMBER(F28)),IF(ROUND(D28,O28)=ROUND(F28,O28),"Reproduced to precision","Unresolved published value"),"Not comparable") -> Reproduced to precision | I28: Official note 9 lists local creditors, import bills and contractors bills separately. Published series reproduces by including contractors bills and using the closing balance. Standardized supplier-payable measure excludes unallocated contractor/capital balances and uses average opening/closing balances. | J28: FY2025 AR p53 "Key financial data for the last six years" (per-share items split-adjusted 5:1) | K28: Not reproduced | L28: Published methodology difference (reconstructed) | M28: =IF(ISNUMBER(E28),E28-D28,"n/m") -> -7.9955888 | N28: =IF(ISNUMBER(F28),F28-D28,"n/m") -> -0.0027591544 | O28: 2
A29: KOHC | B29: Days in payables | C29: FY2025 | D29: 34.79 | E29: =KOHC!H149 -> 31.106489 | F29: =365/((-KOHC!H85)/(KOHC!H51+KOHC!H254)) -> 34.78887 | G29: COGS / closing (trade creditors + contractors bills) | H29: =IF(AND(ISNUMBER(D29),ISNUMBER(F29)),IF(ROUND(D29,O29)=ROUND(F29,O29),"Reproduced to precision","Unresolved published value"),"Not comparable") -> Reproduced to precision | I29: Official note 9 lists local creditors, import bills and contractors bills separately. Published series reproduces by including contractors bills and using the closing balance. Standardized supplier-payable measure excludes unallocated contractor/capital balances and uses average opening/closing balances. | J29: FY2025 AR p53 "Key financial data for the last six years" (per-share items split-adjusted 5:1) | K29: Not reproduced | L29: Published methodology difference (reconstructed) | M29: =IF(ISNUMBER(E29),E29-D29,"n/m") -> -3.6835111 | N29: =IF(ISNUMBER(F29),F29-D29,"n/m") -> -0.0011298098 | O29: 2
A30: KOHC | B30: Cash conversion cycle | C30: FY2021 | D30: 44.66 | E30: =KOHC!D151 -> 59.663349 | F30: =365*KOHC!D65/KOHC!D84+365*KOHC!D32/KOHC!D84-365*(KOHC!D51+KOHC!D254)/(-KOHC!D85) -> 44.658827 | G30: Company component conventions; independent raw reconstruction | H30: =IF(AND(ISNUMBER(D30),ISNUMBER(F30)),IF(ROUND(D30,O30)=ROUND(F30,O30),"Reproduced to precision","Unresolved published value"),"Not comparable") -> Reproduced to precision | I30: Tested the source-based convention shown in G against official published precision. Unmatched values remain unresolved; neither the standardized method nor the financial inputs were altered to force agreement. | J30: FY2025 AR p53 "Key financial data for the last six years" (per-share items split-adjusted 5:1) | K30: See components | L30: Source comparison | M30: =IF(ISNUMBER(E30),E30-D30,"n/m") -> 15.003349 | N30: =IF(ISNUMBER(F30),F30-D30,"n/m") -> -0.0011731675 | O30: 2
A31: KOHC | B31: Cash conversion cycle | C31: FY2022 | D31: 52.16 | E31: =KOHC!E151 -> 66.072196 | F31: =365*KOHC!E65/KOHC!E84+365*KOHC!E32/KOHC!E84-365*(KOHC!E51+KOHC!E254)/(-KOHC!E85) -> 52.160932 | G31: Company component conventions; independent raw reconstruction | H31: =IF(AND(ISNUMBER(D31),ISNUMBER(F31)),IF(ROUND(D31,O31)=ROUND(F31,O31),"Reproduced to precision","Unresolved published value"),"Not comparable") -> Reproduced to precision | I31: Tested the source-based convention shown in G against official published precision. Unmatched values remain unresolved; neither the standardized method nor the financial inputs were altered to force agreement. | J31: FY2025 AR p53 "Key financial data for the last six years" (per-share items split-adjusted 5:1) | K31: See components | L31: Source comparison | M31: =IF(ISNUMBER(E31),E31-D31,"n/m") -> 13.912196 | N31: =IF(ISNUMBER(F31),F31-D31,"n/m") -> 0.00093193202 | O31: 2
A32: KOHC | B32: Cash conversion cycle | C32: FY2023 | D32: 73.96 | E32: =KOHC!F151 -> 82.788876 | F32: =365*KOHC!F65/KOHC!F84+365*KOHC!F32/KOHC!F84-365*(KOHC!F51+KOHC!F254)/(-KOHC!F85) -> 73.963569 | G32: Company component conventions; independent raw reconstruction | H32: =IF(AND(ISNUMBER(D32),ISNUMBER(F32)),IF(ROUND(D32,O32)=ROUND(F32,O32),"Reproduced to precision","Unresolved published value"),"Not comparable") -> Reproduced to precision | I32: Tested the source-based convention shown in G against official published precision. Unmatched values remain unresolved; neither the standardized method nor the financial inputs were altered to force agreement. | J32: FY2025 AR p53 "Key financial data for the last six years" (per-share items split-adjusted 5:1) | K32: See components | L32: Source comparison | M32: =IF(ISNUMBER(E32),E32-D32,"n/m") -> 8.8288762 | N32: =IF(ISNUMBER(F32),F32-D32,"n/m") -> 0.0035688092 | O32: 2
A33: KOHC | B33: Cash conversion cycle | C33: FY2024 | D33: 67.15 | E33: =KOHC!G151 -> 100.80235 | F33: =365*KOHC!G65/KOHC!G84+365*KOHC!G32/KOHC!G84-365*(KOHC!G51+KOHC!G254)/(-KOHC!G85) -> 67.154666 | G33: Company component conventions; independent raw reconstruction | H33: =IF(AND(ISNUMBER(D33),ISNUMBER(F33)),IF(ROUND(D33,O33)=ROUND(F33,O33),"Reproduced to precision","Unresolved published value"),"Not comparable") -> Reproduced to precision | I33: Tested the source-based convention shown in G against official published precision. Unmatched values remain unresolved; neither the standardized method nor the financial inputs were altered to force agreement. | J33: FY2025 AR p53 "Key financial data for the last six years" (per-share items split-adjusted 5:1) | K33: See components | L33: Source comparison | M33: =IF(ISNUMBER(E33),E33-D33,"n/m") -> 33.652346 | N33: =IF(ISNUMBER(F33),F33-D33,"n/m") -> 0.0046661235 | O33: 2
A34: KOHC | B34: Cash conversion cycle | C34: FY2025 | D34: 54.64 | E34: =KOHC!H151 -> 108.04716 | F34: =365*KOHC!H65/KOHC!H84+365*KOHC!H32/KOHC!H84-365*(KOHC!H51+KOHC!H254)/(-KOHC!H85) -> 54.644291 | G34: Company component conventions; independent raw reconstruction | H34: =IF(AND(ISNUMBER(D34),ISNUMBER(F34)),IF(ROUND(D34,O34)=ROUND(F34,O34),"Reproduced to precision","Unresolved published value"),"Not comparable") -> Reproduced to precision | I34: Tested the source-based convention shown in G against official published precision. Unmatched values remain unresolved; neither the standardized method nor the financial inputs were altered to force agreement. | J34: FY2025 AR p53 "Key financial data for the last six years" (per-share items split-adjusted 5:1) | K34: See components | L34: Source comparison | M34: =IF(ISNUMBER(E34),E34-D34,"n/m") -> 53.407163 | N34: =IF(ISNUMBER(F34),F34-D34,"n/m") -> 0.0042909142 | O34: 2
A35: KOHC | B35: Total assets turnover | C35: FY2021 | D35: 0.67 | E35: =KOHC!D152 -> 0.70920116 | F35: =KOHC!D84/KOHC!D37 -> 0.66665083 | G35: Sales / closing assets | H35: =IF(AND(ISNUMBER(D35),ISNUMBER(F35)),IF(ROUND(D35,O35)=ROUND(F35,O35),"Reproduced to precision","Unresolved published value"),"Not comparable") -> Reproduced to precision | I35: Tested the source-based convention shown in G against official published precision. Unmatched values remain unresolved; neither the standardized method nor the financial inputs were altered to force agreement. | J35: FY2025 AR p53 "Key financial data for the last six years" (per-share items split-adjusted 5:1) | K35: Reconciled (company convention) | L35: Source comparison | M35: =IF(ISNUMBER(E35),E35-D35,"n/m") -> 0.039201162 | N35: =IF(ISNUMBER(F35),F35-D35,"n/m") -> -0.0033491738 | O35: 2
A36: KOHC | B36: Total assets turnover | C36: FY2022 | D36: 0.76 | E36: =KOHC!E152 -> 0.82774287 | F36: =KOHC!E84/KOHC!E37 -> 0.75839545 | G36: Sales / closing assets | H36: =IF(AND(ISNUMBER(D36),ISNUMBER(F36)),IF(ROUND(D36,O36)=ROUND(F36,O36),"Reproduced to precision","Unresolved published value"),"Not comparable") -> Reproduced to precision | I36: Tested the source-based convention shown in G against official published precision. Unmatched values remain unresolved; neither the standardized method nor the financial inputs were altered to force agreement. | J36: FY2025 AR p53 "Key financial data for the last six years" (per-share items split-adjusted 5:1) | K36: Reconciled (company convention) | L36: Source comparison | M36: =IF(ISNUMBER(E36),E36-D36,"n/m") -> 0.067742873 | N36: =IF(ISNUMBER(F36),F36-D36,"n/m") -> -0.0016045516 | O36: 2
A37: KOHC | B37: Total assets turnover | C37: FY2023 | D37: 0.79 | E37: =KOHC!F152 -> 0.83809914 | F37: =KOHC!F84/KOHC!F37 -> 0.78581821 | G37: Sales / closing assets | H37: =IF(AND(ISNUMBER(D37),ISNUMBER(F37)),IF(ROUND(D37,O37)=ROUND(F37,O37),"Reproduced to precision","Unresolved published value"),"Not comparable") -> Reproduced to precision | I37: Tested the source-based convention shown in G against official published precision. Unmatched values remain unresolved; neither the standardized method nor the financial inputs were altered to force agreement. | J37: FY2025 AR p53 "Key financial data for the last six years" (per-share items split-adjusted 5:1) | K37: Reconciled (company convention) | L37: Source comparison | M37: =IF(ISNUMBER(E37),E37-D37,"n/m") -> 0.048099135 | N37: =IF(ISNUMBER(F37),F37-D37,"n/m") -> -0.0041817891 | O37: 2
A38: KOHC | B38: Total assets turnover | C38: FY2024 | D38: 0.66 | E38: =KOHC!G152 -> 0.71323366 | F38: =KOHC!G84/KOHC!G37 -> 0.65679136 | G38: Sales / closing assets | H38: =IF(AND(ISNUMBER(D38),ISNUMBER(F38)),IF(ROUND(D38,O38)=ROUND(F38,O38),"Reproduced to precision","Unresolved published value"),"Not comparable") -> Reproduced to precision | I38: Tested the source-based convention shown in G against official published precision. Unmatched values remain unresolved; neither the standardized method nor the financial inputs were altered to force agreement. | J38: FY2025 AR p53 "Key financial data for the last six years" (per-share items split-adjusted 5:1) | K38: Reconciled (company convention) | L38: Source comparison | M38: =IF(ISNUMBER(E38),E38-D38,"n/m") -> 0.053233661 | N38: =IF(ISNUMBER(F38),F38-D38,"n/m") -> -0.0032086384 | O38: 2
A39: KOHC | B39: Total assets turnover | C39: FY2025 | D39: 0.56 | E39: =KOHC!H152 -> 0.59752333 | F39: =KOHC!H84/KOHC!H37 -> 0.56195953 | G39: Sales / closing assets | H39: =IF(AND(ISNUMBER(D39),ISNUMBER(F39)),IF(ROUND(D39,O39)=ROUND(F39,O39),"Reproduced to precision","Unresolved published value"),"Not comparable") -> Reproduced to precision | I39: Tested the source-based convention shown in G against official published precision. Unmatched values remain unresolved; neither the standardized method nor the financial inputs were altered to force agreement. | J39: FY2025 AR p53 "Key financial data for the last six years" (per-share items split-adjusted 5:1) | K39: Reconciled (company convention) | L39: Source comparison | M39: =IF(ISNUMBER(E39),E39-D39,"n/m") -> 0.037523326 | N39: =IF(ISNUMBER(F39),F39-D39,"n/m") -> 0.0019595349 | O39: 2
A40: KOHC | B40: Fixed assets turnover | C40: FY2021 | D40: 1.11 | E40: =KOHC!D153 -> 1.0844791 | F40: =KOHC!D84/KOHC!D22 -> 1.1059029 | G40: Sales / closing operating PPE | H40: =IF(AND(ISNUMBER(D40),ISNUMBER(F40)),IF(ROUND(D40,O40)=ROUND(F40,O40),"Reproduced to precision","Unresolved published value"),"Not comparable") -> Reproduced to precision | I40: Tested the source-based convention shown in G against official published precision. Unmatched values remain unresolved; neither the standardized method nor the financial inputs were altered to force agreement. | J40: FY2025 AR p53 "Key financial data for the last six years" (per-share items split-adjusted 5:1) | K40: Reconciled (company convention) | L40: Source comparison | M40: =IF(ISNUMBER(E40),E40-D40,"n/m") -> -0.025520899 | N40: =IF(ISNUMBER(F40),F40-D40,"n/m") -> -0.0040970657 | O40: 2
A41: KOHC | B41: Fixed assets turnover | C41: FY2022 | D41: 1.55 | E41: =KOHC!E153 -> 1.5307979 | F41: =KOHC!E84/KOHC!E22 -> 1.5507703 | G41: Sales / closing operating PPE | H41: =IF(AND(ISNUMBER(D41),ISNUMBER(F41)),IF(ROUND(D41,O41)=ROUND(F41,O41),"Reproduced to precision","Unresolved published value"),"Not comparable") -> Reproduced to precision | I41: Tested the source-based convention shown in G against official published precision. Unmatched values remain unresolved; neither the standardized method nor the financial inputs were altered to force agreement. | J41: FY2025 AR p53 "Key financial data for the last six years" (per-share items split-adjusted 5:1) | K41: Reconciled (company convention) | L41: Source comparison | M41: =IF(ISNUMBER(E41),E41-D41,"n/m") -> -0.01920211 | N41: =IF(ISNUMBER(F41),F41-D41,"n/m") -> 0.0007703457 | O41: 2
A42: KOHC | B42: Fixed assets turnover | C42: FY2023 | D42: 1.92 | E42: =KOHC!F153 -> 1.8763377 | F42: =KOHC!F84/KOHC!F22 -> 1.9186059 | G42: Sales / closing operating PPE | H42: =IF(AND(ISNUMBER(D42),ISNUMBER(F42)),IF(ROUND(D42,O42)=ROUND(F42,O42),"Reproduced to precision","Unresolved published value"),"Not comparable") -> Reproduced to precision | I42: Tested the source-based convention shown in G against official published precision. Unmatched values remain unresolved; neither the standardized method nor the financial inputs were altered to force agreement. | J42: FY2025 AR p53 "Key financial data for the last six years" (per-share items split-adjusted 5:1) | K42: Reconciled (company convention) | L42: Source comparison | M42: =IF(ISNUMBER(E42),E42-D42,"n/m") -> -0.043662328 | N42: =IF(ISNUMBER(F42),F42-D42,"n/m") -> -0.0013940967 | O42: 2
A43: KOHC | B43: Fixed assets turnover | C43: FY2024 | D43: 1.83 | E43: =KOHC!G153 -> 1.8650719 | F43: =KOHC!G84/KOHC!G22 -> 1.8266859 | G43: Sales / closing operating PPE | H43: =IF(AND(ISNUMBER(D43),ISNUMBER(F43)),IF(ROUND(D43,O43)=ROUND(F43,O43),"Reproduced to precision","Unresolved published value"),"Not comparable") -> Reproduced to precision | I43: Tested the source-based convention shown in G against official published precision. Unmatched values remain unresolved; neither the standardized method nor the financial inputs were altered to force agreement. | J43: FY2025 AR p53 "Key financial data for the last six years" (per-share items split-adjusted 5:1) | K43: Reconciled (company convention) | L43: Source comparison | M43: =IF(ISNUMBER(E43),E43-D43,"n/m") -> 0.035071946 | N43: =IF(ISNUMBER(F43),F43-D43,"n/m") -> -0.0033140557 | O43: 2
A44: KOHC | B44: Fixed assets turnover | C44: FY2025 | D44: 1.8 | E44: =KOHC!H153 -> 1.7861105 | F44: =KOHC!H84/KOHC!H22 -> 1.7982599 | G44: Sales / closing operating PPE | H44: =IF(AND(ISNUMBER(D44),ISNUMBER(F44)),IF(ROUND(D44,O44)=ROUND(F44,O44),"Reproduced to precision","Unresolved published value"),"Not comparable") -> Reproduced to precision | I44: Tested the source-based convention shown in G against official published precision. Unmatched values remain unresolved; neither the standardized method nor the financial inputs were altered to force agreement. | J44: FY2025 AR p53 "Key financial data for the last six years" (per-share items split-adjusted 5:1) | K44: Reconciled (company convention) | L44: Source comparison | M44: =IF(ISNUMBER(E44),E44-D44,"n/m") -> -0.013889544 | N44: =IF(ISNUMBER(F44),F44-D44,"n/m") -> -0.0017401132 | O44: 2
A45: KOHC | B45: Interest coverage | C45: FY2021 | D45: 10.45 | E45: =KOHC!D159 -> 11.019707 | F45: =KOHC!D108/(-KOHC!D95) -> 10.449576 | G45: EBIT / all finance cost | H45: =IF(AND(ISNUMBER(D45),ISNUMBER(F45)),IF(ROUND(D45,O45)=ROUND(F45,O45),"Reproduced to precision","Unresolved published value"),"Not comparable") -> Reproduced to precision | I45: Tested the source-based convention shown in G against official published precision. Unmatched values remain unresolved; neither the standardized method nor the financial inputs were altered to force agreement. | J45: FY2025 AR p53 "Key financial data for the last six years" (per-share items split-adjusted 5:1) | K45: Reconciled (company convention) | L45: Source comparison | M45: =IF(ISNUMBER(E45),E45-D45,"n/m") -> 0.5697069 | N45: =IF(ISNUMBER(F45),F45-D45,"n/m") -> -0.00042364096 | O45: 2
A46: KOHC | B46: Interest coverage | C46: FY2022 | D46: 17.6 | E46: =KOHC!E159 -> 18.363152 | F46: =KOHC!E108/(-KOHC!E95) -> 17.599051 | G46: EBIT / all finance cost | H46: =IF(AND(ISNUMBER(D46),ISNUMBER(F46)),IF(ROUND(D46,O46)=ROUND(F46,O46),"Reproduced to precision","Unresolved published value"),"Not comparable") -> Reproduced to precision | I46: Tested the source-based convention shown in G against official published precision. Unmatched values remain unresolved; neither the standardized method nor the financial inputs were altered to force agreement. | J46: FY2025 AR p53 "Key financial data for the last six years" (per-share items split-adjusted 5:1) | K46: Reconciled (company convention) | L46: Source comparison | M46: =IF(ISNUMBER(E46),E46-D46,"n/m") -> 0.76315245 | N46: =IF(ISNUMBER(F46),F46-D46,"n/m") -> -0.00094921468 | O46: 2
A47: KOHC | B47: Interest coverage | C47: FY2023 | D47: 15.14 | E47: =KOHC!F159 -> 16.398825 | F47: =KOHC!F108/(-KOHC!F95) -> 15.141859 | G47: EBIT / all finance cost | H47: =IF(AND(ISNUMBER(D47),ISNUMBER(F47)),IF(ROUND(D47,O47)=ROUND(F47,O47),"Reproduced to precision","Unresolved published value"),"Not comparable") -> Reproduced to precision | I47: Tested the source-based convention shown in G against official published precision. Unmatched values remain unresolved; neither the standardized method nor the financial inputs were altered to force agreement. | J47: FY2025 AR p53 "Key financial data for the last six years" (per-share items split-adjusted 5:1) | K47: Reconciled (company convention) | L47: Source comparison | M47: =IF(ISNUMBER(E47),E47-D47,"n/m") -> 1.2588253 | N47: =IF(ISNUMBER(F47),F47-D47,"n/m") -> 0.0018585945 | O47: 2
A48: KOHC | B48: Interest coverage | C48: FY2024 | D48: 21.34 | E48: =KOHC!G159 -> 22.36772 | F48: =KOHC!G108/(-KOHC!G95) -> 21.337577 | G48: EBIT / all finance cost | H48: =IF(AND(ISNUMBER(D48),ISNUMBER(F48)),IF(ROUND(D48,O48)=ROUND(F48,O48),"Reproduced to precision","Unresolved published value"),"Not comparable") -> Reproduced to precision | I48: Tested the source-based convention shown in G against official published precision. Unmatched values remain unresolved; neither the standardized method nor the financial inputs were altered to force agreement. | J48: FY2025 AR p53 "Key financial data for the last six years" (per-share items split-adjusted 5:1) | K48: Reconciled (company convention) | L48: Source comparison | M48: =IF(ISNUMBER(E48),E48-D48,"n/m") -> 1.0277202 | N48: =IF(ISNUMBER(F48),F48-D48,"n/m") -> -0.0024229904 | O48: 2
A49: KOHC | B49: Interest coverage | C49: FY2025 | D49: 51.72 | E49: =KOHC!H159 -> 59.098953 | F49: =KOHC!H108/(-KOHC!H95) -> 51.718148 | G49: EBIT / all finance cost | H49: =IF(AND(ISNUMBER(D49),ISNUMBER(F49)),IF(ROUND(D49,O49)=ROUND(F49,O49),"Reproduced to precision","Unresolved published value"),"Not comparable") -> Reproduced to precision | I49: Tested the source-based convention shown in G against official published precision. Unmatched values remain unresolved; neither the standardized method nor the financial inputs were altered to force agreement. | J49: FY2025 AR p53 "Key financial data for the last six years" (per-share items split-adjusted 5:1) | K49: Reconciled (company convention) | L49: Source comparison | M49: =IF(ISNUMBER(E49),E49-D49,"n/m") -> 7.3789532 | N49: =IF(ISNUMBER(F49),F49-D49,"n/m") -> -0.0018521825 | O49: 2
A50: KOHC | B50: Gross profit ratio | C50: FY2021 | D50: 0.248 | E50: =KOHC!D161 -> 0.24796341 | F50: =KOHC!D86/KOHC!D84 -> 0.24796341 | G50: Standard definition | H50: =IF(AND(ISNUMBER(D50),ISNUMBER(F50)),IF(ROUND(D50,O50)=ROUND(F50,O50),"Reproduced to precision","Unresolved published value"),"Not comparable") -> Reproduced to precision | I50: Tested the source-based convention shown in G against official published precision. Unmatched values remain unresolved; neither the standardized method nor the financial inputs were altered to force agreement. | J50: FY2025 AR p53 "Key financial data for the last six years" (per-share items split-adjusted 5:1) | K50: Agrees (same convention) | L50: Source comparison | M50: =IF(ISNUMBER(E50),E50-D50,"n/m") -> -3.6586992e-05 | N50: =IF(ISNUMBER(F50),F50-D50,"n/m") -> -3.6586992e-05 | O50: 4
A51: KOHC | B51: Gross profit ratio | C51: FY2022 | D51: 0.2984 | E51: =KOHC!E161 -> 0.29843914 | F51: =KOHC!E86/KOHC!E84 -> 0.29843914 | G51: Standard definition | H51: =IF(AND(ISNUMBER(D51),ISNUMBER(F51)),IF(ROUND(D51,O51)=ROUND(F51,O51),"Reproduced to precision","Unresolved published value"),"Not comparable") -> Reproduced to precision | I51: Tested the source-based convention shown in G against official published precision. Unmatched values remain unresolved; neither the standardized method nor the financial inputs were altered to force agreement. | J51: FY2025 AR p53 "Key financial data for the last six years" (per-share items split-adjusted 5:1) | K51: Agrees (same convention) | L51: Source comparison | M51: =IF(ISNUMBER(E51),E51-D51,"n/m") -> 3.9142135e-05 | N51: =IF(ISNUMBER(F51),F51-D51,"n/m") -> 3.9142135e-05 | O51: 4
A52: KOHC | B52: Gross profit ratio | C52: FY2023 | D52: 0.268 | E52: =KOHC!F161 -> 0.26804357 | F52: =KOHC!F86/KOHC!F84 -> 0.26804357 | G52: Standard definition | H52: =IF(AND(ISNUMBER(D52),ISNUMBER(F52)),IF(ROUND(D52,O52)=ROUND(F52,O52),"Reproduced to precision","Unresolved published value"),"Not comparable") -> Reproduced to precision | I52: Tested the source-based convention shown in G against official published precision. Unmatched values remain unresolved; neither the standardized method nor the financial inputs were altered to force agreement. | J52: FY2025 AR p53 "Key financial data for the last six years" (per-share items split-adjusted 5:1) | K52: Agrees (same convention) | L52: Source comparison | M52: =IF(ISNUMBER(E52),E52-D52,"n/m") -> 4.356819e-05 | N52: =IF(ISNUMBER(F52),F52-D52,"n/m") -> 4.356819e-05 | O52: 4
A53: KOHC | B53: Gross profit ratio | C53: FY2024 | D53: 0.2913 | E53: =KOHC!G161 -> 0.29125851 | F53: =KOHC!G86/KOHC!G84 -> 0.29125851 | G53: Standard definition | H53: =IF(AND(ISNUMBER(D53),ISNUMBER(F53)),IF(ROUND(D53,O53)=ROUND(F53,O53),"Reproduced to precision","Unresolved published value"),"Not comparable") -> Reproduced to precision | I53: Tested the source-based convention shown in G against official published precision. Unmatched values remain unresolved; neither the standardized method nor the financial inputs were altered to force agreement. | J53: FY2025 AR p53 "Key financial data for the last six years" (per-share items split-adjusted 5:1) | K53: Agrees (same convention) | L53: Source comparison | M53: =IF(ISNUMBER(E53),E53-D53,"n/m") -> -4.1485326e-05 | N53: =IF(ISNUMBER(F53),F53-D53,"n/m") -> -4.1485326e-05 | O53: 4
A54: KOHC | B54: Gross profit ratio | C54: FY2025 | D54: 0.3922 | E54: =KOHC!H161 -> 0.39220278 | F54: =KOHC!H86/KOHC!H84 -> 0.39220278 | G54: Standard definition | H54: =IF(AND(ISNUMBER(D54),ISNUMBER(F54)),IF(ROUND(D54,O54)=ROUND(F54,O54),"Reproduced to precision","Unresolved published value"),"Not comparable") -> Reproduced to precision | I54: Tested the source-based convention shown in G against official published precision. Unmatched values remain unresolved; neither the standardized method nor the financial inputs were altered to force agreement. | J54: FY2025 AR p53 "Key financial data for the last six years" (per-share items split-adjusted 5:1) | K54: Agrees (same convention) | L54: Source comparison | M54: =IF(ISNUMBER(E54),E54-D54,"n/m") -> 2.7817545e-06 | N54: =IF(ISNUMBER(F54),F54-D54,"n/m") -> 2.7817545e-06 | O54: 4
A55: KOHC | B55: Net profit to sales | C55: FY2021 | D55: 0.1454 | E55: =KOHC!D163 -> 0.14538191 | F55: =KOHC!D99/KOHC!D84 -> 0.14538191 | G55: Standard definition | H55: =IF(AND(ISNUMBER(D55),ISNUMBER(F55)),IF(ROUND(D55,O55)=ROUND(F55,O55),"Reproduced to precision","Unresolved published value"),"Not comparable") -> Reproduced to precision | I55: Tested the source-based convention shown in G against official published precision. Unmatched values remain unresolved; neither the standardized method nor the financial inputs were altered to force agreement. | J55: FY2025 AR p53 "Key financial data for the last six years" (per-share items split-adjusted 5:1) | K55: Agrees (same convention) | L55: Source comparison | M55: =IF(ISNUMBER(E55),E55-D55,"n/m") -> -1.809101e-05 | N55: =IF(ISNUMBER(F55),F55-D55,"n/m") -> -1.809101e-05 | O55: 4
A56: KOHC | B56: Net profit to sales | C56: FY2022 | D56: 0.1528 | E56: =KOHC!E163 -> 0.15282076 | F56: =KOHC!E99/KOHC!E84 -> 0.15282076 | G56: Standard definition | H56: =IF(AND(ISNUMBER(D56),ISNUMBER(F56)),IF(ROUND(D56,O56)=ROUND(F56,O56),"Reproduced to precision","Unresolved published value"),"Not comparable") -> Reproduced to precision | I56: Tested the source-based convention shown in G against official published precision. Unmatched values remain unresolved; neither the standardized method nor the financial inputs were altered to force agreement. | J56: FY2025 AR p53 "Key financial data for the last six years" (per-share items split-adjusted 5:1) | K56: Agrees (same convention) | L56: Source comparison | M56: =IF(ISNUMBER(E56),E56-D56,"n/m") -> 2.0756958e-05 | N56: =IF(ISNUMBER(F56),F56-D56,"n/m") -> 2.0756958e-05 | O56: 4
A57: KOHC | B57: Net profit to sales | C57: FY2023 | D57: 0.1496 | E57: =KOHC!F163 -> 0.14955053 | F57: =KOHC!F99/KOHC!F84 -> 0.14955053 | G57: Standard definition | H57: =IF(AND(ISNUMBER(D57),ISNUMBER(F57)),IF(ROUND(D57,O57)=ROUND(F57,O57),"Reproduced to precision","Unresolved published value"),"Not comparable") -> Reproduced to precision | I57: Tested the source-based convention shown in G against official published precision. Unmatched values remain unresolved; neither the standardized method nor the financial inputs were altered to force agreement. | J57: FY2025 AR p53 "Key financial data for the last six years" (per-share items split-adjusted 5:1) | K57: Agrees (same convention) | L57: Source comparison | M57: =IF(ISNUMBER(E57),E57-D57,"n/m") -> -4.9471286e-05 | N57: =IF(ISNUMBER(F57),F57-D57,"n/m") -> -4.9471286e-05 | O57: 4
A58: KOHC | B58: Net profit to sales | C58: FY2024 | D58: 0.2301 | E58: =KOHC!G163 -> 0.23011561 | F58: =KOHC!G99/KOHC!G84 -> 0.23011561 | G58: Standard definition | H58: =IF(AND(ISNUMBER(D58),ISNUMBER(F58)),IF(ROUND(D58,O58)=ROUND(F58,O58),"Reproduced to precision","Unresolved published value"),"Not comparable") -> Reproduced to precision | I58: Tested the source-based convention shown in G against official published precision. Unmatched values remain unresolved; neither the standardized method nor the financial inputs were altered to force agreement. | J58: FY2025 AR p53 "Key financial data for the last six years" (per-share items split-adjusted 5:1) | K58: Agrees (same convention) | L58: Source comparison | M58: =IF(ISNUMBER(E58),E58-D58,"n/m") -> 1.5612199e-05 | N58: =IF(ISNUMBER(F58),F58-D58,"n/m") -> 1.5612199e-05 | O58: 4
A59: KOHC | B59: Net profit to sales | C59: FY2025 | D59: 0.3084 | E59: =KOHC!H163 -> 0.3083772 | F59: =KOHC!H99/KOHC!H84 -> 0.3083772 | G59: Standard definition | H59: =IF(AND(ISNUMBER(D59),ISNUMBER(F59)),IF(ROUND(D59,O59)=ROUND(F59,O59),"Reproduced to precision","Unresolved published value"),"Not comparable") -> Reproduced to precision | I59: Tested the source-based convention shown in G against official published precision. Unmatched values remain unresolved; neither the standardized method nor the financial inputs were altered to force agreement. | J59: FY2025 AR p53 "Key financial data for the last six years" (per-share items split-adjusted 5:1) | K59: Agrees (same convention) | L59: Source comparison | M59: =IF(ISNUMBER(E59),E59-D59,"n/m") -> -2.2802924e-05 | N59: =IF(ISNUMBER(F59),F59-D59,"n/m") -> -2.2802924e-05 | O59: 4
A60: KOHC | B60: Return on equity | C60: FY2021 | D60: 0.1574 | E60: =KOHC!D165 -> 0.17081754 | F60: =KOHC!D99/KOHC!D41 -> 0.1573785 | G60: PAT / closing equity | H60: =IF(AND(ISNUMBER(D60),ISNUMBER(F60)),IF(ROUND(D60,O60)=ROUND(F60,O60),"Reproduced to precision","Unresolved published value"),"Not comparable") -> Reproduced to precision | I60: Tested the source-based convention shown in G against official published precision. Unmatched values remain unresolved; neither the standardized method nor the financial inputs were altered to force agreement. | J60: FY2025 AR p53 "Key financial data for the last six years" (per-share items split-adjusted 5:1) | K60: Reconciled (company convention) | L60: Source comparison | M60: =IF(ISNUMBER(E60),E60-D60,"n/m") -> 0.013417538 | N60: =IF(ISNUMBER(F60),F60-D60,"n/m") -> -2.1501975e-05 | O60: 4
A61: KOHC | B61: Return on equity | C61: FY2022 | D61: 0.1844 | E61: =KOHC!E165 -> 0.20312532 | F61: =KOHC!E99/KOHC!E41 -> 0.18440284 | G61: PAT / closing equity | H61: =IF(AND(ISNUMBER(D61),ISNUMBER(F61)),IF(ROUND(D61,O61)=ROUND(F61,O61),"Reproduced to precision","Unresolved published value"),"Not comparable") -> Reproduced to precision | I61: Tested the source-based convention shown in G against official published precision. Unmatched values remain unresolved; neither the standardized method nor the financial inputs were altered to force agreement. | J61: FY2025 AR p53 "Key financial data for the last six years" (per-share items split-adjusted 5:1) | K61: Reconciled (company convention) | L61: Source comparison | M61: =IF(ISNUMBER(E61),E61-D61,"n/m") -> 0.018725315 | N61: =IF(ISNUMBER(F61),F61-D61,"n/m") -> 2.8352338e-06 | O61: 4
A62: KOHC | B62: Return on equity | C62: FY2023 | D62: 0.1785 | E62: =KOHC!F165 -> 0.19449096 | F62: =KOHC!F99/KOHC!F41 -> 0.17849565 | G62: PAT / closing equity | H62: =IF(AND(ISNUMBER(D62),ISNUMBER(F62)),IF(ROUND(D62,O62)=ROUND(F62,O62),"Reproduced to precision","Unresolved published value"),"Not comparable") -> Reproduced to precision | I62: Tested the source-based convention shown in G against official published precision. Unmatched values remain unresolved; neither the standardized method nor the financial inputs were altered to force agreement. | J62: FY2025 AR p53 "Key financial data for the last six years" (per-share items split-adjusted 5:1) | K62: Reconciled (company convention) | L62: Source comparison | M62: =IF(ISNUMBER(E62),E62-D62,"n/m") -> 0.015990957 | N62: =IF(ISNUMBER(F62),F62-D62,"n/m") -> -4.3508834e-06 | O62: 4
A63: KOHC | B63: Return on equity | C63: FY2024 | D63: 0.2164 | E63: =KOHC!G165 -> 0.24134091 | F63: =KOHC!G99/KOHC!G41 -> 0.21643681 | G63: PAT / closing equity | H63: =IF(AND(ISNUMBER(D63),ISNUMBER(F63)),IF(ROUND(D63,O63)=ROUND(F63,O63),"Reproduced to precision","Unresolved published value"),"Not comparable") -> Reproduced to precision | I63: Tested the source-based convention shown in G against official published precision. Unmatched values remain unresolved; neither the standardized method nor the financial inputs were altered to force agreement. | J63: FY2025 AR p53 "Key financial data for the last six years" (per-share items split-adjusted 5:1) | K63: Reconciled (company convention) | L63: Source comparison | M63: =IF(ISNUMBER(E63),E63-D63,"n/m") -> 0.02494091 | N63: =IF(ISNUMBER(F63),F63-D63,"n/m") -> 3.6814573e-05 | O63: 4
A64: KOHC | B64: Return on equity | C64: FY2025 | D64: 0.2414 | E64: =KOHC!H165 -> 0.25998291 | F64: =KOHC!H99/KOHC!H41 -> 0.24137435 | G64: PAT / closing equity | H64: =IF(AND(ISNUMBER(D64),ISNUMBER(F64)),IF(ROUND(D64,O64)=ROUND(F64,O64),"Reproduced to precision","Unresolved published value"),"Not comparable") -> Reproduced to precision | I64: Tested the source-based convention shown in G against official published precision. Unmatched values remain unresolved; neither the standardized method nor the financial inputs were altered to force agreement. | J64: FY2025 AR p53 "Key financial data for the last six years" (per-share items split-adjusted 5:1) | K64: Reconciled (company convention) | L64: Source comparison | M64: =IF(ISNUMBER(E64),E64-D64,"n/m") -> 0.018582909 | N64: =IF(ISNUMBER(F64),F64-D64,"n/m") -> -2.5647911e-05 | O64: 4
A65: KOHC | B65: Price earning ratio | C65: FY2021 | D65: 11.86 | E65: =KOHC!D172 -> 11.858689 | F65: ='PSX Prices'!F6/(KOHC!D99/'PSX Prices'!O6) -> 11.859263 | G65: Report price / unrounded report-basis EPS | H65: =IF(AND(ISNUMBER(D65),ISNUMBER(F65)),IF(ROUND(D65,O65)=ROUND(F65,O65),"Reproduced to precision","Unresolved published value"),"Not comparable") -> Reproduced to precision | I65: Tested the source-based convention shown in G against official published precision. Unmatched values remain unresolved; neither the standardized method nor the financial inputs were altered to force agreement. | J65: FY2025 AR p53 "Key financial data for the last six years" (per-share items split-adjusted 5:1) | K65: Market recheck | L65: Source comparison | M65: =IF(ISNUMBER(E65),E65-D65,"n/m") -> -0.0013114288 | N65: =IF(ISNUMBER(F65),F65-D65,"n/m") -> -0.0007371304 | O65: 2
A66: KOHC | B66: Price earning ratio | C66: FY2022 | D66: 5.2 | E66: =KOHC!E172 -> 5.2023532 | F66: ='PSX Prices'!F7/(KOHC!E99/'PSX Prices'!O7) -> 5.2031528 | G66: Report price / unrounded report-basis EPS | H66: =IF(AND(ISNUMBER(D66),ISNUMBER(F66)),IF(ROUND(D66,O66)=ROUND(F66,O66),"Reproduced to precision","Unresolved published value"),"Not comparable") -> Reproduced to precision | I66: Tested the source-based convention shown in G against official published precision. Unmatched values remain unresolved; neither the standardized method nor the financial inputs were altered to force agreement. | J66: FY2025 AR p53 "Key financial data for the last six years" (per-share items split-adjusted 5:1) | K66: Market recheck | L66: Source comparison | M66: =IF(ISNUMBER(E66),E66-D66,"n/m") -> 0.002353218 | N66: =IF(ISNUMBER(F66),F66-D66,"n/m") -> 0.0031527804 | O66: 2
A67: KOHC | B67: Price earning ratio | C67: FY2023 | D67: 5.99 | E67: =KOHC!F172 -> 5.9860675 | F67: ='PSX Prices'!F8/(KOHC!F99/'PSX Prices'!O8) -> 5.9853773 | G67: Report price / unrounded report-basis EPS | H67: =IF(AND(ISNUMBER(D67),ISNUMBER(F67)),IF(ROUND(D67,O67)=ROUND(F67,O67),"Reproduced to precision","Unresolved published value"),"Not comparable") -> Reproduced to precision | I67: Tested the source-based convention shown in G against official published precision. Unmatched values remain unresolved; neither the standardized method nor the financial inputs were altered to force agreement. | J67: FY2025 AR p53 "Key financial data for the last six years" (per-share items split-adjusted 5:1) | K67: Market recheck | L67: Source comparison | M67: =IF(ISNUMBER(E67),E67-D67,"n/m") -> -0.003932511 | N67: =IF(ISNUMBER(F67),F67-D67,"n/m") -> -0.0046226669 | O67: 2
A68: KOHC | B68: Price earning ratio | C68: FY2024 | D68: 5.41 | E68: =KOHC!G172 -> 5.5313975 | F68: ='PSX Prices'!F9/(KOHC!G99/'PSX Prices'!O9) -> 5.4114619 | G68: Report price / unrounded report-basis EPS | H68: =IF(AND(ISNUMBER(D68),ISNUMBER(F68)),IF(ROUND(D68,O68)=ROUND(F68,O68),"Reproduced to precision","Unresolved published value"),"Not comparable") -> Reproduced to precision | I68: Tested the source-based convention shown in G against official published precision. Unmatched values remain unresolved; neither the standardized method nor the financial inputs were altered to force agreement. | J68: FY2025 AR p53 "Key financial data for the last six years" (per-share items split-adjusted 5:1) | K68: Market recheck | L68: Source comparison | M68: =IF(ISNUMBER(E68),E68-D68,"n/m") -> 0.12139753 | N68: =IF(ISNUMBER(F68),F68-D68,"n/m") -> 0.0014618635 | O68: 2
A69: KOHC | B69: Price earning ratio | C69: FY2025 | D69: 6.32 | E69: =KOHC!H172 -> 6.3393545 | F69: ='PSX Prices'!F10/(KOHC!H99/'PSX Prices'!O10) -> 6.3224768 | G69: Report price / unrounded report-basis EPS | H69: =IF(AND(ISNUMBER(D69),ISNUMBER(F69)),IF(ROUND(D69,O69)=ROUND(F69,O69),"Reproduced to precision","Unresolved published value"),"Not comparable") -> Reproduced to precision | I69: Tested the source-based convention shown in G against official published precision. Unmatched values remain unresolved; neither the standardized method nor the financial inputs were altered to force agreement. | J69: FY2025 AR p53 "Key financial data for the last six years" (per-share items split-adjusted 5:1) | K69: Market recheck | L69: Source comparison | M69: =IF(ISNUMBER(E69),E69-D69,"n/m") -> 0.019354531 | N69: =IF(ISNUMBER(F69),F69-D69,"n/m") -> 0.0024767686 | O69: 2
A70: KOHC | B70: Price to book ratio | C70: FY2021 | D70: 0.23 | E70: =KOHC!D170 -> 1.8663026 | F70: ='PSX Prices'!F6/'PSX Prices'!M6 -> 1.8662449 | G70: Report price / reported BVPS | H70: =IF(AND(ISNUMBER(D70),ISNUMBER(F70)),IF(ROUND(D70,O70)=ROUND(F70,O70),"Reproduced to precision","Unresolved published value"),"Not comparable") -> Unresolved published value | I70: Official glossary supports investigating tangible ASSETS rather than net book EQUITY. ColumnP tests one consistent diagnostic using the report share basis; it matches FY2024-25 and is five times FY2021-23 printed ratios. Mixed historical split treatment remains inconsistent with the report footnote. No historical PSX price or standardized ratio is adjusted. | J70: FY2025 AR p53 "Key financial data for the last six years" (per-share items split-adjusted 5:1) | K70: Published value unresolved | L70: Unresolved official market-series inconsistency | M70: =IF(ISNUMBER(E70),E70-D70,"n/m") -> 1.6363026 | N70: =IF(ISNUMBER(F70),F70-D70,"n/m") -> 1.6362449 | O70: 2 | P70: ='PSX Prices'!F6*'PSX Prices'!O6/(KOHC!D37-KOHC!D24) -> 1.1496018 | Q70: The official glossary (FY2025 PDF p54) refers to assets less intangibles, rather than equity. This uniform report-price x report-weighted-shares / tangible-assets diagnostic gives about1.15/0.60/0.70/0.82/1.10. FY2021-23 printed ratios are a further division by5; FY2024-25 match this alternative denominator. The glossary omits a per-share conversion and does not specify weighted shares. This is a strong official-source lead, not confirmation of a coherent P/B definition or split basis. Main MTB uses equity and the actual PSX close.
A71: KOHC | B71: Price to book ratio | C71: FY2022 | D71: 0.12 | E71: =KOHC!E170 -> 0.95932868 | F71: ='PSX Prices'!F7/'PSX Prices'!M7 -> 0.95945448 | G71: Report price / reported BVPS | H71: =IF(AND(ISNUMBER(D71),ISNUMBER(F71)),IF(ROUND(D71,O71)=ROUND(F71,O71),"Reproduced to precision","Unresolved published value"),"Not comparable") -> Unresolved published value | I71: Official glossary supports investigating tangible ASSETS rather than net book EQUITY. ColumnP tests one consistent diagnostic using the report share basis; it matches FY2024-25 and is five times FY2021-23 printed ratios. Mixed historical split treatment remains inconsistent with the report footnote. No historical PSX price or standardized ratio is adjusted. | J71: FY2025 AR p53 "Key financial data for the last six years" (per-share items split-adjusted 5:1) | K71: Published value unresolved | L71: Unresolved official market-series inconsistency | M71: =IF(ISNUMBER(E71),E71-D71,"n/m") -> 0.83932868 | N71: =IF(ISNUMBER(F71),F71-D71,"n/m") -> 0.83945448 | O71: 2 | P71: ='PSX Prices'!F7*'PSX Prices'!O7/(KOHC!E37-KOHC!E24) -> 0.60307553 | Q71: The official glossary (FY2025 PDF p54) refers to assets less intangibles, rather than equity. This uniform report-price x report-weighted-shares / tangible-assets diagnostic gives about1.15/0.60/0.70/0.82/1.10. FY2021-23 printed ratios are a further division by5; FY2024-25 match this alternative denominator. The glossary omits a per-share conversion and does not specify weighted shares. This is a strong official-source lead, not confirmation of a coherent P/B definition or split basis. Main MTB uses equity and the actual PSX close.
A72: KOHC | B72: Price to book ratio | C72: FY2023 | D72: 0.14 | E72: =KOHC!F170 -> 1.068487 | F72: ='PSX Prices'!F8/'PSX Prices'!M8 -> 1.0683708 | G72: Report price / reported BVPS | H72: =IF(AND(ISNUMBER(D72),ISNUMBER(F72)),IF(ROUND(D72,O72)=ROUND(F72,O72),"Reproduced to precision","Unresolved published value"),"Not comparable") -> Unresolved published value | I72: Official glossary supports investigating tangible ASSETS rather than net book EQUITY. ColumnP tests one consistent diagnostic using the report share basis; it matches FY2024-25 and is five times FY2021-23 printed ratios. Mixed historical split treatment remains inconsistent with the report footnote. No historical PSX price or standardized ratio is adjusted. | J72: FY2025 AR p53 "Key financial data for the last six years" (per-share items split-adjusted 5:1) | K72: Published value unresolved | L72: Unresolved official market-series inconsistency | M72: =IF(ISNUMBER(E72),E72-D72,"n/m") -> 0.928487 | N72: =IF(ISNUMBER(F72),F72-D72,"n/m") -> 0.9283708 | O72: 2 | P72: ='PSX Prices'!F8*'PSX Prices'!O8/(KOHC!F37-KOHC!F24) -> 0.70342099 | Q72: The official glossary (FY2025 PDF p54) refers to assets less intangibles, rather than equity. This uniform report-price x report-weighted-shares / tangible-assets diagnostic gives about1.15/0.60/0.70/0.82/1.10. FY2021-23 printed ratios are a further division by5; FY2024-25 match this alternative denominator. The glossary omits a per-share conversion and does not specify weighted shares. This is a strong official-source lead, not confirmation of a coherent P/B definition or split basis. Main MTB uses equity and the actual PSX close.
A73: KOHC | B73: Price to book ratio | C73: FY2024 | D73: 0.82 | E73: =KOHC!G170 -> 1.1937011 | F73: ='PSX Prices'!F9/'PSX Prices'!M9 -> 1.1711281 | G73: Report price / reported BVPS | H73: =IF(AND(ISNUMBER(D73),ISNUMBER(F73)),IF(ROUND(D73,O73)=ROUND(F73,O73),"Reproduced to precision","Unresolved published value"),"Not comparable") -> Unresolved published value | I73: Official glossary supports investigating tangible ASSETS rather than net book EQUITY. ColumnP tests one consistent diagnostic using the report share basis; it matches FY2024-25 and is five times FY2021-23 printed ratios. Mixed historical split treatment remains inconsistent with the report footnote. No historical PSX price or standardized ratio is adjusted. | J73: FY2025 AR p53 "Key financial data for the last six years" (per-share items split-adjusted 5:1) | K73: Published value unresolved | L73: Unresolved official market-series inconsistency | M73: =IF(ISNUMBER(E73),E73-D73,"n/m") -> 0.37370115 | N73: =IF(ISNUMBER(F73),F73-D73,"n/m") -> 0.35112811 | O73: 2 | P73: ='PSX Prices'!F9*'PSX Prices'!O9/(KOHC!G37-KOHC!G24) -> 0.8178843 | Q73: The official glossary (FY2025 PDF p54) refers to assets less intangibles, rather than equity. This uniform report-price x report-weighted-shares / tangible-assets diagnostic gives about1.15/0.60/0.70/0.82/1.10. FY2021-23 printed ratios are a further division by5; FY2024-25 match this alternative denominator. The glossary omits a per-share conversion and does not specify weighted shares. This is a strong official-source lead, not confirmation of a coherent P/B definition or split basis. Main MTB uses equity and the actual PSX close.
A74: KOHC | B74: Price to book ratio | C74: FY2025 | D74: 1.1 | E74: =KOHC!H170 -> 1.4544748 | F74: ='PSX Prices'!F10/'PSX Prices'!M10 -> 1.5262203 | G74: Report price / reported BVPS | H74: =IF(AND(ISNUMBER(D74),ISNUMBER(F74)),IF(ROUND(D74,O74)=ROUND(F74,O74),"Reproduced to precision","Unresolved published value"),"Not comparable") -> Unresolved published value | I74: Official glossary supports investigating tangible ASSETS rather than net book EQUITY. ColumnP tests one consistent diagnostic using the report share basis; it matches FY2024-25 and is five times FY2021-23 printed ratios. Mixed historical split treatment remains inconsistent with the report footnote. No historical PSX price or standardized ratio is adjusted. | J74: FY2025 AR p53 "Key financial data for the last six years" (per-share items split-adjusted 5:1) | K74: Published value unresolved | L74: Unresolved official market-series inconsistency | M74: =IF(ISNUMBER(E74),E74-D74,"n/m") -> 0.35447479 | N74: =IF(ISNUMBER(F74),F74-D74,"n/m") -> 0.42622025 | O74: 2 | P74: ='PSX Prices'!F10*'PSX Prices'!O10/(KOHC!H37-KOHC!H24) -> 1.0956611 | Q74: The official glossary (FY2025 PDF p54) refers to assets less intangibles, rather than equity. This uniform report-price x report-weighted-shares / tangible-assets diagnostic gives about1.15/0.60/0.70/0.82/1.10. FY2021-23 printed ratios are a further division by5; FY2024-25 match this alternative denominator. The glossary omits a per-share conversion and does not specify weighted shares. This is a strong official-source lead, not confirmation of a coherent P/B definition or split basis. Main MTB uses equity and the actual PSX close.
A75: KOHC | B75: Debt : equity (debt share of debt + equity) | C75: FY2021 | D75: 0.21 | E75: =KOHC!D157 -> 0.21400285 | F75: =KOHC!D66/(KOHC!D66+KOHC!D41) -> 0.21400285 | G75: Interest-bearing debt / (IBD + equity) | H75: =IF(AND(ISNUMBER(D75),ISNUMBER(F75)),IF(ROUND(D75,O75)=ROUND(F75,O75),"Reproduced to precision","Unresolved published value"),"Not comparable") -> Reproduced to precision | I75: Company prints debt : equity as whole-percentage shares of debt plus equity (e.g. 21:79); reconstruction is compared at that whole-percentage precision, not at two decimal percentage points. | J75: FY2025 AR p53 "Key financial data for the last six years" (per-share items split-adjusted 5:1) | K75: Agrees (same convention) | L75: Source comparison | M75: =IF(ISNUMBER(E75),E75-D75,"n/m") -> 0.0040028467 | N75: =IF(ISNUMBER(F75),F75-D75,"n/m") -> 0.0040028467 | O75: 2
A76: KOHC | B76: Debt : equity (debt share of debt + equity) | C76: FY2022 | D76: 0.13 | E76: =KOHC!E157 -> 0.13497287 | F76: =KOHC!E66/(KOHC!E66+KOHC!E41) -> 0.13497287 | G76: Interest-bearing debt / (IBD + equity) | H76: =IF(AND(ISNUMBER(D76),ISNUMBER(F76)),IF(ROUND(D76,O76)=ROUND(F76,O76),"Reproduced to precision","Unresolved published value"),"Not comparable") -> Reproduced to precision | I76: Company prints debt : equity as whole-percentage shares of debt plus equity (e.g. 21:79); reconstruction is compared at that whole-percentage precision, not at two decimal percentage points. | J76: FY2025 AR p53 "Key financial data for the last six years" (per-share items split-adjusted 5:1) | K76: Agrees (same convention) | L76: Source comparison | M76: =IF(ISNUMBER(E76),E76-D76,"n/m") -> 0.0049728728 | N76: =IF(ISNUMBER(F76),F76-D76,"n/m") -> 0.0049728728 | O76: 2
A77: KOHC | B77: Debt : equity (debt share of debt + equity) | C77: FY2023 | D77: 0.09 | E77: =KOHC!F157 -> 0.088937391 | F77: =KOHC!F66/(KOHC!F66+KOHC!F41) -> 0.088937391 | G77: Interest-bearing debt / (IBD + equity) | H77: =IF(AND(ISNUMBER(D77),ISNUMBER(F77)),IF(ROUND(D77,O77)=ROUND(F77,O77),"Reproduced to precision","Unresolved published value"),"Not comparable") -> Reproduced to precision | I77: Company prints debt : equity as whole-percentage shares of debt plus equity (e.g. 21:79); reconstruction is compared at that whole-percentage precision, not at two decimal percentage points. | J77: FY2025 AR p53 "Key financial data for the last six years" (per-share items split-adjusted 5:1) | K77: Agrees (same convention) | L77: Source comparison | M77: =IF(ISNUMBER(E77),E77-D77,"n/m") -> -0.0010626085 | N77: =IF(ISNUMBER(F77),F77-D77,"n/m") -> -0.0010626085 | O77: 2
A78: KOHC | B78: Debt : equity (debt share of debt + equity) | C78: FY2024 | D78: 0.05 | E78: =KOHC!G157 -> 0.049789363 | F78: =KOHC!G66/(KOHC!G66+KOHC!G41) -> 0.049789363 | G78: Interest-bearing debt / (IBD + equity) | H78: =IF(AND(ISNUMBER(D78),ISNUMBER(F78)),IF(ROUND(D78,O78)=ROUND(F78,O78),"Reproduced to precision","Unresolved published value"),"Not comparable") -> Reproduced to precision | I78: Company prints debt : equity as whole-percentage shares of debt plus equity (e.g. 21:79); reconstruction is compared at that whole-percentage precision, not at two decimal percentage points. | J78: FY2025 AR p53 "Key financial data for the last six years" (per-share items split-adjusted 5:1) | K78: Agrees (same convention) | L78: Source comparison | M78: =IF(ISNUMBER(E78),E78-D78,"n/m") -> -0.00021063672 | N78: =IF(ISNUMBER(F78),F78-D78,"n/m") -> -0.00021063672 | O78: 2
A79: KOHC | B79: Debt : equity (debt share of debt + equity) | C79: FY2025 | D79: 0.04 | E79: =KOHC!H157 -> 0.044675679 | F79: =KOHC!H66/(KOHC!H66+KOHC!H41) -> 0.044675679 | G79: Interest-bearing debt / (IBD + equity) | H79: =IF(AND(ISNUMBER(D79),ISNUMBER(F79)),IF(ROUND(D79,O79)=ROUND(F79,O79),"Reproduced to precision","Unresolved published value"),"Not comparable") -> Reproduced to precision | I79: Company prints debt : equity as whole-percentage shares of debt plus equity (e.g. 21:79); reconstruction is compared at that whole-percentage precision, not at two decimal percentage points. | J79: FY2025 AR p53 "Key financial data for the last six years" (per-share items split-adjusted 5:1) | K79: Agrees (company shows whole-number ratio, e.g. 21:79) | L79: Source comparison | M79: =IF(ISNUMBER(E79),E79-D79,"n/m") -> 0.0046756793 | N79: =IF(ISNUMBER(F79),F79-D79,"n/m") -> 0.0046756793 | O79: 2
A80: LUCK | B80: Inventory turnover | C80: FY2021 | D80: 3.81 | E80: =LUCK!D144 -> 3.8136073 | F80: =(-LUCK!D85)/AVERAGE(LUCK!C65,LUCK!D65) -> 3.8136073 | G80: COGS / average stores + stock | H80: =IF(AND(ISNUMBER(D80),ISNUMBER(F80)),IF(ROUND(D80,O80)=ROUND(F80,O80),"Reproduced to precision","Unresolved published value"),"Not comparable") -> Reproduced to precision | I80: Tested the source-based convention shown in G against official published precision. Unmatched values remain unresolved; neither the standardized method nor the financial inputs were altered to force agreement. | J80: FY2025 AR p166 "Horizontal / key ratio analysis" (per-share split-adjusted to Rs 2 basis) | K80: Agrees (same convention) | L80: Source comparison | M80: =IF(ISNUMBER(E80),E80-D80,"n/m") -> 0.0036073127 | N80: =IF(ISNUMBER(F80),F80-D80,"n/m") -> 0.0036073127 | O80: 2
A81: LUCK | B81: Inventory turnover | C81: FY2022 | D81: 3.66 | E81: =LUCK!E144 -> 3.6577331 | F81: =(-LUCK!E85)/AVERAGE(LUCK!D65,LUCK!E65) -> 3.6577331 | G81: COGS / average stores + stock | H81: =IF(AND(ISNUMBER(D81),ISNUMBER(F81)),IF(ROUND(D81,O81)=ROUND(F81,O81),"Reproduced to precision","Unresolved published value"),"Not comparable") -> Reproduced to precision | I81: Tested the source-based convention shown in G against official published precision. Unmatched values remain unresolved; neither the standardized method nor the financial inputs were altered to force agreement. | J81: FY2025 AR p166 "Horizontal / key ratio analysis" (per-share split-adjusted to Rs 2 basis) | K81: Agrees (same convention) | L81: Source comparison | M81: =IF(ISNUMBER(E81),E81-D81,"n/m") -> -0.0022668739 | N81: =IF(ISNUMBER(F81),F81-D81,"n/m") -> -0.0022668739 | O81: 2
A82: LUCK | B82: Inventory turnover | C82: FY2023 | D82: 3.62 | E82: =LUCK!F144 -> 3.6234818 | F82: =(-LUCK!F85)/AVERAGE(LUCK!E65,LUCK!F65) -> 3.6234818 | G82: COGS / average stores + stock | H82: =IF(AND(ISNUMBER(D82),ISNUMBER(F82)),IF(ROUND(D82,O82)=ROUND(F82,O82),"Reproduced to precision","Unresolved published value"),"Not comparable") -> Reproduced to precision | I82: Tested the source-based convention shown in G against official published precision. Unmatched values remain unresolved; neither the standardized method nor the financial inputs were altered to force agreement. | J82: FY2025 AR p166 "Horizontal / key ratio analysis" (per-share split-adjusted to Rs 2 basis) | K82: Agrees (same convention) | L82: Source comparison | M82: =IF(ISNUMBER(E82),E82-D82,"n/m") -> 0.0034818388 | N82: =IF(ISNUMBER(F82),F82-D82,"n/m") -> 0.0034818388 | O82: 2
A83: LUCK | B83: Inventory turnover | C83: FY2024 | D83: 3.54 | E83: =LUCK!G144 -> 3.54017 | F83: =(-LUCK!G85)/AVERAGE(LUCK!F65,LUCK!G65) -> 3.54017 | G83: COGS / average stores + stock | H83: =IF(AND(ISNUMBER(D83),ISNUMBER(F83)),IF(ROUND(D83,O83)=ROUND(F83,O83),"Reproduced to precision","Unresolved published value"),"Not comparable") -> Reproduced to precision | I83: Tested the source-based convention shown in G against official published precision. Unmatched values remain unresolved; neither the standardized method nor the financial inputs were altered to force agreement. | J83: FY2025 AR p166 "Horizontal / key ratio analysis" (per-share split-adjusted to Rs 2 basis) | K83: Agrees (same convention) | L83: Source comparison | M83: =IF(ISNUMBER(E83),E83-D83,"n/m") -> 0.00016995509 | N83: =IF(ISNUMBER(F83),F83-D83,"n/m") -> 0.00016995509 | O83: 2
A84: LUCK | B84: Inventory turnover | C84: FY2025 | D84: 3.43 | E84: =LUCK!H144 -> 3.426095 | F84: =(-LUCK!H85)/AVERAGE(LUCK!G65,LUCK!H65) -> 3.426095 | G84: COGS / average stores + stock | H84: =IF(AND(ISNUMBER(D84),ISNUMBER(F84)),IF(ROUND(D84,O84)=ROUND(F84,O84),"Reproduced to precision","Unresolved published value"),"Not comparable") -> Reproduced to precision | I84: Tested the source-based convention shown in G against official published precision. Unmatched values remain unresolved; neither the standardized method nor the financial inputs were altered to force agreement. | J84: FY2025 AR p166 "Horizontal / key ratio analysis" (per-share split-adjusted to Rs 2 basis) | K84: Agrees (same convention) | L84: Source comparison | M84: =IF(ISNUMBER(E84),E84-D84,"n/m") -> -0.0039050474 | N84: =IF(ISNUMBER(F84),F84-D84,"n/m") -> -0.0039050474 | O84: 2
A85: LUCK | B85: No. of days in receivables | C85: FY2021 | D85: 17.78 | E85: =LUCK!D148 -> 17.782498 | F85: =365*AVERAGE(LUCK!C32,LUCK!D32)/LUCK!D84 -> 17.782498 | G85: 365 x average trade debts / sales | H85: =IF(AND(ISNUMBER(D85),ISNUMBER(F85)),IF(ROUND(D85,O85)=ROUND(F85,O85),"Reproduced to precision","Unresolved published value"),"Not comparable") -> Reproduced to precision | I85: Tested the source-based convention shown in G against official published precision. Unmatched values remain unresolved; neither the standardized method nor the financial inputs were altered to force agreement. | J85: FY2025 AR p166 "Horizontal / key ratio analysis" (per-share split-adjusted to Rs 2 basis) | K85: Agrees (same convention) | L85: Source comparison | M85: =IF(ISNUMBER(E85),E85-D85,"n/m") -> 0.0024983332 | N85: =IF(ISNUMBER(F85),F85-D85,"n/m") -> 0.0024983332 | O85: 2
A86: LUCK | B86: No. of days in receivables | C86: FY2022 | D86: 14.03 | E86: =LUCK!E148 -> 14.027318 | F86: =365*AVERAGE(LUCK!D32,LUCK!E32)/LUCK!E84 -> 14.027318 | G86: 365 x average trade debts / sales | H86: =IF(AND(ISNUMBER(D86),ISNUMBER(F86)),IF(ROUND(D86,O86)=ROUND(F86,O86),"Reproduced to precision","Unresolved published value"),"Not comparable") -> Reproduced to precision | I86: Tested the source-based convention shown in G against official published precision. Unmatched values remain unresolved; neither the standardized method nor the financial inputs were altered to force agreement. | J86: FY2025 AR p166 "Horizontal / key ratio analysis" (per-share split-adjusted to Rs 2 basis) | K86: Agrees (same convention) | L86: Source comparison | M86: =IF(ISNUMBER(E86),E86-D86,"n/m") -> -0.002681666 | N86: =IF(ISNUMBER(F86),F86-D86,"n/m") -> -0.002681666 | O86: 2
A87: LUCK | B87: No. of days in receivables | C87: FY2023 | D87: 16.4 | E87: =LUCK!F148 -> 16.401585 | F87: =365*AVERAGE(LUCK!E32,LUCK!F32)/LUCK!F84 -> 16.401585 | G87: 365 x average trade debts / sales | H87: =IF(AND(ISNUMBER(D87),ISNUMBER(F87)),IF(ROUND(D87,O87)=ROUND(F87,O87),"Reproduced to precision","Unresolved published value"),"Not comparable") -> Reproduced to precision | I87: Tested the source-based convention shown in G against official published precision. Unmatched values remain unresolved; neither the standardized method nor the financial inputs were altered to force agreement. | J87: FY2025 AR p166 "Horizontal / key ratio analysis" (per-share split-adjusted to Rs 2 basis) | K87: Agrees (same convention) | L87: Source comparison | M87: =IF(ISNUMBER(E87),E87-D87,"n/m") -> 0.0015853156 | N87: =IF(ISNUMBER(F87),F87-D87,"n/m") -> 0.0015853156 | O87: 2
A88: LUCK | B88: No. of days in receivables | C88: FY2024 | D88: 19.02 | E88: =LUCK!G148 -> 19.024867 | F88: =365*AVERAGE(LUCK!F32,LUCK!G32)/LUCK!G84 -> 19.024867 | G88: 365 x average trade debts / sales | H88: =IF(AND(ISNUMBER(D88),ISNUMBER(F88)),IF(ROUND(D88,O88)=ROUND(F88,O88),"Reproduced to precision","Unresolved published value"),"Not comparable") -> Reproduced to precision | I88: Tested the source-based convention shown in G against official published precision. Unmatched values remain unresolved; neither the standardized method nor the financial inputs were altered to force agreement. | J88: FY2025 AR p166 "Horizontal / key ratio analysis" (per-share split-adjusted to Rs 2 basis) | K88: Agrees (same convention) | L88: Source comparison | M88: =IF(ISNUMBER(E88),E88-D88,"n/m") -> 0.0048666676 | N88: =IF(ISNUMBER(F88),F88-D88,"n/m") -> 0.0048666676 | O88: 2
A89: LUCK | B89: No. of days in receivables | C89: FY2025 | D89: 19.48 | E89: =LUCK!H148 -> 19.473146 | F89: =365*AVERAGE(LUCK!G32,LUCK!H32)/LUCK!H84 -> 19.473146 | G89: 365 x average trade debts / sales | H89: =IF(AND(ISNUMBER(D89),ISNUMBER(F89)),IF(ROUND(D89,O89)=ROUND(F89,O89),"Reproduced to precision","Unresolved published value"),"Not comparable") -> Unresolved published value | I89: Tested the source-based convention shown in G against official published precision. Unmatched values remain unresolved; neither the standardized method nor the financial inputs were altered to force agreement. | J89: FY2025 AR p166 "Horizontal / key ratio analysis" (per-share split-adjusted to Rs 2 basis) | K89: Agrees within 0.01 (rounding of inputs) | L89: Source comparison | M89: =IF(ISNUMBER(E89),E89-D89,"n/m") -> -0.0068543785 | N89: =IF(ISNUMBER(F89),F89-D89,"n/m") -> -0.0068543785 | O89: 2
A90: LUCK | B90: No. of days in payables | C90: FY2021 | D90: 166.67 | E90: =LUCK!D149 -> 22.744516 | F90: =365/(ROUND((-LUCK!D85)/AVERAGE(LUCK!C50,LUCK!D50),2)) -> 166.66667 | G90: COGS / average total trade AND other payables; rounded turnover before days | H90: =IF(AND(ISNUMBER(D90),ISNUMBER(F90)),IF(ROUND(D90,O90)=ROUND(F90,O90),"Reproduced to precision","Unresolved published value"),"Not comparable") -> Reproduced to precision | I90: Report p166 prints both creditor turnover and days. COGS / average TOTAL trade-and-other-payables rounds to the printed turnover; 365 / that rounded turnover reproduces all five days. The published denominator includes accruals and statutory payables that the uniform supplier balance excludes. | J90: FY2025 AR p166 "Horizontal / key ratio analysis" (per-share split-adjusted to Rs 2 basis) | K90: Not reproduced | L90: Published methodology difference (reconstructed) | M90: =IF(ISNUMBER(E90),E90-D90,"n/m") -> -143.92548 | N90: =IF(ISNUMBER(F90),F90-D90,"n/m") -> -0.0033333333 | O90: 2
A91: LUCK | B91: No. of days in payables | C91: FY2022 | D91: 137.22 | E91: =LUCK!E149 -> 19.438565 | F91: =365/(ROUND((-LUCK!E85)/AVERAGE(LUCK!D50,LUCK!E50),2)) -> 137.21805 | G91: COGS / average total trade AND other payables; rounded turnover before days | H91: =IF(AND(ISNUMBER(D91),ISNUMBER(F91)),IF(ROUND(D91,O91)=ROUND(F91,O91),"Reproduced to precision","Unresolved published value"),"Not comparable") -> Reproduced to precision | I91: Report p166 prints both creditor turnover and days. COGS / average TOTAL trade-and-other-payables rounds to the printed turnover; 365 / that rounded turnover reproduces all five days. The published denominator includes accruals and statutory payables that the uniform supplier balance excludes. | J91: FY2025 AR p166 "Horizontal / key ratio analysis" (per-share split-adjusted to Rs 2 basis) | K91: Not reproduced | L91: Published methodology difference (reconstructed) | M91: =IF(ISNUMBER(E91),E91-D91,"n/m") -> -117.78143 | N91: =IF(ISNUMBER(F91),F91-D91,"n/m") -> -0.0019548872 | O91: 2
A92: LUCK | B92: No. of days in payables | C92: FY2023 | D92: 138.78 | E92: =LUCK!F149 -> 21.928688 | F92: =365/(ROUND((-LUCK!F85)/AVERAGE(LUCK!E50,LUCK!F50),2)) -> 138.78327 | G92: COGS / average total trade AND other payables; rounded turnover before days | H92: =IF(AND(ISNUMBER(D92),ISNUMBER(F92)),IF(ROUND(D92,O92)=ROUND(F92,O92),"Reproduced to precision","Unresolved published value"),"Not comparable") -> Reproduced to precision | I92: Report p166 prints both creditor turnover and days. COGS / average TOTAL trade-and-other-payables rounds to the printed turnover; 365 / that rounded turnover reproduces all five days. The published denominator includes accruals and statutory payables that the uniform supplier balance excludes. | J92: FY2025 AR p166 "Horizontal / key ratio analysis" (per-share split-adjusted to Rs 2 basis) | K92: Not reproduced | L92: Published methodology difference (reconstructed) | M92: =IF(ISNUMBER(E92),E92-D92,"n/m") -> -116.85131 | N92: =IF(ISNUMBER(F92),F92-D92,"n/m") -> 0.003269962 | O92: 2
A93: LUCK | B93: No. of days in payables | C93: FY2024 | D93: 143.14 | E93: =LUCK!G149 -> 29.103243 | F93: =365/(ROUND((-LUCK!G85)/AVERAGE(LUCK!F50,LUCK!G50),2)) -> 143.13725 | G93: COGS / average total trade AND other payables; rounded turnover before days | H93: =IF(AND(ISNUMBER(D93),ISNUMBER(F93)),IF(ROUND(D93,O93)=ROUND(F93,O93),"Reproduced to precision","Unresolved published value"),"Not comparable") -> Reproduced to precision | I93: Report p166 prints both creditor turnover and days. COGS / average TOTAL trade-and-other-payables rounds to the printed turnover; 365 / that rounded turnover reproduces all five days. The published denominator includes accruals and statutory payables that the uniform supplier balance excludes. | J93: FY2025 AR p166 "Horizontal / key ratio analysis" (per-share split-adjusted to Rs 2 basis) | K93: Not reproduced | L93: Published methodology difference (reconstructed) | M93: =IF(ISNUMBER(E93),E93-D93,"n/m") -> -114.03676 | N93: =IF(ISNUMBER(F93),F93-D93,"n/m") -> -0.002745098 | O93: 2
A94: LUCK | B94: No. of days in payables | C94: FY2025 | D94: 127.62 | E94: =LUCK!H149 -> 30.330299 | F94: =365/(ROUND((-LUCK!H85)/AVERAGE(LUCK!G50,LUCK!H50),2)) -> 127.62238 | G94: COGS / average total trade AND other payables; rounded turnover before days | H94: =IF(AND(ISNUMBER(D94),ISNUMBER(F94)),IF(ROUND(D94,O94)=ROUND(F94,O94),"Reproduced to precision","Unresolved published value"),"Not comparable") -> Reproduced to precision | I94: Report p166 prints both creditor turnover and days. COGS / average TOTAL trade-and-other-payables rounds to the printed turnover; 365 / that rounded turnover reproduces all five days. The published denominator includes accruals and statutory payables that the uniform supplier balance excludes. | J94: FY2025 AR p166 "Horizontal / key ratio analysis" (per-share split-adjusted to Rs 2 basis) | K94: Not reproduced | L94: Published methodology difference (reconstructed) | M94: =IF(ISNUMBER(E94),E94-D94,"n/m") -> -97.289701 | N94: =IF(ISNUMBER(F94),F94-D94,"n/m") -> 0.0023776224 | O94: 2
A95: LUCK | B95: Total assets turnover | C95: FY2021 | D95: 0.4 | E95: =LUCK!D152 -> 0.43075247 | F95: =LUCK!D84/LUCK!D37 -> 0.40251701 | G95: Sales / closing assets | H95: =IF(AND(ISNUMBER(D95),ISNUMBER(F95)),IF(ROUND(D95,O95)=ROUND(F95,O95),"Reproduced to precision","Unresolved published value"),"Not comparable") -> Reproduced to precision | I95: Tested the source-based convention shown in G against official published precision. Unmatched values remain unresolved; neither the standardized method nor the financial inputs were altered to force agreement. | J95: FY2025 AR p166 "Horizontal / key ratio analysis" (per-share split-adjusted to Rs 2 basis) | K95: Reconciled (company convention) | L95: Source comparison | M95: =IF(ISNUMBER(E95),E95-D95,"n/m") -> 0.030752471 | N95: =IF(ISNUMBER(F95),F95-D95,"n/m") -> 0.0025170114 | O95: 2
A96: LUCK | B96: Total assets turnover | C96: FY2022 | D96: 0.44 | E96: =LUCK!E152 -> 0.47516141 | F96: =LUCK!E84/LUCK!E37 -> 0.43843256 | G96: Sales / closing assets | H96: =IF(AND(ISNUMBER(D96),ISNUMBER(F96)),IF(ROUND(D96,O96)=ROUND(F96,O96),"Reproduced to precision","Unresolved published value"),"Not comparable") -> Reproduced to precision | I96: Tested the source-based convention shown in G against official published precision. Unmatched values remain unresolved; neither the standardized method nor the financial inputs were altered to force agreement. | J96: FY2025 AR p166 "Horizontal / key ratio analysis" (per-share split-adjusted to Rs 2 basis) | K96: Reconciled (company convention) | L96: Source comparison | M96: =IF(ISNUMBER(E96),E96-D96,"n/m") -> 0.035161415 | N96: =IF(ISNUMBER(F96),F96-D96,"n/m") -> -0.0015674373 | O96: 2
A97: LUCK | B97: Total assets turnover | C97: FY2023 | D97: 0.45 | E97: =LUCK!F152 -> 0.48151845 | F97: =LUCK!F84/LUCK!F37 -> 0.44974923 | G97: Sales / closing assets | H97: =IF(AND(ISNUMBER(D97),ISNUMBER(F97)),IF(ROUND(D97,O97)=ROUND(F97,O97),"Reproduced to precision","Unresolved published value"),"Not comparable") -> Reproduced to precision | I97: Tested the source-based convention shown in G against official published precision. Unmatched values remain unresolved; neither the standardized method nor the financial inputs were altered to force agreement. | J97: FY2025 AR p166 "Horizontal / key ratio analysis" (per-share split-adjusted to Rs 2 basis) | K97: Reconciled (company convention) | L97: Source comparison | M97: =IF(ISNUMBER(E97),E97-D97,"n/m") -> 0.031518448 | N97: =IF(ISNUMBER(F97),F97-D97,"n/m") -> -0.00025076677 | O97: 2
A98: LUCK | B98: Total assets turnover | C98: FY2024 | D98: 0.49 | E98: =LUCK!G152 -> 0.51588314 | F98: =LUCK!G84/LUCK!G37 -> 0.49280353 | G98: Sales / closing assets | H98: =IF(AND(ISNUMBER(D98),ISNUMBER(F98)),IF(ROUND(D98,O98)=ROUND(F98,O98),"Reproduced to precision","Unresolved published value"),"Not comparable") -> Reproduced to precision | I98: Tested the source-based convention shown in G against official published precision. Unmatched values remain unresolved; neither the standardized method nor the financial inputs were altered to force agreement. | J98: FY2025 AR p166 "Horizontal / key ratio analysis" (per-share split-adjusted to Rs 2 basis) | K98: Reconciled (company convention) | L98: Source comparison | M98: =IF(ISNUMBER(E98),E98-D98,"n/m") -> 0.025883137 | N98: =IF(ISNUMBER(F98),F98-D98,"n/m") -> 0.002803535 | O98: 2
A99: LUCK | B99: Total assets turnover | C99: FY2025 | D99: 0.47 | E99: =LUCK!H152 -> 0.49728502 | F99: =LUCK!H84/LUCK!H37 -> 0.46677662 | G99: Sales / closing assets | H99: =IF(AND(ISNUMBER(D99),ISNUMBER(F99)),IF(ROUND(D99,O99)=ROUND(F99,O99),"Reproduced to precision","Unresolved published value"),"Not comparable") -> Reproduced to precision | I99: Tested the source-based convention shown in G against official published precision. Unmatched values remain unresolved; neither the standardized method nor the financial inputs were altered to force agreement. | J99: FY2025 AR p166 "Horizontal / key ratio analysis" (per-share split-adjusted to Rs 2 basis) | K99: Reconciled (company convention) | L99: Source comparison | M99: =IF(ISNUMBER(E99),E99-D99,"n/m") -> 0.027285016 | N99: =IF(ISNUMBER(F99),F99-D99,"n/m") -> -0.0032233794 | O99: 2
A100: LUCK | B100: Fixed assets turnover | C100: FY2021 | D100: 1.01 | E100: =LUCK!D153 -> 1.0641934 | F100: =LUCK!D84/(LUCK!D20+LUCK!D24) -> 1.0088184 | G100: Sales / closing fixed-assets caption (PPE + intangible assets) | H100: =IF(AND(ISNUMBER(D100),ISNUMBER(F100)),IF(ROUND(D100,O100)=ROUND(F100,O100),"Reproduced to precision","Unresolved published value"),"Not comparable") -> Reproduced to precision | I100: Official asset statement groups PPE and intangible assets under Fixed assets. Using that closing subtotal reproduces all five published values, including the former0.01 FY2022/24 gaps. Standardized FAT remains sales / average operating PPE excluding CWIP. | J100: FY2025 AR p166 "Horizontal / key ratio analysis" (per-share split-adjusted to Rs 2 basis) | K100: Reconciled (company convention) | L100: Published fixed-asset scope and closing-balance difference | M100: =IF(ISNUMBER(E100),E100-D100,"n/m") -> 0.054193408 | N100: =IF(ISNUMBER(F100),F100-D100,"n/m") -> -0.0011815586 | O100: 2
A101: LUCK | B101: Fixed assets turnover | C101: FY2022 | D101: 0.98 | E101: =LUCK!E153 -> 1.3656162 | F101: =LUCK!E84/(LUCK!E20+LUCK!E24) -> 0.98471354 | G101: Sales / closing fixed-assets caption (PPE + intangible assets) | H101: =IF(AND(ISNUMBER(D101),ISNUMBER(F101)),IF(ROUND(D101,O101)=ROUND(F101,O101),"Reproduced to precision","Unresolved published value"),"Not comparable") -> Reproduced to precision | I101: Official asset statement groups PPE and intangible assets under Fixed assets. Using that closing subtotal reproduces all five published values, including the former0.01 FY2022/24 gaps. Standardized FAT remains sales / average operating PPE excluding CWIP. | J101: FY2025 AR p166 "Horizontal / key ratio analysis" (per-share split-adjusted to Rs 2 basis) | K101: Agrees within 0.01 (rounding of inputs) | L101: Published fixed-asset scope and closing-balance difference | M101: =IF(ISNUMBER(E101),E101-D101,"n/m") -> 0.38561619 | N101: =IF(ISNUMBER(F101),F101-D101,"n/m") -> 0.0047135363 | O101: 2
...

Sheet KOHC
A1: Kohat Cement Company Limited (KOHC) - five-year financial analysis, FY2021-FY2025
A2: Main company | PSX: KOHC | Standalone (single-entity financial statements; no consolidated statements published) | All amounts PKR million unless stated
A3: SOURCE INPUTS retained. Ratio tables below are ARCHIVED prior-33-measure workings; use 27 Calculations for final results. Blue = audited input; black = formula.
A5: A. COMPANY AND DATA INFORMATION
A6: Company | B6: Kohat Cement Company Limited
A7: PSX symbol | B7: KOHC
A8: Role in project | B8: Main company
A9: Financial year-end | B9: 30 June (FY2021 = year ended 30 June 2021, etc.)
A10: Reporting basis | B10: Standalone (single-entity financial statements; no consolidated statements published)
A11: Original audited units | B11: Rupees - normalised here to PKR million (full precision retained)
A12: Annual reports used | B12: FY2021: KOHC_AR_2021.pdf; FY2022: Kohat_Cement_AR_2022.pdf; FY2023: Financial_Statements-30-06-2023.pdf; FY2024: Kohat_Cement_Annual_Report-2024.pdf; FY2025: Kohat_Cement_Annual_Report_2025.pdf
A13: Year selection rule | B13: Each year taken from the most recent audited presentation: FY2025 from FY2025 AR; FY2020-FY2024 from the comparative column of the following year's AR (captures restatements). FY2020 = opening balances only.
A14: Per-share basis | B14: Actual PSX FY-end close paired with the share basis in force on that date. EPS notes, splits, treasury shares and bonus treatment are documented on Share Basis.
A15: Source register | B15: Every blue input is listed with report, statement, PDF page, printed page and remarks on the Sources & Validation sheet.
A17: Item | B17: Definition / formula / source note | C17: FY2020* | D17: FY2021 | E17: FY2022 | F17: FY2023 | G17: FY2024 | H17: FY2025 | I17: Units | J17: Comments
A18: B. STATEMENT OF FINANCIAL POSITION (PKR million; FY2020 = opening balances only)
A19: Non-current assets
A20: Property, plant and equipment (as presented) | B20: Input - see register KOHC|ppe | C20: 22777.666 | D20: 22027.545 | E20: 21331.296 | F20: 22229.434 | G20: 22156.641 | H20: 23359.981 | I20: PKR m
A21: of which: capital work-in-progress (note) | B21: Input - see register KOHC|cwip | C21: 164.57802 | D21: 273.93956 | E21: 130.89795 | F21: 1943.0196 | G21: 999.3266 | H21: 2486.6348 | I21: PKR m
A22: Operating fixed assets = PPE less CWIP | B22: PPE - CWIP | C22: =C20-C21 -> 22613.088 | D22: =D20-D21 -> 21753.605 | E22: =E20-E21 -> 21200.398 | F22: =F20-F21 -> 20286.415 | G22: =G20-G21 -> 21157.314 | H22: =H20-H21 -> 20873.346 | I22: PKR m
A23: Right-of-use assets (presented separately) | B23: Input - see register KOHC|rou | C23: 0 | D23: 0 | E23: 0 | F23: 0 | G23: 0 | H23: 0 | I23: PKR m
A24: Intangible assets | B24: Input - see register KOHC|intang | C24: 11.210982 | D24: 6.725911 | E24: 2.701357 | F24: 1.567709 | G24: 0.508226 | H24: 0.259742 | I24: PKR m
A25: Investment property | B25: Input - see register KOHC|inv_prop | C25: 3691.8396 | D25: 4134.0862 | E25: 4134.2552 | F25: 4324.9107 | G25: 4326.3616 | H25: 4326.3616 | I25: PKR m
A26: Long-term investments | B26: Input - see register KOHC|lt_inv | C26: 0 | D26: 0 | E26: 0 | F26: 0 | G26: 0 | H26: 0 | I26: PKR m
A27: Other non-current assets | B27: Input - see register KOHC|nca_other | C27: 38.32664 | D27: 69.76574 | E27: 106.58347 | F27: 60.785981 | G27: 147.38811 | H27: 492.91746 | I27: PKR m
A28: Total non-current assets | B28: Sum of above (excl. memo) | C28: =C20+C23+C24+C25+C26+C27 -> 26519.044 | D28: =D20+D23+D24+D25+D26+D27 -> 26238.123 | E28: =E20+E23+E24+E25+E26+E27 -> 25574.836 | F28: =F20+F23+F24+F25+F26+F27 -> 26616.699 | G28: =G20+G23+G24+G25+G26+G27 -> 26630.898 | H28: =H20+H23+H24+H25+H26+H27 -> 28179.519 | I28: PKR m
A29: Current assets
A30: Stores, spares and loose tools | B30: Input - see register KOHC|stores | C30: 2250.1564 | D30: 3070.7691 | E30: 4214.8296 | F30: 4713.1298 | G30: 5785.6835 | H30: 4991.3115 | I30: PKR m
A31: Stock-in-trade | B31: Input - see register KOHC|sit | C31: 1016.0242 | D31: 1112.7763 | E31: 1456.1568 | F31: 2942.8616 | G31: 1793.7424 | H31: 2513.5566 | I31: PKR m
A32: Trade debts | B32: Input - see register KOHC|debts | C32: 494.31521 | D32: 983.56822 | E32: 916.03947 | F32: 1205.5534 | G32: 2110.2479 | H32: 1692.2178 | I32: PKR m
A33: Short-term investments | B33: Input - see register KOHC|st_inv | C33: 160.1306 | D33: 2999.4964 | E33: 10124.096 | F33: 12335.074 | G33: 20279.746 | H33: 26941.632 | I33: PKR m
A34: Cash and bank balances | B34: Input - see register KOHC|cash | C34: 891.60609 | D34: 1197.7294 | E34: 480.76563 | F34: 933.53719 | G34: 1102.6492 | H34: 1450.7027 | I34: PKR m
A35: Other current assets | B35: Input - see register KOHC|ca_other | C35: 425.39123 | D35: 484.45935 | E35: 583.94424 | F35: 783.22095 | G35: 1140.3278 | H35: 1025.3717 | I35: PKR m
A36: Total current assets | B36: stores+sit+debts+st_inv+cash+ca_other | C36: =C30+C31+C32+C33+C34+C35 -> 5237.6238 | D36: =D30+D31+D32+D33+D34+D35 -> 9848.7987 | E36: =E30+E31+E32+E33+E34+E35 -> 17775.831 | F36: =F30+F31+F32+F33+F34+F35 -> 22913.377 | G36: =G30+G31+G32+G33+G34+G35 -> 32212.397 | H36: =H30+H31+H32+H33+H34+H35 -> 38614.792 | I36: PKR m
A37: TOTAL ASSETS | B37: tot_nca+tot_ca | C37: =C28+C36 -> 31756.667 | D37: =D28+D36 -> 36086.921 | E37: =E28+E36 -> 43350.668 | F37: =F28+F36 -> 49530.076 | G37: =G28+G36 -> 58843.295 | H37: =H28+H36 -> 66794.312 | I37: PKR m
A38: Equity
A39: Issued, subscribed and paid-up share capital | B39: Input - see register KOHC|share_cap | C39: 2008.613 | D39: 2008.613 | E39: 2008.613 | F39: 2008.613 | G39: 1958.613 | H39: 1838.613 | I39: PKR m
A40: Reserves, retained earnings and revaluation surplus | B40: Input - see register KOHC|eq_other | C40: 16718.06 | D40: 20214.926 | E40: 25237.607 | F40: 30601.432 | G40: 39131.692 | H40: 46116.582 | I40: PKR m
A41: Total equity | B41: share_cap+eq_other | C41: =C39+C40 -> 18726.673 | D41: =D39+D40 -> 22223.539 | E41: =E39+E40 -> 27246.22 | F41: =F39+F40 -> 32610.045 | G41: =G39+G40 -> 41090.305 | H41: =H39+H40 -> 47955.195 | I41: PKR m
A42: Non-current liabilities
A43: Long-term financing (non-current, interest-bearing) | B43: Input - see register KOHC|ltf_nc | C43: 5439.2261 | D43: 4405.7653 | E43: 3179.4001 | F43: 2149.0174 | G43: 1118.6425 | H43: 1448.9778 | I43: PKR m
A44: Lease liabilities (non-current) | B44: Input - see register KOHC|lease_nc | C44: 0 | D44: 0 | E44: 0 | F44: 0 | G44: 0 | H44: 0 | I44: PKR m
A45: Deferred government grant (non-current) | B45: Input - see register KOHC|grant_nc | C45: 0 | D45: 1.328937 | E45: 0 | F45: 0 | G45: 0 | H45: 0 | I45: PKR m
A46: Deferred tax liability | B46: Input - see register KOHC|def_tax | C46: 1287.9421 | D46: 1857.6493 | E46: 3407.3736 | F46: 4823.1584 | G46: 5505.824 | H46: 5688.116 | I46: PKR m
A47: Other non-current liabilities | B47: Input - see register KOHC|ncl_other | C47: 23.277456 | D47: 26.394536 | E47: 29.683198 | F47: 35.383341 | G47: 32.887203 | H47: 40.322031 | I47: PKR m
A48: Total non-current liabilities | B48: ltf_nc+lease_nc+grant_nc+def_tax+ncl_other | C48: =C43+C44+C45+C46+C47 -> 6750.4457 | D48: =D43+D44+D45+D46+D47 -> 6291.1381 | E48: =E43+E44+E45+E46+E47 -> 6616.4569 | F48: =F43+F44+F45+F46+F47 -> 7007.5592 | G48: =G43+G44+G45+G46+G47 -> 6657.3537 | H48: =H43+H44+H45+H46+H47 -> 7177.4159 | I48: PKR m
A49: Current liabilities
A50: Trade and other payables | B50: Input - see register KOHC|tap | C50: 4293.2054 | D50: 4985.3855 | E50: 5525.2212 | F50: 5307.0754 | G50: 6223.1533 | H50: 7710.0124 | I50: PKR m
A51: memo: trade creditors / bills payable (note) | B51: Input - see register KOHC|trade_cred | C51: 1091.301 | D51: 1555.1575 | E51: 1281.5598 | F51: 674.67428 | G51: 1781.4469 | H51: 2107.136 | I51: PKR m
A52: Contract liabilities / advances from customers | B52: Input - see register KOHC|contract | C52: 126.58269 | D52: 137.0915 | E52: 264.98441 | F52: 253.13594 | G52: 113.41861 | H52: 144.30091 | I52: PKR m
A53: Accrued mark-up / interest | B53: Input - see register KOHC|acc_markup | C53: 208.76676 | D53: 122.61397 | E53: 142.17199 | F53: 192.67479 | G53: 0 | H53: 0 | I53: PKR m
A54: Short-term borrowings (incl. running finance; FCCL parent loan) | B54: Input - see register KOHC|stb | C54: 1301.6091 | D54: 498 | E54: 0 | F54: 0 | G54: 0.061253 | H54: 3.704884 | I54: PKR m
A55: Current portion of long-term financing | B55: Input - see register KOHC|cp_ltf | C55: 248.49632 | D55: 1147.0208 | E55: 1071.9124 | F55: 1034.3559 | G55: 1169.2956 | H55: 837.35926 | I55: PKR m
A56: Current portion of lease liabilities | B56: Input - see register KOHC|cp_lease | C56: 0 | D56: 0 | E56: 0 | F56: 0 | G56: 0 | H56: 0 | I56: PKR m
A57: Current portion of deferred government grant | B57: Input - see register KOHC|cp_grant | C57: 0 | D57: 0 | E57: 0 | F57: 0 | G57: 0 | H57: 0 | I57: PKR m
A58: Unclaimed / unpaid dividends | B58: Input - see register KOHC|div_liab | C58: 48.014348 | D58: 46.197552 | E58: 45.648049 | F58: 45.47522 | G58: 45.338931 | H58: 42.181257 | I58: PKR m
A59: Taxation payable (net) | B59: Input - see register KOHC|tax_liab | C59: 52.873661 | D59: 635.93454 | E59: 2438.0527 | F59: 3079.7542 | G59: 3544.3685 | H59: 2924.1424 | I59: PKR m
A60: Other current liabilities | B60: Input - see register KOHC|cl_other | C60: 0 | D60: 0 | E60: 0 | F60: 0 | G60: 0 | H60: 0 | I60: PKR m
A61: Total current liabilities | B61: tap+contract+acc_markup+stb+cp_ltf+cp_lease+cp_grant+div_liab+tax_liab+cl_other | C61: =C50+C52+C53+C54+C55+C56+C57+C58+C59+C60 -> 6279.5483 | D61: =D50+D52+D53+D54+D55+D56+D57+D58+D59+D60 -> 7572.2439 | E61: =E50+E52+E53+E54+E55+E56+E57+E58+E59+E60 -> 9487.9907 | F61: =F50+F52+F53+F54+F55+F56+F57+F58+F59+F60 -> 9912.4714 | G61: =G50+G52+G53+G54+G55+G56+G57+G58+G59+G60 -> 11095.636 | H61: =H50+H52+H53+H54+H55+H56+H57+H58+H59+H60 -> 11661.701 | I61: PKR m | J61: Trade creditors memo line excluded (already inside trade and other payables)
A62: Total liabilities | B62: tot_ncl+tot_cl | C62: =C48+C61 -> 13029.994 | D62: =D48+D61 -> 13863.382 | E62: =E48+E61 -> 16104.448 | F62: =F48+F61 -> 16920.031 | G62: =G48+G61 -> 17752.99 | H62: =H48+H61 -> 18839.117 | I62: PKR m
A63: TOTAL EQUITY AND LIABILITIES | B63: tot_eq+tot_liab | C63: =C41+C62 -> 31756.667 | D63: =D41+D62 -> 36086.921 | E63: =E41+E62 -> 43350.668 | F63: =F41+F62 -> 49530.076 | G63: =G41+G62 -> 58843.295 | H63: =H41+H62 -> 66794.312 | I63: PKR m
A64: Derived balances used in ratios
A65: Inventories = stores and spares + stock-in-trade | B65: stores+sit | C65: =C30+C31 -> 3266.1807 | D65: =D30+D31 -> 4183.5454 | E65: =E30+E31 -> 5670.9864 | F65: =F30+F31 -> 7655.9913 | G65: =G30+G31 -> 7579.4259 | H65: =H30+H31 -> 7504.868 | I65: PKR m
A66: Interest-bearing debt = LT financing + leases + ST borrowings + current portions | B66: ltf_nc+lease_nc+stb+cp_ltf+cp_lease | C66: =C43+C44+C54+C55+C56-C251-C252 -> 6989.3316 | D66: =D43+D44+D54+D55+D56-D251-D252 -> 6050.7861 | E66: =E43+E44+E54+E55+E56-E251-E252 -> 4251.3125 | F66: =F43+F44+F54+F55+F56-F251-F252 -> 3183.3732 | G66: =G43+G44+G54+G55+G56-G251-G252 -> 2153.0596 | H66: =H43+H44+H54+H55+H56-H251-H252 -> 2242.6215 | I66: PKR m
A67: Long-term interest-bearing debt (non-current financing + non-current leases) | B67: ltf_nc+lease_nc | C67: =C43+C44 -> 5439.2261 | D67: =D43+D44 -> 4405.7653 | E67: =E43+E44 -> 3179.4001 | F67: =F43+F44 -> 2149.0174 | G67: =G43+G44 -> 1118.6425 | H67: =H43+H44 -> 1448.9778 | I67: PKR m
I68: PKR m
I69: PKR m
A70: Invested capital = interest-bearing debt + equity | B70: ibd+tot_eq | C70: =C66+C41 -> 25716.005 | D70: =D66+D41 -> 28274.326 | E70: =E66+E41 -> 31497.533 | F70: =F66+F41 -> 35793.418 | G70: =G66+G41 -> 43243.365 | H70: =H66+H41 -> 50197.816 | I70: PKR m
A71: Capital employed = total assets - current liabilities | B71: tot_assets-tot_cl | C71: =C37-C61 -> 25477.119 | D71: =D37-D61 -> 28514.677 | E71: =E37-E61 -> 33862.677 | F71: =F37-F61 -> 39617.604 | G71: =G37-G61 -> 47747.659 | H71: =H37-H61 -> 55132.611 | I71: PKR m
A72: Operating current assets = CA - cash - ST investments | B72: tot_ca-cash-st_inv | C72: =C36-C34-C33 -> 4185.8871 | D72: =D36-D34-D33 -> 5651.5729 | E72: =E36-E34-E33 -> 7170.9701 | F72: =F36-F34-F33 -> 9644.7656 | G72: =G36-G34-G33 -> 10830.002 | H72: =H36-H34-H33 -> 10222.458 | I72: PKR m
A73: Operating current liabilities = CL - ST borrowings - current portions - accrued mark-up - dividends | B73: tot_cl-stb-cp_ltf-cp_lease-cp_grant-acc_markup-div_liab | C73: =C61-C54-C55-C56-C57-C53-C58 -> 4472.6617 | D73: =D61-D54-D55-D56-D57-D53-D58 -> 5758.4116 | E73: =E61-E54-E55-E56-E57-E53-E58 -> 8228.2583 | F73: =F61-F54-F55-F56-F57-F53-F58 -> 8639.9655 | G73: =G61-G54-G55-G56-G57-G53-G58 -> 9880.9404 | H73: =H61-H54-H55-H56-H57-H53-H58 -> 10778.456 | I73: PKR m
A74: Source totals (as printed in audited statements) and checks
A75: Printed total assets | B75: Input - see register KOHC|pr_TA | C75: 31756.667 | D75: 36086.921 | E75: 43350.668 | F75: 49530.076 | G75: 58843.295 | H75: 66794.312 | I75: PKR m
A76: Printed total equity | B76: Input - see register KOHC|pr_EQ | C76: 18726.673 | D76: 22223.539 | E76: 27246.22 | F76: 32610.045 | G76: 41090.305 | H76: 47955.195 | I76: PKR m
A77: Printed total current assets | B77: Input - see register KOHC|pr_CA | C77: 5237.6238 | D77: 9848.7987 | E77: 17775.831 | F77: 22913.377 | G77: 32212.397 | H77: 38614.792 | I77: PKR m
A78: Printed total current liabilities | B78: Input - see register KOHC|pr_CL | C78: 6279.5483 | D78: 7572.2439 | E78: 9487.9907 | F78: 9912.4714 | G78: 11095.636 | H78: 11661.701 | I78: PKR m
A79: Check: total assets = equity + liabilities | B79: Validation formula | C79: =IF(ABS(C37-C63)<0.005,"PASS","FAIL") -> PASS | D79: =IF(ABS(D37-D63)<0.005,"PASS","FAIL") -> PASS | E79: =IF(ABS(E37-E63)<0.005,"PASS","FAIL") -> PASS | F79: =IF(ABS(F37-F63)<0.005,"PASS","FAIL") -> PASS | G79: =IF(ABS(G37-G63)<0.005,"PASS","FAIL") -> PASS | H79: =IF(ABS(H37-H63)<0.005,"PASS","FAIL") -> PASS
A80: Check: total assets = printed total | B80: Validation formula | C80: =IF(ABS(C37-C75)<0.005,"PASS","FAIL") -> PASS | D80: =IF(ABS(D37-D75)<0.005,"PASS","FAIL") -> PASS | E80: =IF(ABS(E37-E75)<0.005,"PASS","FAIL") -> PASS | F80: =IF(ABS(F37-F75)<0.005,"PASS","FAIL") -> PASS | G80: =IF(ABS(G37-G75)<0.005,"PASS","FAIL") -> PASS | H80: =IF(ABS(H37-H75)<0.005,"PASS","FAIL") -> PASS
A81: Check: equity, CA and CL = printed subtotals | B81: Validation formula | C81: =IF(AND(ABS(C41-C76)<0.005,ABS(C36-C77)<0.005,ABS(C61-C78)<0.005),"PASS","FAIL") -> PASS | D81: =IF(AND(ABS(D41-D76)<0.005,ABS(D36-D77)<0.005,ABS(D61-D78)<0.005),"PASS","FAIL") -> PASS | E81: =IF(AND(ABS(E41-E76)<0.005,ABS(E36-E77)<0.005,ABS(E61-E78)<0.005),"PASS","FAIL") -> PASS | F81: =IF(AND(ABS(F41-F76)<0.005,ABS(F36-F77)<0.005,ABS(F61-F78)<0.005),"PASS","FAIL") -> PASS | G81: =IF(AND(ABS(G41-G76)<0.005,ABS(G36-G77)<0.005,ABS(G61-G78)<0.005),"PASS","FAIL") -> PASS | H81: =IF(AND(ABS(H41-H76)<0.005,ABS(H36-H77)<0.005,ABS(H61-H78)<0.005),"PASS","FAIL") -> PASS
A83: C. STATEMENT OF PROFIT OR LOSS (PKR million)
A84: Revenue / net sales | B84: Input - see register KOHC|rev | D84: 24057.376 | E84: 32876.949 | F84: 38921.635 | G84: 38647.768 | H84: 37535.7 | I84: PKR m
A85: Cost of sales | B85: Input - see register KOHC|cogs | D85: -18092.027 | E85: -23065.181 | F85: -28488.941 | G85: -27391.276 | H85: -22814.094 | I85: PKR m
A86: Gross profit | B86: rev+cogs | D86: =D84+D85 -> 5965.3491 | E86: =E84+E85 -> 9811.7685 | F86: =F84+F85 -> 10432.694 | G86: =G84+G85 -> 11256.491 | H86: =H84+H85 -> 14721.606 | I86: PKR m
A87: Selling and distribution expenses | B87: Input - see register KOHC|selling | D87: -94.165965 | E87: -122.13674 | F87: -176.12346 | G87: -197.25936 | H87: -225.60042 | I87: PKR m
A88: Administrative expenses | B88: Input - see register KOHC|admin | D88: -313.52467 | E88: -353.52285 | F88: -396.23005 | G88: -488.04283 | H88: -695.55312 | I88: PKR m
A89: Impairment / expected credit loss on financial assets | B89: Input - see register KOHC|impair | D89: 0 | E89: 0 | F89: 0 | G89: 2.010516 | H89: -44.078565 | I89: PKR m
A90: Other operating expenses (incl. WPPF/WWF) | B90: Input - see register KOHC|oth_exp | D90: -325.32307 | E90: -563.05238 | F90: -736.51296 | G90: -571.95039 | H90: -940.35906 | I90: PKR m
A91: Operating profit (core) = GP - operating expenses, excl. other income | B91: gp+selling+admin+impair+oth_exp | D91: =D86+D87+D88+D89+D90 -> 5232.3354 | E91: =E86+E87+E88+E89+E90 -> 8773.0565 | F91: =F86+F87+F88+F89+F90 -> 9123.8275 | G91: =G86+G87+G88+G89+G90 -> 10001.249 | H91: =H86+H87+H88+H89+H90 -> 12816.015 | I91: PKR m
A92: Other income | B92: Input - see register KOHC|oth_inc | D92: 170.67467 | E92: 690.1434 | F92: 2085.8081 | G92: 4452.4165 | H92: 5280.7192 | I92: PKR m
A93: Finance income (where presented separately) | B93: Input - see register KOHC|fin_inc | D93: 0 | E93: 0 | F93: 0 | G93: 0 | H93: 0 | I93: PKR m
A94: Share of profit of associate | B94: Input - see register KOHC|assoc | D94: 0 | E94: 0 | F94: 0 | G94: 0 | H94: 0 | I94: PKR m
A95: Finance cost | B95: Input - see register KOHC|fin_cost | D95: -517.05541 | E95: -537.71082 | F95: -740.30777 | G95: -677.38085 | H95: -349.91072 | I95: PKR m
A96: Profit before levies and income tax | B96: core_op+oth_inc+fin_inc+assoc+fin_cost | D96: =D91+D92+D93+D94+D95 -> 4885.9546 | E96: =E91+E92+E93+E94+E95 -> 8925.4891 | F96: =F91+F92+F93+F94+F95 -> 10469.328 | G96: =G91+G92+G93+G94+G95 -> 13776.285 | H96: =H91+H92+H93+H94+H95 -> 17746.823 | I96: PKR m
A97: Levies (final / minimum taxes presented separately) | B97: Input - see register KOHC|levy | D97: 0 | E97: 0 | F97: -343.981 | G97: -844.15137 | H97: -58.631368 | I97: PKR m
A98: Income tax | B98: Input - see register KOHC|tax | D98: -1388.4474 | E98: -3901.2089 | F98: -4304.5957 | G98: -4038.6789 | H98: -6113.038 | I98: PKR m
A99: Profit after tax (attributable to ordinary shareholders) | B99: pbt_pre+levy+tax | D99: =D96+D97+D98 -> 3497.5072 | E99: =E96+E97+E98 -> 5024.2803 | F99: =F96+F97+F98 -> 5820.7511 | G99: =G96+G97+G98 -> 8893.4548 | H99: =H96+H97+H98 -> 11575.154 | I99: PKR m
A100: Printed gross profit | B100: Input - see register KOHC|pr_gp | D100: 5965.3491 | E100: 9811.7685 | F100: 10432.694 | G100: 11256.491 | H100: 14721.606 | I100: PKR m
A101: Printed profit before levies and income tax | B101: Input - see register KOHC|pr_pbt | D101: 4885.9546 | E101: 8925.4891 | F101: 10469.328 | G101: 13776.285 | H101: 17746.823 | I101: PKR m
A102: Printed profit after tax | B102: Input - see register KOHC|pr_pat | D102: 3497.5072 | E102: 5024.2803 | F102: 5820.7511 | G102: 8893.4548 | H102: 11575.154 | I102: PKR m
A103: Check: GP, PBT and PAT agree to printed statement | B103: Validation formula | D103: =IF(AND(ABS(D86-D100)<0.005,ABS(D96-D101)<0.005,ABS(D99-D102)<0.005),"PASS","FAIL") -> PASS | E103: =IF(AND(ABS(E86-E100)<0.005,ABS(E96-E101)<0.005,ABS(E99-E102)<0.005),"PASS","FAIL") -> PASS | F103: =IF(AND(ABS(F86-F100)<0.005,ABS(F96-F101)<0.005,ABS(F99-F102)<0.005),"PASS","FAIL") -> PASS | G103: =IF(AND(ABS(G86-G100)<0.005,ABS(G96-G101)<0.005,ABS(G99-G102)<0.005),"PASS","FAIL") -> PASS | H103: =IF(AND(ABS(H86-H100)<0.005,ABS(H96-H101)<0.005,ABS(H99-H102)<0.005),"PASS","FAIL") -> PASS
...

Sheet LUCK
A1: Lucky Cement Limited (LUCK) - five-year financial analysis, FY2021-FY2025
A2: Competitor 1 | PSX: LUCK | Unconsolidated (separate) financial statements | All amounts PKR million unless stated
A3: SOURCE INPUTS retained. Ratio tables below are ARCHIVED prior-33-measure workings; use 27 Calculations for final results. Blue = audited input; black = formula.
A5: A. COMPANY AND DATA INFORMATION
A6: Company | B6: Lucky Cement Limited
A7: PSX symbol | B7: LUCK
A8: Role in project | B8: Competitor 1
A9: Financial year-end | B9: 30 June (FY2021 = year ended 30 June 2021, etc.)
A10: Reporting basis | B10: Unconsolidated (separate) financial statements
A11: Original audited units | B11: PKR '000 - normalised here to PKR million (full precision retained)
A12: Annual reports used | B12: FY2021: 2021.pdf; FY2022: 2022.pdf; FY2023: 2023.pdf; FY2024: 2024.pdf; FY2025: 2025.pdf
A13: Year selection rule | B13: Each year taken from the most recent audited presentation: FY2025 from FY2025 AR; FY2020-FY2024 from the comparative column of the following year's AR (captures restatements). FY2020 = opening balances only.
A14: Per-share basis | B14: Actual PSX FY-end close paired with the share basis in force on that date. EPS notes, splits, treasury shares and bonus treatment are documented on Share Basis.
A15: Source register | B15: Every blue input is listed with report, statement, PDF page, printed page and remarks on the Sources & Validation sheet.
A17: Item | B17: Definition / formula / source note | C17: FY2020* | D17: FY2021 | E17: FY2022 | F17: FY2023 | G17: FY2024 | H17: FY2025 | I17: Units | J17: Comments
A18: B. STATEMENT OF FINANCIAL POSITION (PKR million; FY2020 = opening balances only)
A19: Non-current assets
A20: Property, plant and equipment (as presented) | B20: Input - see register LUCK|ppe | C20: 60247.57 | D20: 62389.947 | E20: 82301.05 | F20: 95620.306 | G20: 107258.97 | H20: 107409.59 | I20: PKR m
A21: of which: capital work-in-progress (note) | B21: Input - see register LUCK|cwip | C21: 334.191 | D21: 4015.044 | E21: 21911.214 | F21: 5562.145 | G21: 11633.303 | H21: 5420.742 | I21: PKR m
A22: Operating fixed assets = PPE less CWIP | B22: PPE - CWIP | C22: =C20-C21 -> 59913.379 | D22: =D20-D21 -> 58374.903 | E22: =E20-E21 -> 60389.836 | F22: =F20-F21 -> 90058.161 | G22: =G20-G21 -> 95625.67 | H22: =H20-H21 -> 101988.85 | I22: PKR m
A23: Right-of-use assets (presented separately) | B23: Input - see register LUCK|rou | C23: 0 | D23: 0 | E23: 0 | F23: 0 | G23: 0 | H23: 0 | I23: PKR m
A24: Intangible assets | B24: Input - see register LUCK|intang | C24: 11.323 | D24: 0.67 | E24: 51.352 | F24: 85.588 | G24: 69.394 | H24: 46.229 | I24: PKR m
A25: Investment property | B25: Input - see register LUCK|inv_prop | C25: 0 | D25: 0 | E25: 0 | F25: 0 | G25: 0 | H25: 0 | I25: PKR m
A26: Long-term investments | B26: Input - see register LUCK|lt_inv | C26: 47144.485 | D26: 53194.485 | E26: 57594.485 | F26: 57594.485 | G26: 58072.373 | H26: 58555.707 | I26: PKR m
A27: Other non-current assets | B27: Input - see register LUCK|nca_other | C27: 90.183 | D27: 106.592 | E27: 199.79 | F27: 202.046 | G27: 165.266 | H27: 189.147 | I27: PKR m
A28: Total non-current assets | B28: Sum of above (excl. memo) | C28: =C20+C23+C24+C25+C26+C27 -> 107493.56 | D28: =D20+D23+D24+D25+D26+D27 -> 115691.69 | E28: =E20+E23+E24+E25+E26+E27 -> 140146.68 | F28: =F20+F23+F24+F25+F26+F27 -> 153502.43 | G28: =G20+G23+G24+G25+G26+G27 -> 165566.01 | H28: =H20+H23+H24+H25+H26+H27 -> 166200.67 | I28: PKR m
A29: Current assets
A30: Stores, spares and loose tools | B30: Input - see register LUCK|stores | C30: 6520.17 | D30: 10526.573 | E30: 11206.843 | F30: 14084.018 | G30: 14591.821 | H30: 19895.13 | I30: PKR m
A31: Stock-in-trade | B31: Input - see register LUCK|sit | C31: 2915.552 | D31: 3105.037 | E31: 7171.364 | F31: 6048.507 | G31: 8505.426 | H31: 4774.577 | I31: PKR m
A32: Trade debts | B32: Input - see register LUCK|debts | C32: 3422.767 | D32: 2710.081 | E32: 3522.931 | F32: 5089.667 | G32: 6932.479 | H32: 6353.194 | I32: PKR m
A33: Short-term investments | B33: Input - see register LUCK|st_inv | C33: 2970.999 | D33: 16227.103 | E33: 12751.155 | F33: 21898.496 | G33: 29837.628 | H33: 61298.052 | I33: PKR m
A34: Cash and bank balances | B34: Input - see register LUCK|cash | C34: 7816.606 | D34: 2825.424 | E34: 3871.078 | F34: 4116.181 | G34: 2567.176 | H34: 2790.323 | I34: PKR m
A35: Other current assets | B35: Input - see register LUCK|ca_other | C35: 4728.819 | D35: 5282.15 | E35: 6292.32 | F35: 8339.773 | G35: 6017.554 | H35: 5436.083 | I35: PKR m
A36: Total current assets | B36: stores+sit+debts+st_inv+cash+ca_other | C36: =C30+C31+C32+C33+C34+C35 -> 28374.913 | D36: =D30+D31+D32+D33+D34+D35 -> 40676.368 | E36: =E30+E31+E32+E33+E34+E35 -> 44815.691 | F36: =F30+F31+F32+F33+F34+F35 -> 59576.642 | G36: =G30+G31+G32+G33+G34+G35 -> 68452.084 | H36: =H30+H31+H32+H33+H34+H35 -> 100547.36 | I36: PKR m
A37: TOTAL ASSETS | B37: tot_nca+tot_ca | C37: =C28+C36 -> 135868.47 | D37: =D28+D36 -> 156368.06 | E37: =E28+E36 -> 184962.37 | F37: =F28+F36 -> 213079.07 | G37: =G28+G36 -> 234018.09 | H37: =H28+H36 -> 266748.03 | I37: PKR m
A38: Equity
A39: Issued, subscribed and paid-up share capital | B39: Input - see register LUCK|share_cap | C39: 3233.75 | D39: 3233.75 | E39: 3233.75 | F39: 3118.386 | G39: 2930 | H39: 2930 | I39: PKR m
A40: Reserves, retained earnings and revaluation surplus | B40: Input - see register LUCK|eq_other | C40: 95950.111 | D40: 109966.51 | E40: 125306.57 | F40: 134247.94 | G40: 144831.28 | H40: 172980.4 | I40: PKR m
A41: Total equity | B41: share_cap+eq_other | C41: =C39+C40 -> 99183.861 | D41: =D39+D40 -> 113200.26 | E41: =E39+E40 -> 128540.32 | F41: =F39+F40 -> 137366.33 | G41: =G39+G40 -> 147761.28 | H41: =H39+H40 -> 175910.4 | I41: PKR m
A42: Non-current liabilities
A43: Long-term financing (non-current, interest-bearing) | B43: Input - see register LUCK|ltf_nc | C43: 320.461 | D43: 2934.044 | E43: 14108.446 | F43: 14557.294 | G43: 12760.637 | H43: 9184.522 | I43: PKR m
A44: Lease liabilities (non-current) | B44: Input - see register LUCK|lease_nc | C44: 0 | D44: 0 | E44: 0 | F44: 0 | G44: 0 | H44: 0 | I44: PKR m
A45: Deferred government grant (non-current) | B45: Input - see register LUCK|grant_nc | C45: 59.72 | D45: 1107.94 | E45: 2164.455 | F45: 2121.307 | G45: 1766.055 | H45: 1382.651 | I45: PKR m
A46: Deferred tax liability | B46: Input - see register LUCK|def_tax | C46: 5167.161 | D46: 6157.224 | E46: 6941.172 | F46: 10025.499 | G46: 0 | H46: 0 | I46: PKR m
A47: Other non-current liabilities | B47: Input - see register LUCK|ncl_other | C47: 2181.519 | D47: 2581.53 | E47: 2846.613 | F47: 2827.762 | G47: 17541.648 | H47: 21629.074 | I47: PKR m
A48: Total non-current liabilities | B48: ltf_nc+lease_nc+grant_nc+def_tax+ncl_other | C48: =C43+C44+C45+C46+C47 -> 7728.861 | D48: =D43+D44+D45+D46+D47 -> 12780.738 | E48: =E43+E44+E45+E46+E47 -> 26060.686 | F48: =F43+F44+F45+F46+F47 -> 29531.862 | G48: =G43+G44+G45+G46+G47 -> 32068.34 | H48: =H43+H44+H45+H46+H47 -> 32196.247 | I48: PKR m
A49: Current liabilities
A50: Trade and other payables | B50: Input - see register LUCK|tap | C50: 19354.794 | D50: 20789.76 | E50: 23191.483 | F50: 29918.702 | G50: 30006.625 | H50: 27300.919 | I50: PKR m
A51: memo: trade creditors / bills payable (note) | B51: Input - see register LUCK|trade_cred | C51: 2599.29 | D51: 2882.434 | E51: 3352.998 | F51: 5030.546 | G51: 7172.144 | H51: 6426.975 | I51: PKR m
A52: Contract liabilities / advances from customers | B52: Input - see register LUCK|contract | C52: 0 | D52: 0 | E52: 0 | F52: 0 | G52: 0 | H52: 0 | I52: PKR m
A53: Accrued mark-up / interest | B53: Input - see register LUCK|acc_markup | C53: 46.173 | D53: 70.868 | E53: 135.452 | F53: 497.745 | G53: 342.935 | H53: 185.616 | I53: PKR m
A54: Short-term borrowings (incl. running finance; FCCL parent loan) | B54: Input - see register LUCK|stb | C54: 7931.444 | D54: 7050 | E54: 1000 | F54: 5885 | G54: 5485 | H54: 6485 | I54: PKR m
A55: Current portion of long-term financing | B55: Input - see register LUCK|cp_ltf | C55: 126.727 | D55: 506.908 | E55: 487.202 | F55: 599.653 | G55: 2099.147 | H55: 1866.085 | I55: PKR m
A56: Current portion of lease liabilities | B56: Input - see register LUCK|cp_lease | C56: 0 | D56: 0 | E56: 0 | F56: 0 | G56: 0 | H56: 0 | I56: PKR m
A57: Current portion of deferred government grant | B57: Input - see register LUCK|cp_grant | C57: 0 | D57: 0 | E57: 0 | F57: 0 | G57: 0 | H57: 0 | I57: PKR m
A58: Unclaimed / unpaid dividends | B58: Input - see register LUCK|div_liab | C58: 73.347 | D58: 53.458 | E58: 51.03 | F58: 50.115 | G58: 59.148 | H58: 65.745 | I58: PKR m
A59: Taxation payable (net) | B59: Input - see register LUCK|tax_liab | C59: 1422.867 | D59: 1916.072 | E59: 5496.191 | F59: 9229.664 | G59: 16195.618 | H59: 22738.018 | I59: PKR m
A60: Other current liabilities | B60: Input - see register LUCK|cl_other | C60: 0 | D60: 0 | E60: 0 | F60: 0 | G60: 0 | H60: 0 | I60: PKR m
A61: Total current liabilities | B61: tap+contract+acc_markup+stb+cp_ltf+cp_lease+cp_grant+div_liab+tax_liab+cl_other | C61: =C50+C52+C53+C54+C55+C56+C57+C58+C59+C60 -> 28955.352 | D61: =D50+D52+D53+D54+D55+D56+D57+D58+D59+D60 -> 30387.066 | E61: =E50+E52+E53+E54+E55+E56+E57+E58+E59+E60 -> 30361.358 | F61: =F50+F52+F53+F54+F55+F56+F57+F58+F59+F60 -> 46180.879 | G61: =G50+G52+G53+G54+G55+G56+G57+G58+G59+G60 -> 54188.473 | H61: =H50+H52+H53+H54+H55+H56+H57+H58+H59+H60 -> 58641.383 | I61: PKR m | J61: Trade creditors memo line excluded (already inside trade and other payables)
A62: Total liabilities | B62: tot_ncl+tot_cl | C62: =C48+C61 -> 36684.213 | D62: =D48+D61 -> 43167.804 | E62: =E48+E61 -> 56422.044 | F62: =F48+F61 -> 75712.741 | G62: =G48+G61 -> 86256.813 | H62: =H48+H61 -> 90837.63 | I62: PKR m
A63: TOTAL EQUITY AND LIABILITIES | B63: tot_eq+tot_liab | C63: =C41+C62 -> 135868.07 | D63: =D41+D62 -> 156368.06 | E63: =E41+E62 -> 184962.37 | F63: =F41+F62 -> 213079.07 | G63: =G41+G62 -> 234018.09 | H63: =H41+H62 -> 266748.03 | I63: PKR m
A64: Derived balances used in ratios
A65: Inventories = stores and spares + stock-in-trade | B65: stores+sit | C65: =C30+C31 -> 9435.722 | D65: =D30+D31 -> 13631.61 | E65: =E30+E31 -> 18378.207 | F65: =F30+F31 -> 20132.525 | G65: =G30+G31 -> 23097.247 | H65: =H30+H31 -> 24669.707 | I65: PKR m
A66: Interest-bearing debt = LT financing + leases + ST borrowings + current portions | B66: ltf_nc+lease_nc+stb+cp_ltf+cp_lease | C66: =C43+C44+C54+C55+C56-C251-C252 -> 8378.632 | D66: =D43+D44+D54+D55+D56-D251-D252 -> 10490.952 | E66: =E43+E44+E54+E55+E56-E251-E252 -> 15595.648 | F66: =F43+F44+F54+F55+F56-F251-F252 -> 21041.947 | G66: =G43+G44+G54+G55+G56-G251-G252 -> 20344.784 | H66: =H43+H44+H54+H55+H56-H251-H252 -> 17535.607 | I66: PKR m
A67: Long-term interest-bearing debt (non-current financing + non-current leases) | B67: ltf_nc+lease_nc | C67: =C43+C44 -> 320.461 | D67: =D43+D44 -> 2934.044 | E67: =E43+E44 -> 14108.446 | F67: =F43+F44 -> 14557.294 | G67: =G43+G44 -> 12760.637 | H67: =H43+H44 -> 9184.522 | I67: PKR m
I68: PKR m
I69: PKR m
A70: Invested capital = interest-bearing debt + equity | B70: ibd+tot_eq | C70: =C66+C41 -> 107562.49 | D70: =D66+D41 -> 123691.21 | E70: =E66+E41 -> 144135.97 | F70: =F66+F41 -> 158408.27 | G70: =G66+G41 -> 168106.06 | H70: =H66+H41 -> 193446.01 | I70: PKR m
A71: Capital employed = total assets - current liabilities | B71: tot_assets-tot_cl | C71: =C37-C61 -> 106913.12 | D71: =D37-D61 -> 125981 | E71: =E37-E61 -> 154601.01 | F71: =F37-F61 -> 166898.19 | G71: =G37-G61 -> 179829.62 | H71: =H37-H61 -> 208106.65 | I71: PKR m
A72: Operating current assets = CA - cash - ST investments | B72: tot_ca-cash-st_inv | C72: =C36-C34-C33 -> 17587.308 | D72: =D36-D34-D33 -> 21623.841 | E72: =E36-E34-E33 -> 28193.458 | F72: =F36-F34-F33 -> 33561.965 | G72: =G36-G34-G33 -> 36047.28 | H72: =H36-H34-H33 -> 36458.984 | I72: PKR m
A73: Operating current liabilities = CL - ST borrowings - current portions - accrued mark-up - dividends | B73: tot_cl-stb-cp_ltf-cp_lease-cp_grant-acc_markup-div_liab | C73: =C61-C54-C55-C56-C57-C53-C58 -> 20777.661 | D73: =D61-D54-D55-D56-D57-D53-D58 -> 22705.832 | E73: =E61-E54-E55-E56-E57-E53-E58 -> 28687.674 | F73: =F61-F54-F55-F56-F57-F53-F58 -> 39148.366 | G73: =G61-G54-G55-G56-G57-G53-G58 -> 46202.243 | H73: =H61-H54-H55-H56-H57-H53-H58 -> 50038.937 | I73: PKR m
A74: Source totals (as printed in audited statements) and checks
A75: Printed total assets | B75: Input - see register LUCK|pr_TA | C75: 135868.47 | D75: 156368.06 | E75: 184962.37 | F75: 213079.07 | G75: 234018.09 | H75: 266748.03 | I75: PKR m
A76: Printed total equity | B76: Input - see register LUCK|pr_EQ | C76: 99183.861 | D76: 113200.26 | E76: 128540.32 | F76: 137366.33 | G76: 147761.28 | H76: 175910.4 | I76: PKR m
A77: Printed total current assets | B77: Input - see register LUCK|pr_CA | C77: 28374.913 | D77: 40676.368 | E77: 44815.691 | F77: 59576.642 | G77: 68452.084 | H77: 100547.36 | I77: PKR m
A78: Printed total current liabilities | B78: Input - see register LUCK|pr_CL | C78: 28955.352 | D78: 30387.066 | E78: 30361.358 | F78: 46180.879 | G78: 54188.473 | H78: 58641.383 | I78: PKR m
A79: Check: total assets = equity + liabilities | B79: Validation formula | C79: =IF(ABS(C37-C63)<0.005,"PASS","FAIL") -> FAIL | D79: =IF(ABS(D37-D63)<0.005,"PASS","FAIL") -> PASS | E79: =IF(ABS(E37-E63)<0.005,"PASS","FAIL") -> PASS | F79: =IF(ABS(F37-F63)<0.005,"PASS","FAIL") -> PASS | G79: =IF(ABS(G37-G63)<0.005,"PASS","FAIL") -> PASS | H79: =IF(ABS(H37-H63)<0.005,"PASS","FAIL") -> PASS
A80: Check: total assets = printed total | B80: Validation formula | C80: =IF(ABS(C37-C75)<0.005,"PASS","FAIL") -> PASS | D80: =IF(ABS(D37-D75)<0.005,"PASS","FAIL") -> PASS | E80: =IF(ABS(E37-E75)<0.005,"PASS","FAIL") -> PASS | F80: =IF(ABS(F37-F75)<0.005,"PASS","FAIL") -> PASS | G80: =IF(ABS(G37-G75)<0.005,"PASS","FAIL") -> PASS | H80: =IF(ABS(H37-H75)<0.005,"PASS","FAIL") -> PASS
A81: Check: equity, CA and CL = printed subtotals | B81: Validation formula | C81: =IF(AND(ABS(C41-C76)<0.005,ABS(C36-C77)<0.005,ABS(C61-C78)<0.005),"PASS","FAIL") -> PASS | D81: =IF(AND(ABS(D41-D76)<0.005,ABS(D36-D77)<0.005,ABS(D61-D78)<0.005),"PASS","FAIL") -> PASS | E81: =IF(AND(ABS(E41-E76)<0.005,ABS(E36-E77)<0.005,ABS(E61-E78)<0.005),"PASS","FAIL") -> PASS | F81: =IF(AND(ABS(F41-F76)<0.005,ABS(F36-F77)<0.005,ABS(F61-F78)<0.005),"PASS","FAIL") -> PASS | G81: =IF(AND(ABS(G41-G76)<0.005,ABS(G36-G77)<0.005,ABS(G61-G78)<0.005),"PASS","FAIL") -> PASS | H81: =IF(AND(ABS(H41-H76)<0.005,ABS(H36-H77)<0.005,ABS(H61-H78)<0.005),"PASS","FAIL") -> PASS
A83: C. STATEMENT OF PROFIT OR LOSS (PKR million)
A84: Revenue / net sales | B84: Input - see register LUCK|rev | D84: 62940.805 | E84: 81093.525 | F84: 95832.147 | G84: 115324.94 | H84: 124511.74 | I84: PKR m
A85: Cost of sales | B85: Input - see register LUCK|cogs | D85: -43984.873 | E85: -58541.684 | F85: -69771.469 | G85: -76520.37 | H85: -81827.06 | I85: PKR m
A86: Gross profit | B86: rev+cogs | D86: =D84+D85 -> 18955.932 | E86: =E84+E85 -> 22551.841 | F86: =F84+F85 -> 26060.678 | G86: =G84+G85 -> 38804.572 | H86: =H84+H85 -> 42684.684 | I86: PKR m
A87: Selling and distribution expenses | B87: Input - see register LUCK|selling | D87: -4859.096 | E87: -4764.574 | F87: -5326.894 | G87: -7773.885 | H87: -8972.815 | I87: PKR m
A88: Administrative expenses | B88: Input - see register LUCK|admin | D88: -1257.074 | E88: -1512.279 | F88: -1825.578 | G88: -2160.682 | H88: -2427.249 | I88: PKR m
A89: Impairment / expected credit loss on financial assets | B89: Input - see register LUCK|impair | D89: 0 | E89: 0 | F89: 0 | G89: 0 | H89: 0 | I89: PKR m
A90: Other operating expenses (incl. WPPF/WWF) | B90: Input - see register LUCK|oth_exp | D90: -1507.673 | E90: -1847.039 | F90: -2442.585 | G90: -2476.636 | H90: -3056.913 | I90: PKR m
A91: Operating profit (core) = GP - operating expenses, excl. other income | B91: gp+selling+admin+impair+oth_exp | D91: =D86+D87+D88+D89+D90 -> 11332.089 | E91: =E86+E87+E88+E89+E90 -> 14427.949 | F91: =F86+F87+F88+F89+F90 -> 16465.621 | G91: =G86+G87+G88+G89+G90 -> 26393.369 | H91: =H86+H87+H88+H89+H90 -> 28227.707 | I91: PKR m
A92: Other income | B92: Input - see register LUCK|oth_inc | D92: 5993.029 | E92: 7387.8 | F92: 6047.423 | G92: 16575.363 | H92: 20465.921 | I92: PKR m
A93: Finance income (where presented separately) | B93: Input - see register LUCK|fin_inc | D93: 0 | E93: 0 | F93: 0 | G93: 0 | H93: 0 | I93: PKR m
A94: Share of profit of associate | B94: Input - see register LUCK|assoc | D94: 0 | E94: 0 | F94: 0 | G94: 0 | H94: 0 | I94: PKR m
A95: Finance cost | B95: Input - see register LUCK|fin_cost | D95: -332.905 | E95: -394.517 | F95: -1169.77 | G95: -1581.168 | H95: -1370.569 | I95: PKR m
A96: Profit before levies and income tax | B96: core_op+oth_inc+fin_inc+assoc+fin_cost | D96: =D91+D92+D93+D94+D95 -> 16992.213 | E96: =E91+E92+E93+E94+E95 -> 21421.232 | F96: =F91+F92+F93+F94+F95 -> 21343.274 | G96: =G91+G92+G93+G94+G95 -> 41387.564 | H96: =H91+H92+H93+H94+H95 -> 47323.059 | I96: PKR m
A97: Levies (final / minimum taxes presented separately) | B97: Input - see register LUCK|levy | D97: 0 | E97: 0 | F97: -437.833 | G97: -953.051 | H97: -329.6 | I97: PKR m
A98: Income tax | B98: Input - see register LUCK|tax | D98: -2922.024 | E98: -6122.614 | F98: -7179.627 | G98: -12327.974 | H98: -13901.297 | I98: PKR m
A99: Profit after tax (attributable to ordinary shareholders) | B99: pbt_pre+levy+tax | D99: =D96+D97+D98 -> 14070.189 | E99: =E96+E97+E98 -> 15298.618 | F99: =F96+F97+F98 -> 13725.814 | G99: =G96+G97+G98 -> 28106.539 | H99: =H96+H97+H98 -> 33092.162 | I99: PKR m
A100: Printed gross profit | B100: Input - see register LUCK|pr_gp | D100: 18955.932 | E100: 22551.841 | F100: 26060.678 | G100: 38804.572 | H100: 42684.684 | I100: PKR m
A101: Printed profit before levies and income tax | B101: Input - see register LUCK|pr_pbt | D101: 16992.213 | E101: 21421.232 | F101: 21343.274 | G101: 41387.564 | H101: 47323.059 | I101: PKR m
A102: Printed profit after tax | B102: Input - see register LUCK|pr_pat | D102: 14070.189 | E102: 15298.618 | F102: 13725.814 | G102: 28106.539 | H102: 33092.162 | I102: PKR m
A103: Check: GP, PBT and PAT agree to printed statement | B103: Validation formula | D103: =IF(AND(ABS(D86-D100)<0.005,ABS(D96-D101)<0.005,ABS(D99-D102)<0.005),"PASS","FAIL") -> PASS | E103: =IF(AND(ABS(E86-E100)<0.005,ABS(E96-E101)<0.005,ABS(E99-E102)<0.005),"PASS","FAIL") -> PASS | F103: =IF(AND(ABS(F86-F100)<0.005,ABS(F96-F101)<0.005,ABS(F99-F102)<0.005),"PASS","FAIL") -> PASS | G103: =IF(AND(ABS(G86-G100)<0.005,ABS(G96-G101)<0.005,ABS(G99-G102)<0.005),"PASS","FAIL") -> PASS | H103: =IF(AND(ABS(H86-H100)<0.005,ABS(H96-H101)<0.005,ABS(H99-H102)<0.005),"PASS","FAIL") -> PASS
...

Sheet DGKC
A1: D.G. Khan Cement Company Limited (DGKC) - five-year financial analysis, FY2021-FY2025
A2: Competitor 2 | PSX: DGKC | Unconsolidated (separate) financial statements | All amounts PKR million unless stated
A3: SOURCE INPUTS retained. Ratio tables below are ARCHIVED prior-33-measure workings; use 27 Calculations for final results. Blue = audited input; black = formula.
A5: A. COMPANY AND DATA INFORMATION
A6: Company | B6: D.G. Khan Cement Company Limited
A7: PSX symbol | B7: DGKC
A8: Role in project | B8: Competitor 2
A9: Financial year-end | B9: 30 June (FY2021 = year ended 30 June 2021, etc.)
A10: Reporting basis | B10: Unconsolidated (separate) financial statements
A11: Original audited units | B11: Rs '000 - normalised here to PKR million (full precision retained)
A12: Annual reports used | B12: FY2021: DG_Annual_Report_2021.pdf; FY2022: DG_Annual_Report_2022.pdf; FY2023: DGAnnual2023.pdf; FY2024: DGAnnual2024.pdf; FY2025: DGAnnual2025.pdf
A13: Year selection rule | B13: Each year taken from the most recent audited presentation: FY2025 from FY2025 AR; FY2020-FY2024 from the comparative column of the following year's AR (captures restatements). FY2020 = opening balances only.
A14: Per-share basis | B14: Actual PSX FY-end close paired with the share basis in force on that date. EPS notes, splits, treasury shares and bonus treatment are documented on Share Basis.
A15: Source register | B15: Every blue input is listed with report, statement, PDF page, printed page and remarks on the Sources & Validation sheet.
A17: Item | B17: Definition / formula / source note | C17: FY2020* | D17: FY2021 | E17: FY2022 | F17: FY2023 | G17: FY2024 | H17: FY2025 | I17: Units | J17: Comments
A18: B. STATEMENT OF FINANCIAL POSITION (PKR million; FY2020 = opening balances only)
A19: Non-current assets
A20: Property, plant and equipment (as presented) | B20: Input - see register DGKC|ppe | C20: 83537.295 | D20: 85020.109 | E20: 82803.86 | F20: 82245.65 | G20: 79877.839 | H20: 77252.559 | I20: PKR m
A21: of which: capital work-in-progress (note) | B21: Input - see register DGKC|cwip | C21: 6358.259 | D21: 7726.72 | E21: 724.168 | F21: 2006.864 | G21: 1341.029 | H21: 798.312 | I21: PKR m
A22: Operating fixed assets = PPE less CWIP | B22: PPE - CWIP | C22: =C20-C21 -> 77179.036 | D22: =D20-D21 -> 77293.389 | E22: =E20-E21 -> 82079.692 | F22: =F20-F21 -> 80238.786 | G22: =G20-G21 -> 78536.81 | H22: =H20-H21 -> 76454.247 | I22: PKR m
A23: Right-of-use assets (presented separately) | B23: Input - see register DGKC|rou | C23: 0 | D23: 0 | E23: 0 | F23: 0 | G23: 0 | H23: 0 | I23: PKR m
A24: Intangible assets | B24: Input - see register DGKC|intang | C24: 0 | D24: 0 | E24: 17.319 | F24: 10.152 | G24: 42.762 | H24: 13.076 | I24: PKR m
A25: Investment property | B25: Input - see register DGKC|inv_prop | C25: 0 | D25: 0 | E25: 0 | F25: 0 | G25: 0 | H25: 0 | I25: PKR m
A26: Long-term investments | B26: Input - see register DGKC|lt_inv | C26: 11849.828 | D26: 15965.811 | E26: 12866.145 | F26: 13366.36 | G26: 16633.064 | H26: 20689.545 | I26: PKR m
A27: Other non-current assets | B27: Input - see register DGKC|nca_other | C27: 57.984 | D27: 57.513 | E27: 61.526 | F27: 64.426 | G27: 61.568 | H27: 61.013 | I27: PKR m
A28: Total non-current assets | B28: Sum of above (excl. memo) | C28: =C20+C23+C24+C25+C26+C27 -> 95445.107 | D28: =D20+D23+D24+D25+D26+D27 -> 101043.43 | E28: =E20+E23+E24+E25+E26+E27 -> 95748.85 | F28: =F20+F23+F24+F25+F26+F27 -> 95686.588 | G28: =G20+G23+G24+G25+G26+G27 -> 96615.233 | H28: =H20+H23+H24+H25+H26+H27 -> 98016.193 | I28: PKR m
A29: Current assets
A30: Stores, spares and loose tools | B30: Input - see register DGKC|stores | C30: 8237.99 | D30: 12879.348 | E30: 16813.883 | F30: 13852.005 | G30: 12559.774 | H30: 12306.679 | I30: PKR m
A31: Stock-in-trade | B31: Input - see register DGKC|sit | C31: 4352.995 | D31: 2728.589 | E31: 5981.515 | F31: 8873.17 | G31: 7693.067 | H31: 8188.678 | I31: PKR m
A32: Trade debts | B32: Input - see register DGKC|debts | C32: 2286.084 | D32: 1676.245 | E32: 1467.862 | F32: 1193.44 | G32: 855.742 | H32: 1493.08 | I32: PKR m
A33: Short-term investments | B33: Input - see register DGKC|st_inv | C33: 13126.388 | D33: 12946.786 | E33: 9962.421 | F33: 9270.898 | G33: 18384.882 | H33: 24005.1 | I33: PKR m
A34: Cash and bank balances | B34: Input - see register DGKC|cash | C34: 347.834 | D34: 806.373 | E34: 410.803 | F34: 674.972 | G34: 732.168 | H34: 568.832 | I34: PKR m
A35: Other current assets | B35: Input - see register DGKC|ca_other | C35: 5755.136 | D35: 5813.923 | E35: 6176.679 | F35: 5162.181 | G35: 1544.888 | H35: 1345.673 | I35: PKR m
A36: Total current assets | B36: stores+sit+debts+st_inv+cash+ca_other | C36: =C30+C31+C32+C33+C34+C35 -> 34106.427 | D36: =D30+D31+D32+D33+D34+D35 -> 36851.264 | E36: =E30+E31+E32+E33+E34+E35 -> 40813.163 | F36: =F30+F31+F32+F33+F34+F35 -> 39026.666 | G36: =G30+G31+G32+G33+G34+G35 -> 41770.521 | H36: =H30+H31+H32+H33+H34+H35 -> 47908.042 | I36: PKR m
A37: TOTAL ASSETS | B37: tot_nca+tot_ca | C37: =C28+C36 -> 129551.53 | D37: =D28+D36 -> 137894.7 | E37: =E28+E36 -> 136562.01 | F37: =F28+F36 -> 134713.25 | G37: =G28+G36 -> 138385.75 | H37: =H28+H36 -> 145924.23 | I37: PKR m
A38: Equity
A39: Issued, subscribed and paid-up share capital | B39: Input - see register DGKC|share_cap | C39: 4381.191 | D39: 4381.191 | E39: 4381.191 | F39: 4381.191 | G39: 4381.191 | H39: 4381.191 | I39: PKR m
A40: Reserves, retained earnings and revaluation surplus | B40: Input - see register DGKC|eq_other | C40: 62262.966 | D40: 69096.682 | E40: 65536.911 | F40: 59811.086 | G40: 71466.347 | H40: 90286.287 | I40: PKR m
A41: Total equity | B41: share_cap+eq_other | C41: =C39+C40 -> 66644.157 | D41: =D39+D40 -> 73477.873 | E41: =E39+E40 -> 69918.102 | F41: =F39+F40 -> 64192.277 | G41: =G39+G40 -> 75847.538 | H41: =H39+H40 -> 94667.478 | I41: PKR m
A42: Non-current liabilities
A43: Long-term financing (non-current, interest-bearing) | B43: Input - see register DGKC|ltf_nc | C43: 21972 | D43: 19300.064 | E43: 14168.229 | F43: 9663.619 | G43: 15965.116 | H43: 10093.829 | I43: PKR m
A44: Lease liabilities (non-current) | B44: Input - see register DGKC|lease_nc | C44: 0 | D44: 0 | E44: 0 | F44: 0 | G44: 0 | H44: 0 | I44: PKR m
A45: Deferred government grant (non-current) | B45: Input - see register DGKC|grant_nc | C45: 0 | D45: 664.504 | E45: 450.684 | F45: 278.753 | G45: 154.614 | H45: 70.135 | I45: PKR m
A46: Deferred tax liability | B46: Input - see register DGKC|def_tax | C46: 2535.349 | D46: 3378.941 | E46: 4942.15 | F46: 10613.603 | G46: 12675.472 | H46: 13286.942 | I46: PKR m
A47: Other non-current liabilities | B47: Input - see register DGKC|ncl_other | C47: 775.771 | D47: 777.795 | E47: 993.817 | F47: 1289.212 | G47: 1517.297 | H47: 1894.931 | I47: PKR m
A48: Total non-current liabilities | B48: ltf_nc+lease_nc+grant_nc+def_tax+ncl_other | C48: =C43+C44+C45+C46+C47 -> 25283.12 | D48: =D43+D44+D45+D46+D47 -> 24121.304 | E48: =E43+E44+E45+E46+E47 -> 20554.88 | F48: =F43+F44+F45+F46+F47 -> 21845.187 | G48: =G43+G44+G45+G46+G47 -> 30312.499 | H48: =H43+H44+H45+H46+H47 -> 25345.837 | I48: PKR m
A49: Current liabilities
A50: Trade and other payables | B50: Input - see register DGKC|tap | C50: 11298.187 | D50: 14923.151 | E50: 12591.709 | F50: 13783.299 | G50: 12394.455 | H50: 13333.448 | I50: PKR m
A51: memo: trade creditors / bills payable (note) | B51: Input - see register DGKC|trade_cred | C51: 4325.32 | D51: 7375.63 | E51: 3871.207 | F51: 6530.049 | G51: 5046.744 | H51: 3900.142 | I51: PKR m
A52: Contract liabilities / advances from customers | B52: Input - see register DGKC|contract | C52: 0 | D52: 0 | E52: 0 | F52: 0 | G52: 0 | H52: 0 | I52: PKR m
A53: Accrued mark-up / interest | B53: Input - see register DGKC|acc_markup | C53: 712.275 | D53: 507.769 | E53: 883.229 | F53: 1739.547 | G53: 1280.446 | H53: 229.652 | I53: PKR m
A54: Short-term borrowings (incl. running finance; FCCL parent loan) | B54: Input - see register DGKC|stb | C54: 23495.967 | D54: 18362.05 | E54: 25210.506 | F54: 25494.293 | G54: 13064.718 | H54: 9878.499 | I54: PKR m
A55: Current portion of long-term financing | B55: Input - see register DGKC|cp_ltf | C55: 2010.621 | D55: 6130.703 | E55: 7097.166 | F55: 7370.364 | G55: 5291.972 | H55: 1934.772 | I55: PKR m
A56: Current portion of lease liabilities | B56: Input - see register DGKC|cp_lease | C56: 0 | D56: 0 | E56: 0 | F56: 0 | G56: 0 | H56: 0 | I56: PKR m
A57: Current portion of deferred government grant | B57: Input - see register DGKC|cp_grant | C57: 0 | D57: 262.523 | E57: 213.883 | F57: 171.581 | G57: 124.138 | H57: 79.465 | I57: PKR m
A58: Unclaimed / unpaid dividends | B58: Input - see register DGKC|div_liab | C58: 33.837 | D58: 33.517 | E58: 34.512 | F58: 34.704 | G58: 34.201 | H58: 34.154 | I58: PKR m
A59: Taxation payable (net) | B59: Input - see register DGKC|tax_liab | C59: 35.09 | D59: 35.09 | E59: 35.09 | F59: 35.09 | G59: 35.09 | H59: 365.924 | I59: PKR m
A60: Other current liabilities | B60: Input - see register DGKC|cl_other | C60: 38.28 | D60: 40.717 | E60: 22.936 | F60: 46.912 | G60: 0.697 | H60: 55.006 | I60: PKR m
A61: Total current liabilities | B61: tap+contract+acc_markup+stb+cp_ltf+cp_lease+cp_grant+div_liab+tax_liab+cl_other | C61: =C50+C52+C53+C54+C55+C56+C57+C58+C59+C60 -> 37624.257 | D61: =D50+D52+D53+D54+D55+D56+D57+D58+D59+D60 -> 40295.52 | E61: =E50+E52+E53+E54+E55+E56+E57+E58+E59+E60 -> 46089.031 | F61: =F50+F52+F53+F54+F55+F56+F57+F58+F59+F60 -> 48675.79 | G61: =G50+G52+G53+G54+G55+G56+G57+G58+G59+G60 -> 32225.717 | H61: =H50+H52+H53+H54+H55+H56+H57+H58+H59+H60 -> 25910.92 | I61: PKR m | J61: Trade creditors memo line excluded (already inside trade and other payables)
A62: Total liabilities | B62: tot_ncl+tot_cl | C62: =C48+C61 -> 62907.377 | D62: =D48+D61 -> 64416.824 | E62: =E48+E61 -> 66643.911 | F62: =F48+F61 -> 70520.977 | G62: =G48+G61 -> 62538.216 | H62: =H48+H61 -> 51256.757 | I62: PKR m
A63: TOTAL EQUITY AND LIABILITIES | B63: tot_eq+tot_liab | C63: =C41+C62 -> 129551.53 | D63: =D41+D62 -> 137894.7 | E63: =E41+E62 -> 136562.01 | F63: =F41+F62 -> 134713.25 | G63: =G41+G62 -> 138385.75 | H63: =H41+H62 -> 145924.23 | I63: PKR m
A64: Derived balances used in ratios
A65: Inventories = stores and spares + stock-in-trade | B65: stores+sit | C65: =C30+C31 -> 12590.985 | D65: =D30+D31 -> 15607.937 | E65: =E30+E31 -> 22795.398 | F65: =F30+F31 -> 22725.175 | G65: =G30+G31 -> 20252.841 | H65: =H30+H31 -> 20495.357 | I65: PKR m
A66: Interest-bearing debt = LT financing + leases + ST borrowings + current portions | B66: ltf_nc+lease_nc+stb+cp_ltf+cp_lease | C66: =C43+C44+C54+C55+C56-C251-C252 -> 47478.588 | D66: =D43+D44+D54+D55+D56-D251-D252 -> 43792.817 | E66: =E43+E44+E54+E55+E56-E251-E252 -> 46475.901 | F66: =F43+F44+F54+F55+F56-F251-F252 -> 42528.276 | G66: =G43+G44+G54+G55+G56-G251-G252 -> 34321.806 | H66: =H43+H44+H54+H55+H56-H251-H252 -> 21907.1 | I66: PKR m
A67: Long-term interest-bearing debt (non-current financing + non-current leases) | B67: ltf_nc+lease_nc | C67: =C43+C44 -> 21972 | D67: =D43+D44 -> 19300.064 | E67: =E43+E44 -> 14168.229 | F67: =F43+F44 -> 9663.619 | G67: =G43+G44 -> 15965.116 | H67: =H43+H44 -> 10093.829 | I67: PKR m
I68: PKR m
I69: PKR m
A70: Invested capital = interest-bearing debt + equity | B70: ibd+tot_eq | C70: =C66+C41 -> 114122.75 | D70: =D66+D41 -> 117270.69 | E70: =E66+E41 -> 116394 | F70: =F66+F41 -> 106720.55 | G70: =G66+G41 -> 110169.34 | H70: =H66+H41 -> 116574.58 | I70: PKR m
A71: Capital employed = total assets - current liabilities | B71: tot_assets-tot_cl | C71: =C37-C61 -> 91927.277 | D71: =D37-D61 -> 97599.177 | E71: =E37-E61 -> 90472.982 | F71: =F37-F61 -> 86037.464 | G71: =G37-G61 -> 106160.04 | H71: =H37-H61 -> 120013.31 | I71: PKR m
A72: Operating current assets = CA - cash - ST investments | B72: tot_ca-cash-st_inv | C72: =C36-C34-C33 -> 20632.205 | D72: =D36-D34-D33 -> 23098.105 | E72: =E36-E34-E33 -> 30439.939 | F72: =F36-F34-F33 -> 29080.796 | G72: =G36-G34-G33 -> 22653.471 | H72: =H36-H34-H33 -> 23334.11 | I72: PKR m
A73: Operating current liabilities = CL - ST borrowings - current portions - accrued mark-up - dividends | B73: tot_cl-stb-cp_ltf-cp_lease-cp_grant-acc_markup-div_liab | C73: =C61-C54-C55-C56-C57-C53-C58 -> 11371.557 | D73: =D61-D54-D55-D56-D57-D53-D58 -> 14998.958 | E73: =E61-E54-E55-E56-E57-E53-E58 -> 12649.735 | F73: =F61-F54-F55-F56-F57-F53-F58 -> 13865.301 | G73: =G61-G54-G55-G56-G57-G53-G58 -> 12430.242 | H73: =H61-H54-H55-H56-H57-H53-H58 -> 13754.378 | I73: PKR m
A74: Source totals (as printed in audited statements) and checks
A75: Printed total assets | B75: Input - see register DGKC|pr_TA | C75: 129551.53 | D75: 137894.7 | E75: 136562.01 | F75: 134713.25 | G75: 138385.75 | H75: 145924.23 | I75: PKR m
A76: Printed total equity | B76: Input - see register DGKC|pr_EQ | C76: 66644.157 | D76: 73477.873 | E76: 69918.102 | F76: 64192.277 | G76: 75847.538 | H76: 94667.478 | I76: PKR m
A77: Printed total current assets | B77: Input - see register DGKC|pr_CA | C77: 34106.427 | D77: 36851.264 | E77: 40813.163 | F77: 39026.666 | G77: 41770.521 | H77: 47908.042 | I77: PKR m
A78: Printed total current liabilities | B78: Input - see register DGKC|pr_CL | C78: 37624.257 | D78: 40295.52 | E78: 46089.031 | F78: 48675.79 | G78: 32225.717 | H78: 25910.92 | I78: PKR m
A79: Check: total assets = equity + liabilities | B79: Validation formula | C79: =IF(ABS(C37-C63)<0.005,"PASS","FAIL") -> PASS | D79: =IF(ABS(D37-D63)<0.005,"PASS","FAIL") -> PASS | E79: =IF(ABS(E37-E63)<0.005,"PASS","FAIL") -> PASS | F79: =IF(ABS(F37-F63)<0.005,"PASS","FAIL") -> PASS | G79: =IF(ABS(G37-G63)<0.005,"PASS","FAIL") -> PASS | H79: =IF(ABS(H37-H63)<0.005,"PASS","FAIL") -> PASS
A80: Check: total assets = printed total | B80: Validation formula | C80: =IF(ABS(C37-C75)<0.005,"PASS","FAIL") -> PASS | D80: =IF(ABS(D37-D75)<0.005,"PASS","FAIL") -> PASS | E80: =IF(ABS(E37-E75)<0.005,"PASS","FAIL") -> PASS | F80: =IF(ABS(F37-F75)<0.005,"PASS","FAIL") -> PASS | G80: =IF(ABS(G37-G75)<0.005,"PASS","FAIL") -> PASS | H80: =IF(ABS(H37-H75)<0.005,"PASS","FAIL") -> PASS
A81: Check: equity, CA and CL = printed subtotals | B81: Validation formula | C81: =IF(AND(ABS(C41-C76)<0.005,ABS(C36-C77)<0.005,ABS(C61-C78)<0.005),"PASS","FAIL") -> PASS | D81: =IF(AND(ABS(D41-D76)<0.005,ABS(D36-D77)<0.005,ABS(D61-D78)<0.005),"PASS","FAIL") -> PASS | E81: =IF(AND(ABS(E41-E76)<0.005,ABS(E36-E77)<0.005,ABS(E61-E78)<0.005),"PASS","FAIL") -> PASS | F81: =IF(AND(ABS(F41-F76)<0.005,ABS(F36-F77)<0.005,ABS(F61-F78)<0.005),"PASS","FAIL") -> PASS | G81: =IF(AND(ABS(G41-G76)<0.005,ABS(G36-G77)<0.005,ABS(G61-G78)<0.005),"PASS","FAIL") -> PASS | H81: =IF(AND(ABS(H41-H76)<0.005,ABS(H36-H77)<0.005,ABS(H61-H78)<0.005),"PASS","FAIL") -> PASS
A83: C. STATEMENT OF PROFIT OR LOSS (PKR million)
A84: Revenue / net sales | B84: Input - see register DGKC|rev | D84: 45107.69 | E84: 58043.863 | F84: 64983.821 | G84: 66038.689 | H84: 71892.837 | I84: PKR m
A85: Cost of sales | B85: Input - see register DGKC|cogs | D85: -37035.798 | E85: -47615.551 | F85: -55428.046 | G85: -55510.429 | H85: -53387.166 | I85: PKR m
A86: Gross profit | B86: rev+cogs | D86: =D84+D85 -> 8071.892 | E86: =E84+E85 -> 10428.312 | F86: =F84+F85 -> 9555.775 | G86: =G84+G85 -> 10528.26 | H86: =H84+H85 -> 18505.671 | I86: PKR m
A87: Selling and distribution expenses | B87: Input - see register DGKC|selling | D87: -1950.056 | E87: -1748.859 | F87: -1818.028 | G87: -2608.537 | H87: -3874.688 | I87: PKR m
A88: Administrative expenses | B88: Input - see register DGKC|admin | D88: -646.762 | E88: -751.052 | F88: -879.356 | G88: -1206.105 | H88: -1294.974 | I88: PKR m
A89: Impairment / expected credit loss on financial assets | B89: Input - see register DGKC|impair | D89: 104.703 | E89: -8.99 | F89: -104.094 | G89: -103.367 | H89: -6.899 | I89: PKR m
A90: Other operating expenses (incl. WPPF/WWF) | B90: Input - see register DGKC|oth_exp | D90: -414.315 | E90: -1042.803 | F90: -96.461 | G90: -5.033 | H90: -725.663 | I90: PKR m
A91: Operating profit (core) = GP - operating expenses, excl. other income | B91: gp+selling+admin+impair+oth_exp | D91: =D86+D87+D88+D89+D90 -> 5165.462 | E91: =E86+E87+E88+E89+E90 -> 6876.608 | F91: =F86+F87+F88+F89+F90 -> 6657.836 | G91: =G86+G87+G88+G89+G90 -> 6605.218 | H91: =H86+H87+H88+H89+H90 -> 12603.447 | I91: PKR m
A92: Other income | B92: Input - see register DGKC|oth_inc | D92: 2526.818 | E92: 2714.34 | F92: 3246.999 | G92: 4234.797 | H92: 4271.57 | I92: PKR m
A93: Finance income (where presented separately) | B93: Input - see register DGKC|fin_inc | D93: 0 | E93: 0 | F93: 0 | G93: 0 | H93: 0 | I93: PKR m
A94: Share of profit of associate | B94: Input - see register DGKC|assoc | D94: 0 | E94: 0 | F94: 0 | G94: 0 | H94: 0 | I94: PKR m
A95: Finance cost | B95: Input - see register DGKC|fin_cost | D95: -2920.875 | E95: -3571.187 | F95: -6742.292 | G95: -8001.105 | H95: -3870.405 | I95: PKR m
A96: Profit before levies and income tax | B96: core_op+oth_inc+fin_inc+assoc+fin_cost | D96: =D91+D92+D93+D94+D95 -> 4771.405 | E96: =E91+E92+E93+E94+E95 -> 6019.761 | F96: =F91+F92+F93+F94+F95 -> 3162.543 | G96: =G91+G92+G93+G94+G95 -> 2838.91 | H96: =H91+H92+H93+H94+H95 -> 13004.612 | I96: PKR m
A97: Levies (final / minimum taxes presented separately) | B97: Input - see register DGKC|levy | D97: 0 | E97: 0 | F97: -364.054 | G97: -520.848 | H97: -577.125 | I97: PKR m
A98: Income tax | B98: Input - see register DGKC|tax | D98: -1050.132 | E98: -3047.629 | F98: -6434.465 | G98: -1775.666 | H98: -3752.428 | I98: PKR m
A99: Profit after tax (attributable to ordinary shareholders) | B99: pbt_pre+levy+tax | D99: =D96+D97+D98 -> 3721.273 | E99: =E96+E97+E98 -> 2972.132 | F99: =F96+F97+F98 -> -3635.976 | G99: =G96+G97+G98 -> 542.396 | H99: =H96+H97+H98 -> 8675.059 | I99: PKR m
A100: Printed gross profit | B100: Input - see register DGKC|pr_gp | D100: 8071.892 | E100: 10428.312 | F100: 9555.775 | G100: 10528.26 | H100: 18505.671 | I100: PKR m
A101: Printed profit before levies and income tax | B101: Input - see register DGKC|pr_pbt | D101: 4771.405 | E101: 6019.761 | F101: 3162.543 | G101: 2838.91 | H101: 13004.612 | I101: PKR m
A102: Printed profit after tax | B102: Input - see register DGKC|pr_pat | D102: 3721.273 | E102: 2972.132 | F102: -3635.976 | G102: 542.396 | H102: 8675.059 | I102: PKR m
A103: Check: GP, PBT and PAT agree to printed statement | B103: Validation formula | D103: =IF(AND(ABS(D86-D100)<0.005,ABS(D96-D101)<0.005,ABS(D99-D102)<0.005),"PASS","FAIL") -> PASS | E103: =IF(AND(ABS(E86-E100)<0.005,ABS(E96-E101)<0.005,ABS(E99-E102)<0.005),"PASS","FAIL") -> PASS | F103: =IF(AND(ABS(F86-F100)<0.005,ABS(F96-F101)<0.005,ABS(F99-F102)<0.005),"PASS","FAIL") -> PASS | G103: =IF(AND(ABS(G86-G100)<0.005,ABS(G96-G101)<0.005,ABS(G99-G102)<0.005),"PASS","FAIL") -> PASS | H103: =IF(AND(ABS(H86-H100)<0.005,ABS(H96-H101)<0.005,ABS(H99-H102)<0.005),"PASS","FAIL") -> PASS
...

Sheet MLCF
A1: Maple Leaf Cement Factory Limited (MLCF) - five-year financial analysis, FY2021-FY2025
A2: Competitor 3 | PSX: MLCF | Unconsolidated (separate) financial statements | All amounts PKR million unless stated
A3: SOURCE INPUTS retained. Ratio tables below are ARCHIVED prior-33-measure workings; use 27 Calculations for final results. Blue = audited input; black = formula.
A5: A. COMPANY AND DATA INFORMATION
A6: Company | B6: Maple Leaf Cement Factory Limited
A7: PSX symbol | B7: MLCF
A8: Role in project | B8: Competitor 3
A9: Financial year-end | B9: 30 June (FY2021 = year ended 30 June 2021, etc.)
A10: Reporting basis | B10: Unconsolidated (separate) financial statements
A11: Original audited units | B11: Rs '000 - normalised here to PKR million (full precision retained)
A12: Annual reports used | B12: FY2021: 2021.pdf; FY2022: 2022.pdf; FY2023: 2023.pdf; FY2024: 2024.pdf; FY2025: 2025.pdf
A13: Year selection rule | B13: Each year taken from the most recent audited presentation: FY2025 from FY2025 AR; FY2020-FY2024 from the comparative column of the following year's AR (captures restatements). FY2020 = opening balances only.
A14: Per-share basis | B14: Actual PSX FY-end close paired with the share basis in force on that date. EPS notes, splits, treasury shares and bonus treatment are documented on Share Basis.
A15: Source register | B15: Every blue input is listed with report, statement, PDF page, printed page and remarks on the Sources & Validation sheet.
A17: Item | B17: Definition / formula / source note | C17: FY2020* | D17: FY2021 | E17: FY2022 | F17: FY2023 | G17: FY2024 | H17: FY2025 | I17: Units | J17: Comments
A18: B. STATEMENT OF FINANCIAL POSITION (PKR million; FY2020 = opening balances only)
A19: Non-current assets
A20: Property, plant and equipment (as presented) | B20: Input - see register MLCF|ppe | C20: 44297.941 | D20: 44215.539 | E20: 56784.84 | F20: 62354.608 | G20: 65995.598 | H20: 62836.212 | I20: PKR m
A21: of which: capital work-in-progress (note) | B21: Input - see register MLCF|cwip | C21: 871.386 | D21: 2854.293 | E21: 15352.8 | F21: 1676.796 | G21: 471.174 | H21: 125.704 | I21: PKR m
A22: Operating fixed assets = PPE less CWIP | B22: PPE - CWIP | C22: =C20-C21 -> 43426.555 | D22: =D20-D21 -> 41361.246 | E22: =E20-E21 -> 41432.04 | F22: =F20-F21 -> 60677.812 | G22: =G20-G21 -> 65524.424 | H22: =H20-H21 -> 62710.508 | I22: PKR m
A23: Right-of-use assets (presented separately) | B23: Input - see register MLCF|rou | C23: 0 | D23: 0 | E23: 0 | F23: 0 | G23: 0 | H23: 0 | I23: PKR m
A24: Intangible assets | B24: Input - see register MLCF|intang | C24: 9.023 | D24: 6.017 | E24: 10.415 | F24: 6.946 | G24: 84.81 | H24: 62.426 | I24: PKR m
A25: Investment property | B25: Input - see register MLCF|inv_prop | C25: 0 | D25: 0 | E25: 0 | F25: 0 | G25: 0 | H25: 0 | I25: PKR m
A26: Long-term investments | B26: Input - see register MLCF|lt_inv | C26: 5020 | D26: 5020 | E26: 5020 | F26: 5030 | G26: 6322 | H26: 20371.11 | I26: PKR m
A27: Other non-current assets | B27: Input - see register MLCF|nca_other | C27: 75.616 | D27: 74.306 | E27: 76.966 | F27: 76.49 | G27: 95.437 | H27: 83.919 | I27: PKR m
A28: Total non-current assets | B28: Sum of above (excl. memo) | C28: =C20+C23+C24+C25+C26+C27 -> 49402.58 | D28: =D20+D23+D24+D25+D26+D27 -> 49315.862 | E28: =E20+E23+E24+E25+E26+E27 -> 61892.221 | F28: =F20+F23+F24+F25+F26+F27 -> 67468.044 | G28: =G20+G23+G24+G25+G26+G27 -> 72497.845 | H28: =H20+H23+H24+H25+H26+H27 -> 83353.667 | I28: PKR m
A29: Current assets
A30: Stores, spares and loose tools | B30: Input - see register MLCF|stores | C30: 8395.61 | D30: 9738.717 | E30: 12853.605 | F30: 9925.855 | G30: 12277.288 | H30: 12461.312 | I30: PKR m
A31: Stock-in-trade | B31: Input - see register MLCF|sit | C31: 1779.404 | D31: 2150.183 | E31: 2695.621 | F31: 3874.605 | G31: 3256.553 | H31: 4442.989 | I31: PKR m
A32: Trade debts | B32: Input - see register MLCF|debts | C32: 3052.13 | D32: 1679.704 | E32: 2066.212 | F32: 2600.985 | G32: 4188.745 | H32: 4610.182 | I32: PKR m
A33: Short-term investments | B33: Input - see register MLCF|st_inv | C33: 75.245 | D33: 149.148 | E33: 198.346 | F33: 3689.556 | G33: 4220.262 | H33: 11102.413 | I33: PKR m
A34: Cash and bank balances | B34: Input - see register MLCF|cash | C34: 1046.267 | D34: 490.329 | E34: 793.576 | F34: 740.707 | G34: 1133.412 | H34: 1615.481 | I34: PKR m
A35: Other current assets | B35: Input - see register MLCF|ca_other | C35: 2258.535 | D35: 2715.335 | E35: 1714.629 | F35: 1407.959 | G35: 1791.577 | H35: 1520.227 | I35: PKR m
A36: Total current assets | B36: stores+sit+debts+st_inv+cash+ca_other | C36: =C30+C31+C32+C33+C34+C35 -> 16607.191 | D36: =D30+D31+D32+D33+D34+D35 -> 16923.416 | E36: =E30+E31+E32+E33+E34+E35 -> 20321.989 | F36: =F30+F31+F32+F33+F34+F35 -> 22239.667 | G36: =G30+G31+G32+G33+G34+G35 -> 26867.837 | H36: =H30+H31+H32+H33+H34+H35 -> 35752.604 | I36: PKR m
A37: TOTAL ASSETS | B37: tot_nca+tot_ca | C37: =C28+C36 -> 66009.771 | D37: =D28+D36 -> 66239.278 | E37: =E28+E36 -> 82214.21 | F37: =F28+F36 -> 89707.711 | G37: =G28+G36 -> 99365.682 | H37: =H28+H36 -> 119106.27 | I37: PKR m
A38: Equity
A39: Issued, subscribed and paid-up share capital | B39: Input - see register MLCF|share_cap | C39: 10983.462 | D39: 10983.462 | E39: 10983.462 | F39: 10733.462 | G39: 10475.626 | H39: 10475.626 | I39: PKR m
A40: Reserves, retained earnings and revaluation surplus | B40: Input - see register MLCF|eq_other | C40: 20337.369 | D40: 26559.079 | E40: 29575.553 | F40: 34179.652 | G40: 42140.282 | H40: 60985.966 | I40: PKR m
A41: Total equity | B41: share_cap+eq_other | C41: =C39+C40 -> 31320.831 | D41: =D39+D40 -> 37542.541 | E41: =E39+E40 -> 40559.015 | F41: =F39+F40 -> 44913.114 | G41: =G39+G40 -> 52615.908 | H41: =H39+H40 -> 71461.592 | I41: PKR m
A42: Non-current liabilities
A43: Long-term financing (non-current, interest-bearing) | B43: Input - see register MLCF|ltf_nc | C43: 15173.102 | D43: 12636.749 | E43: 18747.868 | F43: 17233.337 | G43: 14285.786 | H43: 9781.639 | I43: PKR m
A44: Lease liabilities (non-current) | B44: Input - see register MLCF|lease_nc | C44: 0 | D44: 0 | E44: 27.136 | F44: 31.408 | G44: 34.67 | H44: 28.495 | I44: PKR m
A45: Deferred government grant (non-current) | B45: Input - see register MLCF|grant_nc | C45: 0 | D45: 49.569 | E45: 786.758 | F45: 605.926 | G45: 450.487 | H45: 322.304 | I45: PKR m
A46: Deferred tax liability | B46: Input - see register MLCF|def_tax | C46: 3379.44 | D46: 3889.907 | E46: 5656.499 | F46: 8669.211 | G46: 13044.29 | H46: 13822.898 | I46: PKR m
A47: Other non-current liabilities | B47: Input - see register MLCF|ncl_other | C47: 822.623 | D47: 671.064 | E47: 243.543 | F47: 2039.694 | G47: 336.741 | H47: 358.852 | I47: PKR m
A48: Total non-current liabilities | B48: ltf_nc+lease_nc+grant_nc+def_tax+ncl_other | C48: =C43+C44+C45+C46+C47 -> 19375.165 | D48: =D43+D44+D45+D46+D47 -> 17247.289 | E48: =E43+E44+E45+E46+E47 -> 25461.804 | F48: =F43+F44+F45+F46+F47 -> 28579.576 | G48: =G43+G44+G45+G46+G47 -> 28151.974 | H48: =H43+H44+H45+H46+H47 -> 24314.188 | I48: PKR m
A49: Current liabilities
A50: Trade and other payables | B50: Input - see register MLCF|tap | C50: 7951.221 | D50: 7511.637 | E50: 9117.414 | F50: 12518.18 | G50: 12482.233 | H50: 17926.267 | I50: PKR m
A51: memo: trade creditors / bills payable (note) | B51: Input - see register MLCF|trade_cred | C51: =3886.684+C253 -> 4173.943 | D51: =3515.408+D253 -> 3576.632 | E51: =3975.712+E253 -> 4108.307 | F51: =4804.356+F253 -> 6676.221 | G51: =4575.18+G253 -> 5396.605 | H51: =5869.802+H253 -> 7322.783 | I51: PKR m
A52: Contract liabilities / advances from customers | B52: Input - see register MLCF|contract | C52: 0 | D52: 0 | E52: 0 | F52: 0 | G52: 0 | H52: 0 | I52: PKR m
A53: Accrued mark-up / interest | B53: Input - see register MLCF|acc_markup | C53: 547.189 | D53: 260.953 | E53: 665.122 | F53: 880.039 | G53: 865.945 | H53: 320.434 | I53: PKR m
A54: Short-term borrowings (incl. running finance; FCCL parent loan) | B54: Input - see register MLCF|stb | C54: 6642.312 | D54: 1894.115 | E54: 3572.073 | F54: 0 | G54: 1645.316 | H54: 822.285 | I54: PKR m
A55: Current portion of long-term financing | B55: Input - see register MLCF|cp_ltf | C55: 125 | D55: 1704.612 | E55: 2619.8 | F55: 2599.401 | G55: 3407.702 | H55: 3933.328 | I55: PKR m
A56: Current portion of lease liabilities | B56: Input - see register MLCF|cp_lease | C56: 0 | D56: 0 | E56: 6.837 | F56: 10.257 | G56: 13.909 | H56: 14.323 | I56: PKR m
A57: Current portion of deferred government grant | B57: Input - see register MLCF|cp_grant | C57: 0 | D57: 49.997 | E57: 184.576 | F57: 179.766 | G57: 155.439 | H57: 128.183 | I57: PKR m
A58: Unclaimed / unpaid dividends | B58: Input - see register MLCF|div_liab | C58: 48.053 | D58: 28.134 | E58: 27.569 | F58: 27.378 | G58: 27.256 | H58: 26.877 | I58: PKR m
A59: Taxation payable (net) | B59: Input - see register MLCF|tax_liab | C59: 0 | D59: 0 | E59: 0 | F59: 0 | G59: 0 | H59: 158.794 | I59: PKR m
A60: Other current liabilities | B60: Input - see register MLCF|cl_other | C60: 0 | D60: 0 | E60: 0 | F60: 0 | G60: 0 | H60: 0 | I60: PKR m
A61: Total current liabilities | B61: tap+contract+acc_markup+stb+cp_ltf+cp_lease+cp_grant+div_liab+tax_liab+cl_other | C61: =C50+C52+C53+C54+C55+C56+C57+C58+C59+C60 -> 15313.775 | D61: =D50+D52+D53+D54+D55+D56+D57+D58+D59+D60 -> 11449.448 | E61: =E50+E52+E53+E54+E55+E56+E57+E58+E59+E60 -> 16193.391 | F61: =F50+F52+F53+F54+F55+F56+F57+F58+F59+F60 -> 16215.021 | G61: =G50+G52+G53+G54+G55+G56+G57+G58+G59+G60 -> 18597.8 | H61: =H50+H52+H53+H54+H55+H56+H57+H58+H59+H60 -> 23330.491 | I61: PKR m | J61: Trade creditors memo line excluded (already inside trade and other payables)
A62: Total liabilities | B62: tot_ncl+tot_cl | C62: =C48+C61 -> 34688.94 | D62: =D48+D61 -> 28696.737 | E62: =E48+E61 -> 41655.195 | F62: =F48+F61 -> 44794.597 | G62: =G48+G61 -> 46749.774 | H62: =H48+H61 -> 47644.679 | I62: PKR m
A63: TOTAL EQUITY AND LIABILITIES | B63: tot_eq+tot_liab | C63: =C41+C62 -> 66009.771 | D63: =D41+D62 -> 66239.278 | E63: =E41+E62 -> 82214.21 | F63: =F41+F62 -> 89707.711 | G63: =G41+G62 -> 99365.682 | H63: =H41+H62 -> 119106.27 | I63: PKR m
A64: Derived balances used in ratios
A65: Inventories = stores and spares + stock-in-trade | B65: stores+sit | C65: =C30+C31 -> 10175.014 | D65: =D30+D31 -> 11888.9 | E65: =E30+E31 -> 15549.226 | F65: =F30+F31 -> 13800.46 | G65: =G30+G31 -> 15533.841 | H65: =H30+H31 -> 16904.301 | I65: PKR m
A66: Interest-bearing debt = LT financing + leases + ST borrowings + current portions | B66: ltf_nc+lease_nc+stb+cp_ltf+cp_lease | C66: =C43+C44+C54+C55+C56-C251-C252 -> 21940.414 | D66: =D43+D44+D54+D55+D56-D251-D252 -> 16235.476 | E66: =E43+E44+E54+E55+E56-E251-E252 -> 24973.714 | F66: =F43+F44+F54+F55+F56-F251-F252 -> 19874.403 | G66: =G43+G44+G54+G55+G56-G251-G252 -> 19387.383 | H66: =H43+H44+H54+H55+H56-H251-H252 -> 14580.07 | I66: PKR m
A67: Long-term interest-bearing debt (non-current financing + non-current leases) | B67: ltf_nc+lease_nc | C67: =C43+C44 -> 15173.102 | D67: =D43+D44 -> 12636.749 | E67: =E43+E44 -> 18775.004 | F67: =F43+F44 -> 17264.745 | G67: =G43+G44 -> 14320.456 | H67: =H43+H44 -> 9810.134 | I67: PKR m
I68: PKR m
I69: PKR m
A70: Invested capital = interest-bearing debt + equity | B70: ibd+tot_eq | C70: =C66+C41 -> 53261.245 | D70: =D66+D41 -> 53778.017 | E70: =E66+E41 -> 65532.729 | F70: =F66+F41 -> 64787.517 | G70: =G66+G41 -> 72003.291 | H70: =H66+H41 -> 86041.662 | I70: PKR m
A71: Capital employed = total assets - current liabilities | B71: tot_assets-tot_cl | C71: =C37-C61 -> 50695.996 | D71: =D37-D61 -> 54789.83 | E71: =E37-E61 -> 66020.819 | F71: =F37-F61 -> 73492.69 | G71: =G37-G61 -> 80767.882 | H71: =H37-H61 -> 95775.78 | I71: PKR m
A72: Operating current assets = CA - cash - ST investments | B72: tot_ca-cash-st_inv | C72: =C36-C34-C33 -> 15485.679 | D72: =D36-D34-D33 -> 16283.939 | E72: =E36-E34-E33 -> 19330.067 | F72: =F36-F34-F33 -> 17809.404 | G72: =G36-G34-G33 -> 21514.163 | H72: =H36-H34-H33 -> 23034.71 | I72: PKR m
A73: Operating current liabilities = CL - ST borrowings - current portions - accrued mark-up - dividends | B73: tot_cl-stb-cp_ltf-cp_lease-cp_grant-acc_markup-div_liab | C73: =C61-C54-C55-C56-C57-C53-C58 -> 7951.221 | D73: =D61-D54-D55-D56-D57-D53-D58 -> 7511.637 | E73: =E61-E54-E55-E56-E57-E53-E58 -> 9117.414 | F73: =F61-F54-F55-F56-F57-F53-F58 -> 12518.18 | G73: =G61-G54-G55-G56-G57-G53-G58 -> 12482.233 | H73: =H61-H54-H55-H56-H57-H53-H58 -> 18085.061 | I73: PKR m
A74: Source totals (as printed in audited statements) and checks
A75: Printed total assets | B75: Input - see register MLCF|pr_TA | C75: 66009.771 | D75: 66239.278 | E75: 82214.21 | F75: 89707.711 | G75: 99365.682 | H75: 119106.27 | I75: PKR m
A76: Printed total equity | B76: Input - see register MLCF|pr_EQ | C76: 31320.831 | D76: 37542.541 | E76: 40559.015 | F76: 44913.114 | G76: 52615.908 | H76: 71461.592 | I76: PKR m
A77: Printed total current assets | B77: Input - see register MLCF|pr_CA | C77: 16607.191 | D77: 16923.416 | E77: 20321.989 | F77: 22239.667 | G77: 26867.837 | H77: 35752.604 | I77: PKR m
A78: Printed total current liabilities | B78: Input - see register MLCF|pr_CL | C78: 15313.775 | D78: 11449.448 | E78: 16193.391 | F78: 16215.021 | G78: 18597.8 | H78: 23330.491 | I78: PKR m
A79: Check: total assets = equity + liabilities | B79: Validation formula | C79: =IF(ABS(C37-C63)<0.005,"PASS","FAIL") -> PASS | D79: =IF(ABS(D37-D63)<0.005,"PASS","FAIL") -> PASS | E79: =IF(ABS(E37-E63)<0.005,"PASS","FAIL") -> PASS | F79: =IF(ABS(F37-F63)<0.005,"PASS","FAIL") -> PASS | G79: =IF(ABS(G37-G63)<0.005,"PASS","FAIL") -> PASS | H79: =IF(ABS(H37-H63)<0.005,"PASS","FAIL") -> PASS
A80: Check: total assets = printed total | B80: Validation formula | C80: =IF(ABS(C37-C75)<0.005,"PASS","FAIL") -> PASS | D80: =IF(ABS(D37-D75)<0.005,"PASS","FAIL") -> PASS | E80: =IF(ABS(E37-E75)<0.005,"PASS","FAIL") -> PASS | F80: =IF(ABS(F37-F75)<0.005,"PASS","FAIL") -> PASS | G80: =IF(ABS(G37-G75)<0.005,"PASS","FAIL") -> PASS | H80: =IF(ABS(H37-H75)<0.005,"PASS","FAIL") -> PASS
A81: Check: equity, CA and CL = printed subtotals | B81: Validation formula | C81: =IF(AND(ABS(C41-C76)<0.005,ABS(C36-C77)<0.005,ABS(C61-C78)<0.005),"PASS","FAIL") -> PASS | D81: =IF(AND(ABS(D41-D76)<0.005,ABS(D36-D77)<0.005,ABS(D61-D78)<0.005),"PASS","FAIL") -> PASS | E81: =IF(AND(ABS(E41-E76)<0.005,ABS(E36-E77)<0.005,ABS(E61-E78)<0.005),"PASS","FAIL") -> PASS | F81: =IF(AND(ABS(F41-F76)<0.005,ABS(F36-F77)<0.005,ABS(F61-F78)<0.005),"PASS","FAIL") -> PASS | G81: =IF(AND(ABS(G41-G76)<0.005,ABS(G36-G77)<0.005,ABS(G61-G78)<0.005),"PASS","FAIL") -> PASS | H81: =IF(AND(ABS(H41-H76)<0.005,ABS(H36-H77)<0.005,ABS(H61-H78)<0.005),"PASS","FAIL") -> PASS
A83: C. STATEMENT OF PROFIT OR LOSS (PKR million)
A84: Revenue / net sales | B84: Input - see register MLCF|rev | D84: 35538.301 | E84: 48519.622 | F84: 62075.259 | G84: 66452.348 | H84: 68942.446 | I84: PKR m
A85: Cost of sales | B85: Input - see register MLCF|cogs | D85: -28135.419 | E85: -36244.156 | F85: -43901.906 | G85: -45488.064 | H85: -45195.63 | I85: PKR m
A86: Gross profit | B86: rev+cogs | D86: =D84+D85 -> 7402.882 | E86: =E84+E85 -> 12275.466 | F86: =F84+F85 -> 18173.353 | G86: =G84+G85 -> 20964.284 | H86: =H84+H85 -> 23746.816 | I86: PKR m
A87: Selling and distribution expenses | B87: Input - see register MLCF|selling | D87: -1013.852 | E87: -1483.876 | F87: -3751.096 | G87: -5471.808 | H87: -4123.754 | I87: PKR m
A88: Administrative expenses | B88: Input - see register MLCF|admin | D88: -813.489 | E88: -971.453 | F88: -1380.607 | G88: -1852.148 | H88: -2176.32 | I88: PKR m
A89: Impairment / expected credit loss on financial assets | B89: Input - see register MLCF|impair | D89: 0 | E89: -209.92 | F89: -191.421 | G89: -357.191 | H89: -514.43 | I89: PKR m
A90: Other operating expenses (incl. WPPF/WWF) | B90: Input - see register MLCF|oth_exp | D90: -524.142 | E90: -742.28 | F90: -995.46 | G90: -569.545 | H90: -1207.018 | I90: PKR m
A91: Operating profit (core) = GP - operating expenses, excl. other income | B91: gp+selling+admin+impair+oth_exp | D91: =D86+D87+D88+D89+D90 -> 5051.399 | E91: =E86+E87+E88+E89+E90 -> 8867.937 | F91: =F86+F87+F88+F89+F90 -> 11854.769 | G91: =G86+G87+G88+G89+G90 -> 12713.592 | H91: =H86+H87+H88+H89+H90 -> 15725.294 | I91: PKR m
A92: Other income | B92: Input - see register MLCF|oth_inc | D92: 3732.132 | E92: 56.601 | F92: 146.646 | G92: 238.451 | H92: 8462.656 | I92: PKR m
A93: Finance income (where presented separately) | B93: Input - see register MLCF|fin_inc | D93: 0 | E93: 0 | F93: 0 | G93: 117.691 | H93: 1031.075 | I93: PKR m
A94: Share of profit of associate | B94: Input - see register MLCF|assoc | D94: 0 | E94: 0 | F94: 0 | G94: 0 | H94: 0 | I94: PKR m
A95: Finance cost | B95: Input - see register MLCF|fin_cost | D95: -1493.93 | E95: -1741.026 | F95: -2750.748 | G95: -4138.286 | H95: -3554.788 | I95: PKR m
A96: Profit before levies and income tax | B96: core_op+oth_inc+fin_inc+assoc+fin_cost | D96: =D91+D92+D93+D94+D95 -> 7289.601 | E96: =E91+E92+E93+E94+E95 -> 7183.512 | F96: =F91+F92+F93+F94+F95 -> 9250.667 | G96: =G91+G92+G93+G94+G95 -> 8931.448 | H96: =H91+H92+H93+H94+H95 -> 21664.237 | I96: PKR m
A97: Levies (final / minimum taxes presented separately) | B97: Input - see register MLCF|levy | D97: 0 | E97: 0 | F97: -12.192 | G97: -45.804 | H97: -38.972 | I97: PKR m
A98: Income tax | B98: Input - see register MLCF|tax | D98: -1035.492 | E98: -3557.172 | F98: -4746.806 | G98: -3613.117 | H98: -4588.891 | I98: PKR m
A99: Profit after tax (attributable to ordinary shareholders) | B99: pbt_pre+levy+tax | D99: =D96+D97+D98 -> 6254.109 | E99: =E96+E97+E98 -> 3626.34 | F99: =F96+F97+F98 -> 4491.669 | G99: =G96+G97+G98 -> 5272.527 | H99: =H96+H97+H98 -> 17036.374 | I99: PKR m
A100: Printed gross profit | B100: Input - see register MLCF|pr_gp | D100: 7402.882 | E100: 12275.466 | F100: 18173.353 | G100: 20964.284 | H100: 23746.816 | I100: PKR m
A101: Printed profit before levies and income tax | B101: Input - see register MLCF|pr_pbt | D101: 7289.601 | E101: 7183.512 | F101: 9250.667 | G101: 8931.448 | H101: 21664.237 | I101: PKR m
A102: Printed profit after tax | B102: Input - see register MLCF|pr_pat | D102: 6254.109 | E102: 3626.34 | F102: 4491.669 | G102: 5272.527 | H102: 17036.374 | I102: PKR m
A103: Check: GP, PBT and PAT agree to printed statement | B103: Validation formula | D103: =IF(AND(ABS(D86-D100)<0.005,ABS(D96-D101)<0.005,ABS(D99-D102)<0.005),"PASS","FAIL") -> PASS | E103: =IF(AND(ABS(E86-E100)<0.005,ABS(E96-E101)<0.005,ABS(E99-E102)<0.005),"PASS","FAIL") -> PASS | F103: =IF(AND(ABS(F86-F100)<0.005,ABS(F96-F101)<0.005,ABS(F99-F102)<0.005),"PASS","FAIL") -> PASS | G103: =IF(AND(ABS(G86-G100)<0.005,ABS(G96-G101)<0.005,ABS(G99-G102)<0.005),"PASS","FAIL") -> PASS | H103: =IF(AND(ABS(H86-H100)<0.005,ABS(H96-H101)<0.005,ABS(H99-H102)<0.005),"PASS","FAIL") -> PASS
...

Sheet FCCL
A1: Fauji Cement Company Limited (FCCL) - five-year financial analysis, FY2021-FY2025
A2: Competitor 4 | PSX: FCCL | Standalone (single-entity financial statements; no consolidated statements published) | All amounts PKR million unless stated
A3: SOURCE INPUTS retained. Ratio tables below are ARCHIVED prior-33-measure workings; use 27 Calculations for final results. Blue = audited input; black = formula.
A5: A. COMPANY AND DATA INFORMATION
A6: Company | B6: Fauji Cement Company Limited
A7: PSX symbol | B7: FCCL
A8: Role in project | B8: Competitor 4
A9: Financial year-end | B9: 30 June (FY2021 = year ended 30 June 2021, etc.)
A10: Reporting basis | B10: Standalone (single-entity financial statements; no consolidated statements published)
A11: Original audited units | B11: Rs '000 - normalised here to PKR million (full precision retained)
A12: Annual reports used | B12: FY2021: FCCL-Annual-Report-2021.pdf; FY2022: FCCL-Annual-Report-2022.pdf; FY2023: FCCL-Annual-Report-2023.pdf; FY2024: FCCL-Annual-Report-2024.pdf; FY2025: FCCL-Annual-Report-2025.pdf
A13: Year selection rule | B13: Each year taken from the most recent audited presentation: FY2025 from FY2025 AR; FY2020-FY2024 from the comparative column of the following year's AR (captures restatements). FY2020 = opening balances only.
A14: Per-share basis | B14: Actual PSX FY-end close paired with the share basis in force on that date. EPS notes, splits, treasury shares and bonus treatment are documented on Share Basis.
A15: Source register | B15: Every blue input is listed with report, statement, PDF page, printed page and remarks on the Sources & Validation sheet.
A17: Item | B17: Definition / formula / source note | C17: FY2020* | D17: FY2021 | E17: FY2022 | F17: FY2023 | G17: FY2024 | H17: FY2025 | I17: Units | J17: Comments
A18: B. STATEMENT OF FINANCIAL POSITION (PKR million; FY2020 = opening balances only)
A19: Non-current assets
A20: Property, plant and equipment (as presented) | B20: Input - see register FCCL|ppe | C20: 22065.172 | D20: 21422.215 | E20: 74126.315 | F20: 104425.18 | G20: 110845.66 | H20: 109579.09 | I20: PKR m
A21: of which: capital work-in-progress (note) | B21: Input - see register FCCL|cwip | C21: 2.808 | D21: 202.087 | E21: 29802.17 | F21: 34531.172 | G21: 700.153 | H21: 296.574 | I21: PKR m
A22: Operating fixed assets = PPE less CWIP | B22: PPE - CWIP | C22: =C20-C21 -> 22062.364 | D22: =D20-D21 -> 21220.128 | E22: =E20-E21 -> 44324.145 | F22: =F20-F21 -> 69894.009 | G22: =G20-G21 -> 110145.51 | H22: =H20-H21 -> 109282.52 | I22: PKR m
A23: Right-of-use assets (presented separately) | B23: Input - see register FCCL|rou | C23: 60.322 | D23: 89.334 | E23: 132.263 | F23: 181.38 | G23: 131.165 | H23: 126.445 | I23: PKR m
A24: Intangible assets | B24: Input - see register FCCL|intang | C24: 0 | D24: 0 | E24: 11029.756 | F24: 10957.737 | G24: 10745.7 | H24: 10533.667 | I24: PKR m
A25: Investment property | B25: Input - see register FCCL|inv_prop | C25: 0 | D25: 0 | E25: 0 | F25: 0 | G25: 0 | H25: 0 | I25: PKR m
A26: Long-term investments | B26: Input - see register FCCL|lt_inv | C26: 0 | D26: 15.349 | E26: 66.657 | F26: 0 | G26: 0 | H26: 0 | I26: PKR m
A27: Other non-current assets | B27: Input - see register FCCL|nca_other | C27: 99.101 | D27: 86.601 | E27: 126.274 | F27: 129.7 | G27: 129.7 | H27: 133.425 | I27: PKR m
A28: Total non-current assets | B28: Sum of above (excl. memo) | C28: =C20+C23+C24+C25+C26+C27 -> 22224.595 | D28: =D20+D23+D24+D25+D26+D27 -> 21613.499 | E28: =E20+E23+E24+E25+E26+E27 -> 85481.265 | F28: =F20+F23+F24+F25+F26+F27 -> 115694 | G28: =G20+G23+G24+G25+G26+G27 -> 121852.23 | H28: =H20+H23+H24+H25+H26+H27 -> 120372.63 | I28: PKR m
A29: Current assets
A30: Stores, spares and loose tools | B30: Input - see register FCCL|stores | C30: 3505.809 | D30: 4250.754 | E30: 11939.147 | F30: 8011.181 | G30: 9099.13 | H30: 10377.008 | I30: PKR m
A31: Stock-in-trade | B31: Input - see register FCCL|sit | C31: 1187.752 | D31: 1189.198 | E31: 3697.721 | F31: 7112.327 | G31: 7495.705 | H31: 9337.617 | I31: PKR m
A32: Trade debts | B32: Input - see register FCCL|debts | C32: 1050.64 | D32: 1449.6 | E32: 2412.758 | F32: 3572.445 | G32: 5545.241 | H32: 6911.322 | I32: PKR m
A33: Short-term investments | B33: Input - see register FCCL|st_inv | C33: 0 | D33: 4397.699 | E33: 3843.01 | F33: 250 | G33: 250 | H33: 9210.1 | I33: PKR m
A34: Cash and bank balances | B34: Input - see register FCCL|cash | C34: 561.174 | D34: 900.778 | E34: 2306.633 | F34: 970.457 | G34: 2932.984 | H34: 2665.338 | I34: PKR m
A35: Other current assets | B35: Input - see register FCCL|ca_other | C35: 677.946 | D35: 250.703 | E35: 4017.543 | F35: 3218.089 | G35: 461.011 | H35: 1971.18 | I35: PKR m
A36: Total current assets | B36: stores+sit+debts+st_inv+cash+ca_other | C36: =C30+C31+C32+C33+C34+C35 -> 6983.321 | D36: =D30+D31+D32+D33+D34+D35 -> 12438.732 | E36: =E30+E31+E32+E33+E34+E35 -> 28216.812 | F36: =F30+F31+F32+F33+F34+F35 -> 23134.499 | G36: =G30+G31+G32+G33+G34+G35 -> 25784.071 | H36: =H30+H31+H32+H33+H34+H35 -> 40472.565 | I36: PKR m
A37: TOTAL ASSETS | B37: tot_nca+tot_ca | C37: =C28+C36 -> 29207.916 | D37: =D28+D36 -> 34052.231 | E37: =E28+E36 -> 113698.08 | F37: =F28+F36 -> 138828.5 | G37: =G28+G36 -> 147636.3 | H37: =H28+H36 -> 160845.19 | I37: PKR m
A38: Equity
A39: Issued, subscribed and paid-up share capital | B39: Input - see register FCCL|share_cap | C39: 13798.15 | D39: 13798.15 | E39: 21803.09 | F39: 24528.476 | G39: 24528.476 | H39: 24528.476 | I39: PKR m
A40: Reserves, retained earnings and revaluation surplus | B40: Input - see register FCCL|eq_other | C40: 6006.17 | D40: 9477.521 | E40: 35932.966 | F40: 40647.261 | G40: 48870.377 | H40: 59743.732 | I40: PKR m
A41: Total equity | B41: share_cap+eq_other | C41: =C39+C40 -> 19804.32 | D41: =D39+D40 -> 23275.671 | E41: =E39+E40 -> 57736.056 | F41: =F39+F40 -> 65175.737 | G41: =G39+G40 -> 73398.853 | H41: =H39+H40 -> 84272.208 | I41: PKR m
A42: Non-current liabilities
A43: Long-term financing (non-current, interest-bearing) | B43: Input - see register FCCL|ltf_nc | C43: 447.327 | D43: 491.502 | E43: 19555.997 | F43: 31777.087 | G43: 29908.287 | H43: 24208.633 | I43: PKR m
A44: Lease liabilities (non-current) | B44: Input - see register FCCL|lease_nc | C44: 57.656 | D44: 73.593 | E44: 89.965 | F44: 118.972 | G44: 117.454 | H44: 101.211 | I44: PKR m
A45: Deferred government grant (non-current) | B45: Input - see register FCCL|grant_nc | C45: 0 | D45: 6.607 | E45: 1982.301 | F45: 2745.849 | G45: 2164.959 | H45: 1647.63 | I45: PKR m
A46: Deferred tax liability | B46: Input - see register FCCL|def_tax | C46: 3643.608 | D46: 3960.489 | E46: 7433.214 | F46: 10312.402 | G46: 14931.049 | H46: 19694.422 | I46: PKR m
A47: Other non-current liabilities | B47: Input - see register FCCL|ncl_other | C47: 72.547 | D47: 82.38 | E47: 179.291 | F47: 211.595 | G47: 250.23 | H47: 283.59 | I47: PKR m
A48: Total non-current liabilities | B48: ltf_nc+lease_nc+grant_nc+def_tax+ncl_other | C48: =C43+C44+C45+C46+C47 -> 4221.138 | D48: =D43+D44+D45+D46+D47 -> 4614.571 | E48: =E43+E44+E45+E46+E47 -> 29240.768 | F48: =F43+F44+F45+F46+F47 -> 45165.905 | G48: =G43+G44+G45+G46+G47 -> 47371.979 | H48: =H43+H44+H45+H46+H47 -> 45935.486 | I48: PKR m
A49: Current liabilities
A50: Trade and other payables | B50: Input - see register FCCL|tap | C50: 1163.246 | D50: 1822.642 | E50: 6917.149 | F50: 6516.462 | G50: 6108.79 | H50: 3934.508 | I50: PKR m
A51: memo: trade creditors / bills payable (note) | B51: Input - see register FCCL|trade_cred | C51: 354.586 | D51: 863.038 | E51: 2683.21 | F51: 2623.342 | G51: 2726.664 | H51: 2034.141 | I51: PKR m
A52: Contract liabilities / advances from customers | B52: Input - see register FCCL|contract | C52: 367.952 | D52: 435.097 | E52: 862.309 | F52: 584.809 | G52: 432.704 | H52: 588.076 | I52: PKR m
A53: Accrued mark-up / interest | B53: Input - see register FCCL|acc_markup | C53: 0 | D53: 0 | E53: 0 | F53: 0 | G53: 0 | H53: 0 | I53: PKR m
A54: Short-term borrowings (incl. running finance; FCCL parent loan) | B54: Input - see register FCCL|stb | C54: 1869.167 | D54: 1616.787 | E54: 10605.249 | F54: 11917.981 | G54: 8837.934 | H54: 9764.648 | I54: PKR m
A55: Current portion of long-term financing | B55: Input - see register FCCL|cp_ltf | C55: 303.912 | D55: 361.521 | E55: 2985.087 | F55: 4176.493 | G55: 5066.868 | H55: 6104.065 | I55: PKR m
A56: Current portion of lease liabilities | B56: Input - see register FCCL|cp_lease | C56: 23.737 | D56: 24.686 | E56: 68.332 | F56: 50.463 | G56: 46.206 | H56: 43.099 | I56: PKR m
A57: Current portion of deferred government grant | B57: Input - see register FCCL|cp_grant | C57: 0 | D57: 15.654 | E57: 366.464 | F57: 604.292 | G57: 580.891 | H57: 515.175 | I57: PKR m
A58: Unclaimed / unpaid dividends | B58: Input - see register FCCL|div_liab | C58: 40.051 | D58: 38.479 | E58: 37.157 | F58: 36.001 | G58: 35.646 | H58: 41.182 | I58: PKR m
A59: Taxation payable (net) | B59: Input - see register FCCL|tax_liab | C59: 0 | D59: 0 | E59: 0 | F59: 0 | G59: 56.81 | H59: 0 | I59: PKR m
A60: Other current liabilities | B60: Input - see register FCCL|cl_other | C60: 1414.393 | D60: 1847.123 | E60: 4879.506 | F60: 4600.354 | G60: 5699.618 | H60: 9646.744 | I60: PKR m
A61: Total current liabilities | B61: tap+contract+acc_markup+stb+cp_ltf+cp_lease+cp_grant+div_liab+tax_liab+cl_other | C61: =C50+C52+C53+C54+C55+C56+C57+C58+C59+C60 -> 5182.458 | D61: =D50+D52+D53+D54+D55+D56+D57+D58+D59+D60 -> 6161.989 | E61: =E50+E52+E53+E54+E55+E56+E57+E58+E59+E60 -> 26721.253 | F61: =F50+F52+F53+F54+F55+F56+F57+F58+F59+F60 -> 28486.855 | G61: =G50+G52+G53+G54+G55+G56+G57+G58+G59+G60 -> 26865.467 | H61: =H50+H52+H53+H54+H55+H56+H57+H58+H59+H60 -> 30637.497 | I61: PKR m | J61: Trade creditors memo line excluded (already inside trade and other payables)
A62: Total liabilities | B62: tot_ncl+tot_cl | C62: =C48+C61 -> 9403.596 | D62: =D48+D61 -> 10776.56 | E62: =E48+E61 -> 55962.021 | F62: =F48+F61 -> 73652.76 | G62: =G48+G61 -> 74237.446 | H62: =H48+H61 -> 76572.983 | I62: PKR m
A63: TOTAL EQUITY AND LIABILITIES | B63: tot_eq+tot_liab | C63: =C41+C62 -> 29207.916 | D63: =D41+D62 -> 34052.231 | E63: =E41+E62 -> 113698.08 | F63: =F41+F62 -> 138828.5 | G63: =G41+G62 -> 147636.3 | H63: =H41+H62 -> 160845.19 | I63: PKR m
A64: Derived balances used in ratios
A65: Inventories = stores and spares + stock-in-trade | B65: stores+sit | C65: =C30+C31 -> 4693.561 | D65: =D30+D31 -> 5439.952 | E65: =E30+E31 -> 15636.868 | F65: =F30+F31 -> 15123.508 | G65: =G30+G31 -> 16594.835 | H65: =H30+H31 -> 19714.625 | I65: PKR m
A66: Interest-bearing debt = LT financing + leases + ST borrowings + current portions | B66: ltf_nc+lease_nc+stb+cp_ltf+cp_lease | C66: =C43+C44+C54+C55+C56-C251-C252 -> 2701.799 | D66: =D43+D44+D54+D55+D56-D251-D252 -> 2568.089 | E66: =E43+E44+E54+E55+E56-E251-E252 -> 25917.63 | F66: =F43+F44+F54+F55+F56-F251-F252 -> 40653.996 | G66: =G43+G44+G54+G55+G56-G251-G252 -> 36589.749 | H66: =H43+H44+H54+H55+H56-H251-H252 -> 40036.47 | I66: PKR m
A67: Long-term interest-bearing debt (non-current financing + non-current leases) | B67: ltf_nc+lease_nc | C67: =C43+C44 -> 504.983 | D67: =D43+D44 -> 565.095 | E67: =E43+E44 -> 19645.962 | F67: =F43+F44 -> 31896.059 | G67: =G43+G44 -> 30025.741 | H67: =H43+H44 -> 24309.844 | I67: PKR m
I68: PKR m
I69: PKR m
A70: Invested capital = interest-bearing debt + equity | B70: ibd+tot_eq | C70: =C66+C41 -> 22506.119 | D70: =D66+D41 -> 25843.76 | E70: =E66+E41 -> 83653.686 | F70: =F66+F41 -> 105829.73 | G70: =G66+G41 -> 109988.6 | H70: =H66+H41 -> 124308.68 | I70: PKR m
A71: Capital employed = total assets - current liabilities | B71: tot_assets-tot_cl | C71: =C37-C61 -> 24025.458 | D71: =D37-D61 -> 27890.242 | E71: =E37-E61 -> 86976.824 | F71: =F37-F61 -> 110341.64 | G71: =G37-G61 -> 120770.83 | H71: =H37-H61 -> 130207.69 | I71: PKR m
A72: Operating current assets = CA - cash - ST investments | B72: tot_ca-cash-st_inv | C72: =C36-C34-C33 -> 6422.147 | D72: =D36-D34-D33 -> 7140.255 | E72: =E36-E34-E33 -> 22067.169 | F72: =F36-F34-F33 -> 21914.042 | G72: =G36-G34-G33 -> 22601.087 | H72: =H36-H34-H33 -> 28597.127 | I72: PKR m
A73: Operating current liabilities = CL - ST borrowings - current portions - accrued mark-up - dividends | B73: tot_cl-stb-cp_ltf-cp_lease-cp_grant-acc_markup-div_liab | C73: =C61-C54-C55-C56-C57-C53-C58 -> 2945.591 | D73: =D61-D54-D55-D56-D57-D53-D58 -> 4104.862 | E73: =E61-E54-E55-E56-E57-E53-E58 -> 12658.964 | F73: =F61-F54-F55-F56-F57-F53-F58 -> 11701.625 | G73: =G61-G54-G55-G56-G57-G53-G58 -> 12297.922 | H73: =H61-H54-H55-H56-H57-H53-H58 -> 14169.328 | I73: PKR m
A74: Source totals (as printed in audited statements) and checks
A75: Printed total assets | B75: Input - see register FCCL|pr_TA | C75: 29207.916 | D75: 34052.231 | E75: 113698.08 | F75: 138828.5 | G75: 147636.3 | H75: 160845.19 | I75: PKR m
A76: Printed total equity | B76: Input - see register FCCL|pr_EQ | C76: 19804.32 | D76: 23275.671 | E76: 57736.056 | F76: 65175.737 | G76: 73398.853 | H76: 84272.208 | I76: PKR m
A77: Printed total current assets | B77: Input - see register FCCL|pr_CA | C77: 6983.321 | D77: 12438.732 | E77: 28216.812 | F77: 23134.499 | G77: 25784.071 | H77: 40472.565 | I77: PKR m
A78: Printed total current liabilities | B78: Input - see register FCCL|pr_CL | C78: 5182.458 | D78: 6161.989 | E78: 26721.253 | F78: 28486.855 | G78: 26865.467 | H78: 30637.497 | I78: PKR m
A79: Check: total assets = equity + liabilities | B79: Validation formula | C79: =IF(ABS(C37-C63)<0.005,"PASS","FAIL") -> PASS | D79: =IF(ABS(D37-D63)<0.005,"PASS","FAIL") -> PASS | E79: =IF(ABS(E37-E63)<0.005,"PASS","FAIL") -> PASS | F79: =IF(ABS(F37-F63)<0.005,"PASS","FAIL") -> PASS | G79: =IF(ABS(G37-G63)<0.005,"PASS","FAIL") -> PASS | H79: =IF(ABS(H37-H63)<0.005,"PASS","FAIL") -> PASS
A80: Check: total assets = printed total | B80: Validation formula | C80: =IF(ABS(C37-C75)<0.005,"PASS","FAIL") -> PASS | D80: =IF(ABS(D37-D75)<0.005,"PASS","FAIL") -> PASS | E80: =IF(ABS(E37-E75)<0.005,"PASS","FAIL") -> PASS | F80: =IF(ABS(F37-F75)<0.005,"PASS","FAIL") -> PASS | G80: =IF(ABS(G37-G75)<0.005,"PASS","FAIL") -> PASS | H80: =IF(ABS(H37-H75)<0.005,"PASS","FAIL") -> PASS
A81: Check: equity, CA and CL = printed subtotals | B81: Validation formula | C81: =IF(AND(ABS(C41-C76)<0.005,ABS(C36-C77)<0.005,ABS(C61-C78)<0.005),"PASS","FAIL") -> PASS | D81: =IF(AND(ABS(D41-D76)<0.005,ABS(D36-D77)<0.005,ABS(D61-D78)<0.005),"PASS","FAIL") -> PASS | E81: =IF(AND(ABS(E41-E76)<0.005,ABS(E36-E77)<0.005,ABS(E61-E78)<0.005),"PASS","FAIL") -> PASS | F81: =IF(AND(ABS(F41-F76)<0.005,ABS(F36-F77)<0.005,ABS(F61-F78)<0.005),"PASS","FAIL") -> PASS | G81: =IF(AND(ABS(G41-G76)<0.005,ABS(G36-G77)<0.005,ABS(G61-G78)<0.005),"PASS","FAIL") -> PASS | H81: =IF(AND(ABS(H41-H76)<0.005,ABS(H36-H77)<0.005,ABS(H61-H78)<0.005),"PASS","FAIL") -> PASS
A83: C. STATEMENT OF PROFIT OR LOSS (PKR million)
A84: Revenue / net sales | B84: Input - see register FCCL|rev | D84: 24271.285 | E84: 54243.118 | F84: 68069.282 | G84: 80026.226 | H84: 88956.328 | I84: PKR m
A85: Cost of sales | B85: Input - see register FCCL|cogs | D85: -18206.88 | E85: -38779.542 | F85: -47650.809 | G85: -54345.821 | H85: -57384.978 | I85: PKR m
A86: Gross profit | B86: rev+cogs | D86: =D84+D85 -> 6064.405 | E86: =E84+E85 -> 15463.576 | F86: =F84+F85 -> 20418.473 | G86: =G84+G85 -> 25680.405 | H86: =H84+H85 -> 31571.35 | I86: PKR m
A87: Selling and distribution expenses | B87: Input - see register FCCL|selling | D87: -189.537 | E87: -1603.323 | F87: -2705.263 | G87: -3285.923 | H87: -2935.139 | I87: PKR m
A88: Administrative expenses | B88: Input - see register FCCL|admin | D88: -524.709 | E88: -1299.439 | F88: -1381.633 | G88: -1516.046 | H88: -1688.886 | I88: PKR m
A89: Impairment / expected credit loss on financial assets | B89: Input - see register FCCL|impair | D89: 0 | E89: 0 | F89: 0 | G89: 0 | H89: 0 | I89: PKR m
A90: Other operating expenses (incl. WPPF/WWF) | B90: Input - see register FCCL|oth_exp | D90: -377.946 | E90: -808.964 | F90: -750.078 | G90: -826.875 | H90: -1479.276 | I90: PKR m
A91: Operating profit (core) = GP - operating expenses, excl. other income | B91: gp+selling+admin+impair+oth_exp | D91: =D86+D87+D88+D89+D90 -> 4972.213 | E91: =E86+E87+E88+E89+E90 -> 11751.85 | F91: =F86+F87+F88+F89+F90 -> 15581.499 | G91: =G86+G87+G88+G89+G90 -> 20051.561 | H91: =H86+H87+H88+H89+H90 -> 25468.049 | I91: PKR m
A92: Other income | B92: Input - see register FCCL|oth_inc | D92: 81.71 | E92: 230.695 | F92: 436.173 | G92: 540.373 | H92: 760.772 | I92: PKR m
A93: Finance income (where presented separately) | B93: Input - see register FCCL|fin_inc | D93: 160.543 | E93: 745.852 | F93: 527.702 | G93: 299.318 | H93: 1068.831 | I93: PKR m
A94: Share of profit of associate | B94: Input - see register FCCL|assoc | D94: 2.849 | E94: 1.308 | F94: 0 | G94: 0 | H94: 0 | I94: PKR m
A95: Finance cost | B95: Input - see register FCCL|fin_cost | D95: -109.623 | E95: -1201.612 | F95: -3645.265 | G95: -5536.298 | H95: -5772.132 | I95: PKR m
A96: Profit before levies and income tax | B96: core_op+oth_inc+fin_inc+assoc+fin_cost | D96: =D91+D92+D93+D94+D95 -> 5107.692 | E96: =E91+E92+E93+E94+E95 -> 11528.093 | F96: =F91+F92+F93+F94+F95 -> 12900.109 | G96: =G91+G92+G93+G94+G95 -> 15354.954 | H96: =H91+H92+H93+H94+H95 -> 21525.52 | I96: PKR m
A97: Levies (final / minimum taxes presented separately) | B97: Input - see register FCCL|levy | D97: 0 | E97: 0 | F97: -45.66 | G97: -55.223 | H97: 0 | I97: PKR m
A98: Income tax | B98: Input - see register FCCL|tax | D98: -1636.341 | E98: -4415.553 | F98: -5414.768 | G98: -7076.615 | H98: -8199.318 | I98: PKR m
A99: Profit after tax (attributable to ordinary shareholders) | B99: pbt_pre+levy+tax | D99: =D96+D97+D98 -> 3471.351 | E99: =E96+E97+E98 -> 7112.54 | F99: =F96+F97+F98 -> 7439.681 | G99: =G96+G97+G98 -> 8223.116 | H99: =H96+H97+H98 -> 13326.202 | I99: PKR m
A100: Printed gross profit | B100: Input - see register FCCL|pr_gp | D100: 6064.405 | E100: 15463.576 | F100: 20418.473 | G100: 25680.405 | H100: 31571.35 | I100: PKR m
A101: Printed profit before levies and income tax | B101: Input - see register FCCL|pr_pbt | D101: 5107.692 | E101: 11528.093 | F101: 12900.109 | G101: 15354.954 | H101: 21525.52 | I101: PKR m
A102: Printed profit after tax | B102: Input - see register FCCL|pr_pat | D102: 3471.351 | E102: 7112.54 | F102: 7439.681 | G102: 8223.116 | H102: 13326.202 | I102: PKR m
A103: Check: GP, PBT and PAT agree to printed statement | B103: Validation formula | D103: =IF(AND(ABS(D86-D100)<0.005,ABS(D96-D101)<0.005,ABS(D99-D102)<0.005),"PASS","FAIL") -> PASS | E103: =IF(AND(ABS(E86-E100)<0.005,ABS(E96-E101)<0.005,ABS(E99-E102)<0.005),"PASS","FAIL") -> PASS | F103: =IF(AND(ABS(F86-F100)<0.005,ABS(F96-F101)<0.005,ABS(F99-F102)<0.005),"PASS","FAIL") -> PASS | G103: =IF(AND(ABS(G86-G100)<0.005,ABS(G96-G101)<0.005,ABS(G99-G102)<0.005),"PASS","FAIL") -> PASS | H103: =IF(AND(ABS(H86-H100)<0.005,ABS(H96-H101)<0.005,ABS(H99-H102)<0.005),"PASS","FAIL") -> PASS
...

Sheet Industry Comparison
A1: ARCHIVED - prior 33-measure industry comparison
A2: All values are live links to the company sheets. Sample average = arithmetic mean of valid company observations (n/m excluded). Favourable/unfavourable shown only where direction is unambiguous.
A4: Category | B4: No. | C4: Measure | D4: Year | E4: KOHC | F4: LUCK | G4: DGKC | H4: MLCF | I4: FCCL | J4: Sample avg (5) | K4: N valid | L4: KOHC - avg | M4: 4-competitor avg | N4: Median (5) | O4: Direction | P4: KOHC position vs average | Q4: Notes | R4: Avg check
A5: LIQUIDITY
A6: Liquidity | B6: 1 | C6: 1. Current ratio
C7: Current ratio | D7: FY2021 | E7: =KOHC!D138 -> 1.3006447 | F7: =LUCK!D138 -> 1.3386079 | G7: =DGKC!D138 -> 0.91452509 | H7: =MLCF!D138 -> 1.4780989 | I7: =FCCL!D138 -> 2.0186229 | J7: =IF(COUNT(E7:I7)=0,"n/m",AVERAGE(E7:I7)) -> 1.4100999 | K7: =COUNT(E7:I7) -> 5 | L7: =IF(AND(ISNUMBER(E7),ISNUMBER(J7)),E7-J7,"n/m") -> -0.10945522 | M7: =IF(COUNT(F7:I7)=0,"n/m",AVERAGE(F7:I7)) -> 1.4374637 | N7: =IF(COUNT(E7:I7)=0,"n/m",MEDIAN(E7:I7)) -> 1.3386079 | O7: Higher | P7: =IF(NOT(ISNUMBER(L7)),"n/m",IF(O7="Higher",IF(L7>=0,"Above avg - favourable","Below avg - unfavourable"),IF(O7="Lower",IF(L7<=0,"Below avg - favourable","Above avg - unfavourable"),IF(L7>=0,"Above avg - context-dependent","Below avg - context-dependent"))))&IF(K7<5," (N="&K7&")","") -> Below avg - unfavourable | R7: =IF(K7=0,"n/m",IF(ABS(J7-SUM(E7:I7)/K7)<0.000000001,"OK","ERR")) -> OK
C8: Current ratio | D8: FY2022 | E8: =KOHC!E138 -> 1.8735085 | F8: =LUCK!E138 -> 1.4760766 | G8: =DGKC!E138 -> 0.88552877 | H8: =MLCF!E138 -> 1.2549557 | I8: =FCCL!E138 -> 1.0559689 | J8: =IF(COUNT(E8:I8)=0,"n/m",AVERAGE(E8:I8)) -> 1.3092077 | K8: =COUNT(E8:I8) -> 5 | L8: =IF(AND(ISNUMBER(E8),ISNUMBER(J8)),E8-J8,"n/m") -> 0.56430081 | M8: =IF(COUNT(F8:I8)=0,"n/m",AVERAGE(F8:I8)) -> 1.1681325 | N8: =IF(COUNT(E8:I8)=0,"n/m",MEDIAN(E8:I8)) -> 1.2549557 | O8: Higher | P8: =IF(NOT(ISNUMBER(L8)),"n/m",IF(O8="Higher",IF(L8>=0,"Above avg - favourable","Below avg - unfavourable"),IF(O8="Lower",IF(L8<=0,"Below avg - favourable","Above avg - unfavourable"),IF(L8>=0,"Above avg - context-dependent","Below avg - context-dependent"))))&IF(K8<5," (N="&K8&")","") -> Above avg - favourable | R8: =IF(K8=0,"n/m",IF(ABS(J8-SUM(E8:I8)/K8)<0.000000001,"OK","ERR")) -> OK
C9: Current ratio | D9: FY2023 | E9: =KOHC!F138 -> 2.3115705 | F9: =LUCK!F138 -> 1.2900716 | G9: =DGKC!F138 -> 0.80176749 | H9: =MLCF!F138 -> 1.3715472 | I9: =FCCL!F138 -> 0.81211138 | J9: =IF(COUNT(E9:I9)=0,"n/m",AVERAGE(E9:I9)) -> 1.3174136 | K9: =COUNT(E9:I9) -> 5 | L9: =IF(AND(ISNUMBER(E9),ISNUMBER(J9)),E9-J9,"n/m") -> 0.99415687 | M9: =IF(COUNT(F9:I9)=0,"n/m",AVERAGE(F9:I9)) -> 1.0688744 | N9: =IF(COUNT(E9:I9)=0,"n/m",MEDIAN(E9:I9)) -> 1.2900716 | O9: Higher | P9: =IF(NOT(ISNUMBER(L9)),"n/m",IF(O9="Higher",IF(L9>=0,"Above avg - favourable","Below avg - unfavourable"),IF(O9="Lower",IF(L9<=0,"Below avg - favourable","Above avg - unfavourable"),IF(L9>=0,"Above avg - context-dependent","Below avg - context-dependent"))))&IF(K9<5," (N="&K9&")","") -> Above avg - favourable | R9: =IF(K9=0,"n/m",IF(ABS(J9-SUM(E9:I9)/K9)<0.000000001,"OK","ERR")) -> OK
C10: Current ratio | D10: FY2024 | E10: =KOHC!G138 -> 2.9031591 | F10: =LUCK!G138 -> 1.2632222 | G10: =DGKC!G138 -> 1.2961859 | H10: =MLCF!G138 -> 1.4446782 | I10: =FCCL!G138 -> 0.95974773 | J10: =IF(COUNT(E10:I10)=0,"n/m",AVERAGE(E10:I10)) -> 1.5733986 | K10: =COUNT(E10:I10) -> 5 | L10: =IF(AND(ISNUMBER(E10),ISNUMBER(J10)),E10-J10,"n/m") -> 1.3297604 | M10: =IF(COUNT(F10:I10)=0,"n/m",AVERAGE(F10:I10)) -> 1.2409585 | N10: =IF(COUNT(E10:I10)=0,"n/m",MEDIAN(E10:I10)) -> 1.2961859 | O10: Higher | P10: =IF(NOT(ISNUMBER(L10)),"n/m",IF(O10="Higher",IF(L10>=0,"Above avg - favourable","Below avg - unfavourable"),IF(O10="Lower",IF(L10<=0,"Below avg - favourable","Above avg - unfavourable"),IF(L10>=0,"Above avg - context-dependent","Below avg - context-dependent"))))&IF(K10<5," (N="&K10&")","") -> Above avg - favourable | R10: =IF(K10=0,"n/m",IF(ABS(J10-SUM(E10:I10)/K10)<0.000000001,"OK","ERR")) -> OK
C11: Current ratio | D11: FY2025 | E11: =KOHC!H138 -> 3.3112487 | F11: =LUCK!H138 -> 1.7146144 | G11: =DGKC!H138 -> 1.8489518 | H11: =MLCF!H138 -> 1.5324411 | I11: =FCCL!H138 -> 1.3210141 | J11: =IF(COUNT(E11:I11)=0,"n/m",AVERAGE(E11:I11)) -> 1.945654 | K11: =COUNT(E11:I11) -> 5 | L11: =IF(AND(ISNUMBER(E11),ISNUMBER(J11)),E11-J11,"n/m") -> 1.3655947 | M11: =IF(COUNT(F11:I11)=0,"n/m",AVERAGE(F11:I11)) -> 1.6042553 | N11: =IF(COUNT(E11:I11)=0,"n/m",MEDIAN(E11:I11)) -> 1.7146144 | O11: Higher | P11: =IF(NOT(ISNUMBER(L11)),"n/m",IF(O11="Higher",IF(L11>=0,"Above avg - favourable","Below avg - unfavourable"),IF(O11="Lower",IF(L11<=0,"Below avg - favourable","Above avg - unfavourable"),IF(L11>=0,"Above avg - context-dependent","Below avg - context-dependent"))))&IF(K11<5," (N="&K11&")","") -> Above avg - favourable | R11: =IF(K11=0,"n/m",IF(ABS(J11-SUM(E11:I11)/K11)<0.000000001,"OK","ERR")) -> OK
A12: Liquidity | B12: 2 | C12: 2. Quick ratio
C13: Quick ratio | D13: FY2021 | E13: =KOHC!D139 -> 0.74816044 | F13: =LUCK!D139 -> 0.89000886 | G13: =DGKC!D139 -> 0.52718831 | H13: =MLCF!D139 -> 0.43971692 | I13: =FCCL!D139 -> 1.1357988 | J13: =IF(COUNT(E13:I13)=0,"n/m",AVERAGE(E13:I13)) -> 0.74817467 | K13: =COUNT(E13:I13) -> 5 | L13: =IF(AND(ISNUMBER(E13),ISNUMBER(J13)),E13-J13,"n/m") -> -1.4236088e-05 | M13: =IF(COUNT(F13:I13)=0,"n/m",AVERAGE(F13:I13)) -> 0.74817823 | N13: =IF(COUNT(E13:I13)=0,"n/m",MEDIAN(E13:I13)) -> 0.74816044 | O13: Higher | P13: =IF(NOT(ISNUMBER(L13)),"n/m",IF(O13="Higher",IF(L13>=0,"Above avg - favourable","Below avg - unfavourable"),IF(O13="Lower",IF(L13<=0,"Below avg - favourable","Above avg - unfavourable"),IF(L13>=0,"Above avg - context-dependent","Below avg - context-dependent"))))&IF(K13<5," (N="&K13&")","") -> Below avg - unfavourable | R13: =IF(K13=0,"n/m",IF(ABS(J13-SUM(E13:I13)/K13)<0.000000001,"OK","ERR")) -> OK
C14: Quick ratio | D14: FY2022 | E14: =KOHC!E139 -> 1.275807 | F14: =LUCK!E139 -> 0.87076092 | G14: =DGKC!E139 -> 0.39093391 | H14: =MLCF!E139 -> 0.29473524 | I14: =FCCL!E139 -> 0.47078421 | J14: =IF(COUNT(E14:I14)=0,"n/m",AVERAGE(E14:I14)) -> 0.66060426 | K14: =COUNT(E14:I14) -> 5 | L14: =IF(AND(ISNUMBER(E14),ISNUMBER(J14)),E14-J14,"n/m") -> 0.61520275 | M14: =IF(COUNT(F14:I14)=0,"n/m",AVERAGE(F14:I14)) -> 0.50680357 | N14: =IF(COUNT(E14:I14)=0,"n/m",MEDIAN(E14:I14)) -> 0.47078421 | O14: Higher | P14: =IF(NOT(ISNUMBER(L14)),"n/m",IF(O14="Higher",IF(L14>=0,"Above avg - favourable","Below avg - unfavourable"),IF(O14="Lower",IF(L14<=0,"Below avg - favourable","Above avg - unfavourable"),IF(L14>=0,"Above avg - context-dependent","Below avg - context-dependent"))))&IF(K14<5," (N="&K14&")","") -> Above avg - favourable | R14: =IF(K14=0,"n/m",IF(ABS(J14-SUM(E14:I14)/K14)<0.000000001,"OK","ERR")) -> OK
